Workbook
Name Supermercado: Jan!$D$6
Name Janeiro: #REF!
Name A4_: Jan!$D$6

Sheet Jan
C1: Orçamento Doméstico
B2: Descritivo de Receitas e Despesas realizadas | F2: Janeiro | H2: =+'Instruções'!$I$19 -> #REF! | J2: Movimentação do saldo no mês
H3: Meio de pagamento | J3: Saldo do mês anterior
B4: Grupo de conta | C4: Sub-grupo de conta | D4: Cod. | E4: Data | F4: Descritivo | G4: Valor R$ | J4: C.Corrente (+ / -) | K4: Dinheiro (+ / -) | L4: C. de Crédito (+)
A6: 1 | B6: =IF(IF(ISERROR(VLOOKUP(D6,Categorias!$B$4:$C$65,2,FALSE)),"",VLOOKUP(D6,Categorias!$B$4:$C$65,2,FALSE))=D6,"",VLOOKUP(D6,(Categorias!$B$4:$C$65),2,FALSE)) | C6: =IF(IF(ISERROR(VLOOKUP(D6,Categorias!$B$4:$C$65,2,FALSE)),"",VLOOKUP(D6,Categorias!$B$4:$C$65,2,FALSE))=D6,"",VLOOKUP(D6,(Categorias!$B$2:$D$65),3,FALSE)) | J6: =IF(H6="",(""),IF(H6="DP",(J5+G6),IF(H6="DB",(J5-G6),IF(H6="TR",(J5-G6),IF(H6="CH",(J5-G6),IF(H6="SQ",(J5-G6),J5)))))) | K6: =IF(H6="",(""),IF(H6="SQ",(K5+G6),IF(H6="RD",(K5+G6),IF(H6="DI",(K5-G6),K5)))) | L6: =IF(H6="",(""),IF(H6="CC",(L5+G6),IF(H6="PC",(L5+G6),L5)))
B7: =IF(IF(ISERROR(VLOOKUP(D7,Categorias!$B$4:$C$65,2,FALSE)),"",VLOOKUP(D7,Categorias!$B$4:$C$65,2,FALSE))=D7,"",VLOOKUP(D7,(Categorias!$B$4:$C$65),2,FALSE)) | C7: =IF(IF(ISERROR(VLOOKUP(D7,Categorias!$B$4:$C$65,2,FALSE)),"",VLOOKUP(D7,Categorias!$B$4:$C$65,2,FALSE))=D7,"",VLOOKUP(D7,(Categorias!$B$2:$D$65),3,FALSE)) | J7: =IF(H7="",(""),IF(H7="DP",(J6+G7),IF(H7="DB",(J6-G7),IF(H7="TR",(J6-G7),IF(H7="CH",(J6-G7),IF(H7="SQ",(J6-G7),J6)))))) | K7: =IF(H7="",(""),IF(H7="SQ",(K6+G7),IF(H7="RD",(K6+G7),IF(H7="DI",(K6-G7),K6)))) | L7: =IF(H7="",(""),IF(H7="CC",(L6+G7),IF(H7="PC",(L6+G7),L6)))
B8: =IF(IF(ISERROR(VLOOKUP(D8,Categorias!$B$4:$C$65,2,FALSE)),"",VLOOKUP(D8,Categorias!$B$4:$C$65,2,FALSE))=D8,"",VLOOKUP(D8,(Categorias!$B$4:$C$65),2,FALSE)) | C8: =IF(IF(ISERROR(VLOOKUP(D8,Categorias!$B$4:$C$65,2,FALSE)),"",VLOOKUP(D8,Categorias!$B$4:$C$65,2,FALSE))=D8,"",VLOOKUP(D8,(Categorias!$B$2:$D$65),3,FALSE)) | J8: =IF(H8="",(""),IF(H8="DP",(J7+G8),IF(H8="DB",(J7-G8),IF(H8="TR",(J7-G8),IF(H8="CH",(J7-G8),IF(H8="SQ",(J7-G8),J7)))))) | K8: =IF(H8="",(""),IF(H8="SQ",(K7+G8),IF(H8="RD",(K7+G8),IF(H8="DI",(K7-G8),K7)))) | L8: =IF(H8="",(""),IF(H8="CC",(L7+G8),IF(H8="PC",(L7+G8),L7)))
B9: =IF(IF(ISERROR(VLOOKUP(D9,Categorias!$B$4:$C$65,2,FALSE)),"",VLOOKUP(D9,Categorias!$B$4:$C$65,2,FALSE))=D9,"",VLOOKUP(D9,(Categorias!$B$4:$C$65),2,FALSE)) | C9: =IF(IF(ISERROR(VLOOKUP(D9,Categorias!$B$4:$C$65,2,FALSE)),"",VLOOKUP(D9,Categorias!$B$4:$C$65,2,FALSE))=D9,"",VLOOKUP(D9,(Categorias!$B$2:$D$65),3,FALSE)) | J9: =IF(H9="",(""),IF(H9="DP",(J8+G9),IF(H9="DB",(J8-G9),IF(H9="TR",(J8-G9),IF(H9="CH",(J8-G9),IF(H9="SQ",(J8-G9),J8)))))) | K9: =IF(H9="",(""),IF(H9="SQ",(K8+G9),IF(H9="RD",(K8+G9),IF(H9="DI",(K8-G9),K8)))) | L9: =IF(H9="",(""),IF(H9="CC",(L8+G9),IF(H9="PC",(L8+G9),L8)))
B10: =IF(IF(ISERROR(VLOOKUP(D10,Categorias!$B$4:$C$65,2,FALSE)),"",VLOOKUP(D10,Categorias!$B$4:$C$65,2,FALSE))=D10,"",VLOOKUP(D10,(Categorias!$B$4:$C$65),2,FALSE)) | C10: =IF(IF(ISERROR(VLOOKUP(D10,Categorias!$B$4:$C$65,2,FALSE)),"",VLOOKUP(D10,Categorias!$B$4:$C$65,2,FALSE))=D10,"",VLOOKUP(D10,(Categorias!$B$2:$D$65),3,FALSE)) | J10: =IF(H10="",(""),IF(H10="DP",(J9+G10),IF(H10="DB",(J9-G10),IF(H10="TR",(J9-G10),IF(H10="CH",(J9-G10),IF(H10="SQ",(J9-G10),J9)))))) | K10: =IF(H10="",(""),IF(H10="SQ",(K9+G10),IF(H10="RD",(K9+G10),IF(H10="DI",(K9-G10),K9)))) | L10: =IF(H10="",(""),IF(H10="CC",(L9+G10),IF(H10="PC",(L9+G10),L9)))
B11: =IF(IF(ISERROR(VLOOKUP(D11,Categorias!$B$4:$C$65,2,FALSE)),"",VLOOKUP(D11,Categorias!$B$4:$C$65,2,FALSE))=D11,"",VLOOKUP(D11,(Categorias!$B$4:$C$65),2,FALSE)) | C11: =IF(IF(ISERROR(VLOOKUP(D11,Categorias!$B$4:$C$65,2,FALSE)),"",VLOOKUP(D11,Categorias!$B$4:$C$65,2,FALSE))=D11,"",VLOOKUP(D11,(Categorias!$B$2:$D$65),3,FALSE)) | J11: =IF(H11="",(""),IF(H11="DP",(J10+G11),IF(H11="DB",(J10-G11),IF(H11="TR",(J10-G11),IF(H11="CH",(J10-G11),IF(H11="SQ",(J10-G11),J10)))))) | K11: =IF(H11="",(""),IF(H11="SQ",(K10+G11),IF(H11="RD",(K10+G11),IF(H11="DI",(K10-G11),K10)))) | L11: =IF(H11="",(""),IF(H11="CC",(L10+G11),IF(H11="PC",(L10+G11),L10)))
B12: =IF(IF(ISERROR(VLOOKUP(D12,Categorias!$B$4:$C$65,2,FALSE)),"",VLOOKUP(D12,Categorias!$B$4:$C$65,2,FALSE))=D12,"",VLOOKUP(D12,(Categorias!$B$4:$C$65),2,FALSE)) | C12: =IF(IF(ISERROR(VLOOKUP(D12,Categorias!$B$4:$C$65,2,FALSE)),"",VLOOKUP(D12,Categorias!$B$4:$C$65,2,FALSE))=D12,"",VLOOKUP(D12,(Categorias!$B$2:$D$65),3,FALSE)) | J12: =IF(H12="",(""),IF(H12="DP",(J11+G12),IF(H12="DB",(J11-G12),IF(H12="TR",(J11-G12),IF(H12="CH",(J11-G12),IF(H12="SQ",(J11-G12),J11)))))) | K12: =IF(H12="",(""),IF(H12="SQ",(K11+G12),IF(H12="RD",(K11+G12),IF(H12="DI",(K11-G12),K11)))) | L12: =IF(H12="",(""),IF(H12="CC",(L11+G12),IF(H12="PC",(L11+G12),L11)))
B13: =IF(IF(ISERROR(VLOOKUP(D13,Categorias!$B$4:$C$65,2,FALSE)),"",VLOOKUP(D13,Categorias!$B$4:$C$65,2,FALSE))=D13,"",VLOOKUP(D13,(Categorias!$B$4:$C$65),2,FALSE)) | C13: =IF(IF(ISERROR(VLOOKUP(D13,Categorias!$B$4:$C$65,2,FALSE)),"",VLOOKUP(D13,Categorias!$B$4:$C$65,2,FALSE))=D13,"",VLOOKUP(D13,(Categorias!$B$2:$D$65),3,FALSE)) | J13: =IF(H13="",(""),IF(H13="DP",(J12+G13),IF(H13="DB",(J12-G13),IF(H13="TR",(J12-G13),IF(H13="CH",(J12-G13),IF(H13="SQ",(J12-G13),J12)))))) | K13: =IF(H13="",(""),IF(H13="SQ",(K12+G13),IF(H13="RD",(K12+G13),IF(H13="DI",(K12-G13),K12)))) | L13: =IF(H13="",(""),IF(H13="CC",(L12+G13),IF(H13="PC",(L12+G13),L12)))
B14: =IF(IF(ISERROR(VLOOKUP(D14,Categorias!$B$4:$C$65,2,FALSE)),"",VLOOKUP(D14,Categorias!$B$4:$C$65,2,FALSE))=D14,"",VLOOKUP(D14,(Categorias!$B$4:$C$65),2,FALSE)) | C14: =IF(IF(ISERROR(VLOOKUP(D14,Categorias!$B$4:$C$65,2,FALSE)),"",VLOOKUP(D14,Categorias!$B$4:$C$65,2,FALSE))=D14,"",VLOOKUP(D14,(Categorias!$B$2:$D$65),3,FALSE)) | J14: =IF(H14="",(""),IF(H14="DP",(J13+G14),IF(H14="DB",(J13-G14),IF(H14="TR",(J13-G14),IF(H14="CH",(J13-G14),IF(H14="SQ",(J13-G14),J13)))))) | K14: =IF(H14="",(""),IF(H14="SQ",(K13+G14),IF(H14="RD",(K13+G14),IF(H14="DI",(K13-G14),K13)))) | L14: =IF(H14="",(""),IF(H14="CC",(L13+G14),IF(H14="PC",(L13+G14),L13)))
B15: =IF(IF(ISERROR(VLOOKUP(D15,Categorias!$B$4:$C$65,2,FALSE)),"",VLOOKUP(D15,Categorias!$B$4:$C$65,2,FALSE))=D15,"",VLOOKUP(D15,(Categorias!$B$4:$C$65),2,FALSE)) | C15: =IF(IF(ISERROR(VLOOKUP(D15,Categorias!$B$4:$C$65,2,FALSE)),"",VLOOKUP(D15,Categorias!$B$4:$C$65,2,FALSE))=D15,"",VLOOKUP(D15,(Categorias!$B$2:$D$65),3,FALSE)) | J15: =IF(H15="",(""),IF(H15="DP",(J14+G15),IF(H15="DB",(J14-G15),IF(H15="TR",(J14-G15),IF(H15="CH",(J14-G15),IF(H15="SQ",(J14-G15),J14)))))) | K15: =IF(H15="",(""),IF(H15="SQ",(K14+G15),IF(H15="RD",(K14+G15),IF(H15="DI",(K14-G15),K14)))) | L15: =IF(H15="",(""),IF(H15="CC",(L14+G15),IF(H15="PC",(L14+G15),L14)))
B16: =IF(IF(ISERROR(VLOOKUP(D16,Categorias!$B$4:$C$65,2,FALSE)),"",VLOOKUP(D16,Categorias!$B$4:$C$65,2,FALSE))=D16,"",VLOOKUP(D16,(Categorias!$B$4:$C$65),2,FALSE)) | C16: =IF(IF(ISERROR(VLOOKUP(D16,Categorias!$B$4:$C$65,2,FALSE)),"",VLOOKUP(D16,Categorias!$B$4:$C$65,2,FALSE))=D16,"",VLOOKUP(D16,(Categorias!$B$2:$D$65),3,FALSE)) | J16: =IF(H16="",(""),IF(H16="DP",(J15+G16),IF(H16="DB",(J15-G16),IF(H16="TR",(J15-G16),IF(H16="CH",(J15-G16),IF(H16="SQ",(J15-G16),J15)))))) | K16: =IF(H16="",(""),IF(H16="SQ",(K15+G16),IF(H16="RD",(K15+G16),IF(H16="DI",(K15-G16),K15)))) | L16: =IF(H16="",(""),IF(H16="CC",(L15+G16),IF(H16="PC",(L15+G16),L15)))
B17: =IF(IF(ISERROR(VLOOKUP(D17,Categorias!$B$4:$C$65,2,FALSE)),"",VLOOKUP(D17,Categorias!$B$4:$C$65,2,FALSE))=D17,"",VLOOKUP(D17,(Categorias!$B$4:$C$65),2,FALSE)) | C17: =IF(IF(ISERROR(VLOOKUP(D17,Categorias!$B$4:$C$65,2,FALSE)),"",VLOOKUP(D17,Categorias!$B$4:$C$65,2,FALSE))=D17,"",VLOOKUP(D17,(Categorias!$B$2:$D$65),3,FALSE)) | J17: =IF(H17="",(""),IF(H17="DP",(J16+G17),IF(H17="DB",(J16-G17),IF(H17="TR",(J16-G17),IF(H17="CH",(J16-G17),IF(H17="SQ",(J16-G17),J16)))))) | K17: =IF(H17="",(""),IF(H17="SQ",(K16+G17),IF(H17="RD",(K16+G17),IF(H17="DI",(K16-G17),K16)))) | L17: =IF(H17="",(""),IF(H17="CC",(L16+G17),IF(H17="PC",(L16+G17),L16)))
B18: =IF(IF(ISERROR(VLOOKUP(D18,Categorias!$B$4:$C$65,2,FALSE)),"",VLOOKUP(D18,Categorias!$B$4:$C$65,2,FALSE))=D18,"",VLOOKUP(D18,(Categorias!$B$4:$C$65),2,FALSE)) | C18: =IF(IF(ISERROR(VLOOKUP(D18,Categorias!$B$4:$C$65,2,FALSE)),"",VLOOKUP(D18,Categorias!$B$4:$C$65,2,FALSE))=D18,"",VLOOKUP(D18,(Categorias!$B$2:$D$65),3,FALSE)) | J18: =IF(H18="",(""),IF(H18="DP",(J17+G18),IF(H18="DB",(J17-G18),IF(H18="TR",(J17-G18),IF(H18="CH",(J17-G18),IF(H18="SQ",(J17-G18),J17)))))) | K18: =IF(H18="",(""),IF(H18="SQ",(K17+G18),IF(H18="RD",(K17+G18),IF(H18="DI",(K17-G18),K17)))) | L18: =IF(H18="",(""),IF(H18="CC",(L17+G18),IF(H18="PC",(L17+G18),L17)))
... B75: =IF(IF(ISERROR(VLOOKUP(D75,Categorias!$B$4:$C$65,2,FALSE)),"",VLOOKUP(D75,Categorias!$B$4:$C$65,2,FALSE))=D75,"",VLOOKUP(D75,(Categorias!$B$4:$C$65),2,FALSE)) | C75: =IF(IF(ISERROR(VLOOKUP(D75,Categorias!$B$4:$C$65,2,FALSE)),"",VLOOKUP(D75,Categorias!$B$4:$C$65,2,FALSE))=D75,"",VLOOKUP(D75,(Categorias!$B$2:$D$65),3,FALSE)) | J75: =IF(H75="",(""),IF(H75="DP",(J74+G75),IF(H75="DB",(J74-G75),IF(H75="TR",(J74-G75),IF(H75="CH",(J74-G75),IF(H75="SQ",(J74-G75),J74)))))) | K75: =IF(H75="",(""),IF(H75="SQ",(K74+G75),IF(H75="RD",(K74+G75),IF(H75="DI",(K74-G75),K74)))) | L75: =IF(H75="",(""),IF(H75="CC",(L74+G75),IF(H75="PC",(L74+G75),L74)))
F76: Saldo no mês | J76: =+J75 | K76: =+K75 | L76: =+L75
A213: 1
A214: 1

Sheet Fev
C1: Orçamento Doméstico
B2: Descritivo de Receitas e Despesas realizadas | F2: Fevereiro | H2: =+'Instruções'!$I$19 -> #REF! | J2: Movimentação do saldo no mês
H3: Meio de pagamento | J3: Saldo do mês anterior
B4: Grupo de conta | C4: Sub-grupo de conta | D4: Cod. | E4: Data | F4: Descritivo | G4: Valor R$ | J4: C.Corrente (+ / -) | K4: Dinheiro (+ / -) | L4: C. de Crédito (+)
A6: 1 | B6: =IF(IF(ISERROR(VLOOKUP(D6,Categorias!$B$4:$C$65,2,FALSE)),"",VLOOKUP(D6,Categorias!$B$4:$C$65,2,FALSE))=D6,"",VLOOKUP(D6,(Categorias!$B$4:$C$65),2,FALSE)) | C6: =IF(IF(ISERROR(VLOOKUP(D6,Categorias!$B$4:$C$65,2,FALSE)),"",VLOOKUP(D6,Categorias!$B$4:$C$65,2,FALSE))=D6,"",VLOOKUP(D6,(Categorias!$B$2:$D$65),3,FALSE)) | J6: =IF(H6="",(""),IF(H6="DP",(J5+G6),IF(H6="DB",(J5-G6),IF(H6="TR",(J5-G6),IF(H6="CH",(J5-G6),IF(H6="SQ",(J5-G6),J5)))))) | K6: =IF(H6="",(""),IF(H6="SQ",(K5+G6),IF(H6="RD",(K5+G6),IF(H6="DI",(K5-G6),K5)))) | L6: =IF(H6="",(""),IF(H6="CC",(L5+G6),IF(H6="PC",(L5+G6),L5)))
B7: =IF(IF(ISERROR(VLOOKUP(D7,Categorias!$B$4:$C$65,2,FALSE)),"",VLOOKUP(D7,Categorias!$B$4:$C$65,2,FALSE))=D7,"",VLOOKUP(D7,(Categorias!$B$4:$C$65),2,FALSE)) | C7: =IF(IF(ISERROR(VLOOKUP(D7,Categorias!$B$4:$C$65,2,FALSE)),"",VLOOKUP(D7,Categorias!$B$4:$C$65,2,FALSE))=D7,"",VLOOKUP(D7,(Categorias!$B$2:$D$65),3,FALSE)) | J7: =IF(H7="",(""),IF(H7="DP",(J6+G7),IF(H7="DB",(J6-G7),IF(H7="TR",(J6-G7),IF(H7="CH",(J6-G7),IF(H7="SQ",(J6-G7),J6)))))) | K7: =IF(H7="",(""),IF(H7="SQ",(K6+G7),IF(H7="RD",(K6+G7),IF(H7="DI",(K6-G7),K6)))) | L7: =IF(H7="",(""),IF(H7="CC",(L6+G7),IF(H7="PC",(L6+G7),L6)))
B8: =IF(IF(ISERROR(VLOOKUP(D8,Categorias!$B$4:$C$65,2,FALSE)),"",VLOOKUP(D8,Categorias!$B$4:$C$65,2,FALSE))=D8,"",VLOOKUP(D8,(Categorias!$B$4:$C$65),2,FALSE)) | C8: =IF(IF(ISERROR(VLOOKUP(D8,Categorias!$B$4:$C$65,2,FALSE)),"",VLOOKUP(D8,Categorias!$B$4:$C$65,2,FALSE))=D8,"",VLOOKUP(D8,(Categorias!$B$2:$D$65),3,FALSE)) | J8: =IF(H8="",(""),IF(H8="DP",(J7+G8),IF(H8="DB",(J7-G8),IF(H8="TR",(J7-G8),IF(H8="CH",(J7-G8),IF(H8="SQ",(J7-G8),J7)))))) | K8: =IF(H8="",(""),IF(H8="SQ",(K7+G8),IF(H8="RD",(K7+G8),IF(H8="DI",(K7-G8),K7)))) | L8: =IF(H8="",(""),IF(H8="CC",(L7+G8),IF(H8="PC",(L7+G8),L7)))
B9: =IF(IF(ISERROR(VLOOKUP(D9,Categorias!$B$4:$C$65,2,FALSE)),"",VLOOKUP(D9,Categorias!$B$4:$C$65,2,FALSE))=D9,"",VLOOKUP(D9,(Categorias!$B$4:$C$65),2,FALSE)) | C9: =IF(IF(ISERROR(VLOOKUP(D9,Categorias!$B$4:$C$65,2,FALSE)),"",VLOOKUP(D9,Categorias!$B$4:$C$65,2,FALSE))=D9,"",VLOOKUP(D9,(Categorias!$B$2:$D$65),3,FALSE)) | J9: =IF(H9="",(""),IF(H9="DP",(J8+G9),IF(H9="DB",(J8-G9),IF(H9="TR",(J8-G9),IF(H9="CH",(J8-G9),IF(H9="SQ",(J8-G9),J8)))))) | K9: =IF(H9="",(""),IF(H9="SQ",(K8+G9),IF(H9="RD",(K8+G9),IF(H9="DI",(K8-G9),K8)))) | L9: =IF(H9="",(""),IF(H9="CC",(L8+G9),IF(H9="PC",(L8+G9),L8)))
B10: =IF(IF(ISERROR(VLOOKUP(D10,Categorias!$B$4:$C$65,2,FALSE)),"",VLOOKUP(D10,Categorias!$B$4:$C$65,2,FALSE))=D10,"",VLOOKUP(D10,(Categorias!$B$4:$C$65),2,FALSE)) | C10: =IF(IF(ISERROR(VLOOKUP(D10,Categorias!$B$4:$C$65,2,FALSE)),"",VLOOKUP(D10,Categorias!$B$4:$C$65,2,FALSE))=D10,"",VLOOKUP(D10,(Categorias!$B$2:$D$65),3,FALSE)) | J10: =IF(H10="",(""),IF(H10="DP",(J9+G10),IF(H10="DB",(J9-G10),IF(H10="TR",(J9-G10),IF(H10="CH",(J9-G10),IF(H10="SQ",(J9-G10),J9)))))) | K10: =IF(H10="",(""),IF(H10="SQ",(K9+G10),IF(H10="RD",(K9+G10),IF(H10="DI",(K9-G10),K9)))) | L10: =IF(H10="",(""),IF(H10="CC",(L9+G10),IF(H10="PC",(L9+G10),L9)))
B11: =IF(IF(ISERROR(VLOOKUP(D11,Categorias!$B$4:$C$65,2,FALSE)),"",VLOOKUP(D11,Categorias!$B$4:$C$65,2,FALSE))=D11,"",VLOOKUP(D11,(Categorias!$B$4:$C$65),2,FALSE)) | C11: =IF(IF(ISERROR(VLOOKUP(D11,Categorias!$B$4:$C$65,2,FALSE)),"",VLOOKUP(D11,Categorias!$B$4:$C$65,2,FALSE))=D11,"",VLOOKUP(D11,(Categorias!$B$2:$D$65),3,FALSE)) | J11: =IF(H11="",(""),IF(H11="DP",(J10+G11),IF(H11="DB",(J10-G11),IF(H11="TR",(J10-G11),IF(H11="CH",(J10-G11),IF(H11="SQ",(J10-G11),J10)))))) | K11: =IF(H11="",(""),IF(H11="SQ",(K10+G11),IF(H11="RD",(K10+G11),IF(H11="DI",(K10-G11),K10)))) | L11: =IF(H11="",(""),IF(H11="CC",(L10+G11),IF(H11="PC",(L10+G11),L10)))
B12: =IF(IF(ISERROR(VLOOKUP(D12,Categorias!$B$4:$C$65,2,FALSE)),"",VLOOKUP(D12,Categorias!$B$4:$C$65,2,FALSE))=D12,"",VLOOKUP(D12,(Categorias!$B$4:$C$65),2,FALSE)) | C12: =IF(IF(ISERROR(VLOOKUP(D12,Categorias!$B$4:$C$65,2,FALSE)),"",VLOOKUP(D12,Categorias!$B$4:$C$65,2,FALSE))=D12,"",VLOOKUP(D12,(Categorias!$B$2:$D$65),3,FALSE)) | J12: =IF(H12="",(""),IF(H12="DP",(J11+G12),IF(H12="DB",(J11-G12),IF(H12="TR",(J11-G12),IF(H12="CH",(J11-G12),IF(H12="SQ",(J11-G12),J11)))))) | K12: =IF(H12="",(""),IF(H12="SQ",(K11+G12),IF(H12="RD",(K11+G12),IF(H12="DI",(K11-G12),K11)))) | L12: =IF(H12="",(""),IF(H12="CC",(L11+G12),IF(H12="PC",(L11+G12),L11)))
B13: =IF(IF(ISERROR(VLOOKUP(D13,Categorias!$B$4:$C$65,2,FALSE)),"",VLOOKUP(D13,Categorias!$B$4:$C$65,2,FALSE))=D13,"",VLOOKUP(D13,(Categorias!$B$4:$C$65),2,FALSE)) | C13: =IF(IF(ISERROR(VLOOKUP(D13,Categorias!$B$4:$C$65,2,FALSE)),"",VLOOKUP(D13,Categorias!$B$4:$C$65,2,FALSE))=D13,"",VLOOKUP(D13,(Categorias!$B$2:$D$65),3,FALSE)) | J13: =IF(H13="",(""),IF(H13="DP",(J12+G13),IF(H13="DB",(J12-G13),IF(H13="TR",(J12-G13),IF(H13="CH",(J12-G13),IF(H13="SQ",(J12-G13),J12)))))) | K13: =IF(H13="",(""),IF(H13="SQ",(K12+G13),IF(H13="RD",(K12+G13),IF(H13="DI",(K12-G13),K12)))) | L13: =IF(H13="",(""),IF(H13="CC",(L12+G13),IF(H13="PC",(L12+G13),L12)))
B14: =IF(IF(ISERROR(VLOOKUP(D14,Categorias!$B$4:$C$65,2,FALSE)),"",VLOOKUP(D14,Categorias!$B$4:$C$65,2,FALSE))=D14,"",VLOOKUP(D14,(Categorias!$B$4:$C$65),2,FALSE)) | C14: =IF(IF(ISERROR(VLOOKUP(D14,Categorias!$B$4:$C$65,2,FALSE)),"",VLOOKUP(D14,Categorias!$B$4:$C$65,2,FALSE))=D14,"",VLOOKUP(D14,(Categorias!$B$2:$D$65),3,FALSE)) | J14: =IF(H14="",(""),IF(H14="DP",(J13+G14),IF(H14="DB",(J13-G14),IF(H14="TR",(J13-G14),IF(H14="CH",(J13-G14),IF(H14="SQ",(J13-G14),J13)))))) | K14: =IF(H14="",(""),IF(H14="SQ",(K13+G14),IF(H14="RD",(K13+G14),IF(H14="DI",(K13-G14),K13)))) | L14: =IF(H14="",(""),IF(H14="CC",(L13+G14),IF(H14="PC",(L13+G14),L13)))
B15: =IF(IF(ISERROR(VLOOKUP(D15,Categorias!$B$4:$C$65,2,FALSE)),"",VLOOKUP(D15,Categorias!$B$4:$C$65,2,FALSE))=D15,"",VLOOKUP(D15,(Categorias!$B$4:$C$65),2,FALSE)) | C15: =IF(IF(ISERROR(VLOOKUP(D15,Categorias!$B$4:$C$65,2,FALSE)),"",VLOOKUP(D15,Categorias!$B$4:$C$65,2,FALSE))=D15,"",VLOOKUP(D15,(Categorias!$B$2:$D$65),3,FALSE)) | J15: =IF(H15="",(""),IF(H15="DP",(J14+G15),IF(H15="DB",(J14-G15),IF(H15="TR",(J14-G15),IF(H15="CH",(J14-G15),IF(H15="SQ",(J14-G15),J14)))))) | K15: =IF(H15="",(""),IF(H15="SQ",(K14+G15),IF(H15="RD",(K14+G15),IF(H15="DI",(K14-G15),K14)))) | L15: =IF(H15="",(""),IF(H15="CC",(L14+G15),IF(H15="PC",(L14+G15),L14)))
B16: =IF(IF(ISERROR(VLOOKUP(D16,Categorias!$B$4:$C$65,2,FALSE)),"",VLOOKUP(D16,Categorias!$B$4:$C$65,2,FALSE))=D16,"",VLOOKUP(D16,(Categorias!$B$4:$C$65),2,FALSE)) | C16: =IF(IF(ISERROR(VLOOKUP(D16,Categorias!$B$4:$C$65,2,FALSE)),"",VLOOKUP(D16,Categorias!$B$4:$C$65,2,FALSE))=D16,"",VLOOKUP(D16,(Categorias!$B$2:$D$65),3,FALSE)) | J16: =IF(H16="",(""),IF(H16="DP",(J15+G16),IF(H16="DB",(J15-G16),IF(H16="TR",(J15-G16),IF(H16="CH",(J15-G16),IF(H16="SQ",(J15-G16),J15)))))) | K16: =IF(H16="",(""),IF(H16="SQ",(K15+G16),IF(H16="RD",(K15+G16),IF(H16="DI",(K15-G16),K15)))) | L16: =IF(H16="",(""),IF(H16="CC",(L15+G16),IF(H16="PC",(L15+G16),L15)))
B17: =IF(IF(ISERROR(VLOOKUP(D17,Categorias!$B$4:$C$65,2,FALSE)),"",VLOOKUP(D17,Categorias!$B$4:$C$65,2,FALSE))=D17,"",VLOOKUP(D17,(Categorias!$B$4:$C$65),2,FALSE)) | C17: =IF(IF(ISERROR(VLOOKUP(D17,Categorias!$B$4:$C$65,2,FALSE)),"",VLOOKUP(D17,Categorias!$B$4:$C$65,2,FALSE))=D17,"",VLOOKUP(D17,(Categorias!$B$2:$D$65),3,FALSE)) | J17: =IF(H17="",(""),IF(H17="DP",(J16+G17),IF(H17="DB",(J16-G17),IF(H17="TR",(J16-G17),IF(H17="CH",(J16-G17),IF(H17="SQ",(J16-G17),J16)))))) | K17: =IF(H17="",(""),IF(H17="SQ",(K16+G17),IF(H17="RD",(K16+G17),IF(H17="DI",(K16-G17),K16)))) | L17: =IF(H17="",(""),IF(H17="CC",(L16+G17),IF(H17="PC",(L16+G17),L16)))
B18: =IF(IF(ISERROR(VLOOKUP(D18,Categorias!$B$4:$C$65,2,FALSE)),"",VLOOKUP(D18,Categorias!$B$4:$C$65,2,FALSE))=D18,"",VLOOKUP(D18,(Categorias!$B$4:$C$65),2,FALSE)) | C18: =IF(IF(ISERROR(VLOOKUP(D18,Categorias!$B$4:$C$65,2,FALSE)),"",VLOOKUP(D18,Categorias!$B$4:$C$65,2,FALSE))=D18,"",VLOOKUP(D18,(Categorias!$B$2:$D$65),3,FALSE)) | J18: =IF(H18="",(""),IF(H18="DP",(J17+G18),IF(H18="DB",(J17-G18),IF(H18="TR",(J17-G18),IF(H18="CH",(J17-G18),IF(H18="SQ",(J17-G18),J17)))))) | K18: =IF(H18="",(""),IF(H18="SQ",(K17+G18),IF(H18="RD",(K17+G18),IF(H18="DI",(K17-G18),K17)))) | L18: =IF(H18="",(""),IF(H18="CC",(L17+G18),IF(H18="PC",(L17+G18),L17)))
... B75: =IF(IF(ISERROR(VLOOKUP(D75,Categorias!$B$4:$C$65,2,FALSE)),"",VLOOKUP(D75,Categorias!$B$4:$C$65,2,FALSE))=D75,"",VLOOKUP(D75,(Categorias!$B$4:$C$65),2,FALSE)) | C75: =IF(IF(ISERROR(VLOOKUP(D75,Categorias!$B$4:$C$65,2,FALSE)),"",VLOOKUP(D75,Categorias!$B$4:$C$65,2,FALSE))=D75,"",VLOOKUP(D75,(Categorias!$B$2:$D$65),3,FALSE)) | J75: =IF(H75="",(""),IF(H75="DP",(J74+G75),IF(H75="DB",(J74-G75),IF(H75="TR",(J74-G75),IF(H75="CH",(J74-G75),IF(H75="SQ",(J74-G75),J74)))))) | K75: =IF(H75="",(""),IF(H75="SQ",(K74+G75),IF(H75="RD",(K74+G75),IF(H75="DI",(K74-G75),K74)))) | L75: =IF(H75="",(""),IF(H75="CC",(L74+G75),IF(H75="PC",(L74+G75),L74)))
F76: Saldo no mês | J76: =+J75 | K76: =+K75 | L76: =+L75
A213: 1
A214: 1

Sheet Mar
C1: Orçamento Doméstico
B2: Descritivo de Receitas e Despesas realizadas | F2: Março | H2: =+'Instruções'!$I$19 -> #REF! | J2: Movimentação do saldo no mês
H3: Meio de pagamento | J3: Saldo do mês anterior
B4: Grupo de conta | C4: Sub-grupo de conta | D4: Cod. | E4: Data | F4: Descritivo | G4: Valor R$ | J4: C.Corrente (+ / -) | K4: Dinheiro (+ / -) | L4: C. de Crédito (+)
A6: 1 | B6: =IF(IF(ISERROR(VLOOKUP(D6,Categorias!$B$4:$C$65,2,FALSE)),"",VLOOKUP(D6,Categorias!$B$4:$C$65,2,FALSE))=D6,"",VLOOKUP(D6,(Categorias!$B$4:$C$65),2,FALSE)) | C6: =IF(IF(ISERROR(VLOOKUP(D6,Categorias!$B$4:$C$65,2,FALSE)),"",VLOOKUP(D6,Categorias!$B$4:$C$65,2,FALSE))=D6,"",VLOOKUP(D6,(Categorias!$B$2:$D$65),3,FALSE)) | J6: =IF(H6="",(""),IF(H6="DP",(J5+G6),IF(H6="DB",(J5-G6),IF(H6="TR",(J5-G6),IF(H6="CH",(J5-G6),IF(H6="SQ",(J5-G6),J5)))))) | K6: =IF(H6="",(""),IF(H6="SQ",(K5+G6),IF(H6="RD",(K5+G6),IF(H6="DI",(K5-G6),K5)))) | L6: =IF(H6="",(""),IF(H6="CC",(L5+G6),IF(H6="PC",(L5+G6),L5)))
B7: =IF(IF(ISERROR(VLOOKUP(D7,Categorias!$B$4:$C$65,2,FALSE)),"",VLOOKUP(D7,Categorias!$B$4:$C$65,2,FALSE))=D7,"",VLOOKUP(D7,(Categorias!$B$4:$C$65),2,FALSE)) | C7: =IF(IF(ISERROR(VLOOKUP(D7,Categorias!$B$4:$C$65,2,FALSE)),"",VLOOKUP(D7,Categorias!$B$4:$C$65,2,FALSE))=D7,"",VLOOKUP(D7,(Categorias!$B$2:$D$65),3,FALSE)) | J7: =IF(H7="",(""),IF(H7="DP",(J6+G7),IF(H7="DB",(J6-G7),IF(H7="TR",(J6-G7),IF(H7="CH",(J6-G7),IF(H7="SQ",(J6-G7),J6)))))) | K7: =IF(H7="",(""),IF(H7="SQ",(K6+G7),IF(H7="RD",(K6+G7),IF(H7="DI",(K6-G7),K6)))) | L7: =IF(H7="",(""),IF(H7="CC",(L6+G7),IF(H7="PC",(L6+G7),L6)))
B8: =IF(IF(ISERROR(VLOOKUP(D8,Categorias!$B$4:$C$65,2,FALSE)),"",VLOOKUP(D8,Categorias!$B$4:$C$65,2,FALSE))=D8,"",VLOOKUP(D8,(Categorias!$B$4:$C$65),2,FALSE)) | C8: =IF(IF(ISERROR(VLOOKUP(D8,Categorias!$B$4:$C$65,2,FALSE)),"",VLOOKUP(D8,Categorias!$B$4:$C$65,2,FALSE))=D8,"",VLOOKUP(D8,(Categorias!$B$2:$D$65),3,FALSE)) | J8: =IF(H8="",(""),IF(H8="DP",(J7+G8),IF(H8="DB",(J7-G8),IF(H8="TR",(J7-G8),IF(H8="CH",(J7-G8),IF(H8="SQ",(J7-G8),J7)))))) | K8: =IF(H8="",(""),IF(H8="SQ",(K7+G8),IF(H8="RD",(K7+G8),IF(H8="DI",(K7-G8),K7)))) | L8: =IF(H8="",(""),IF(H8="CC",(L7+G8),IF(H8="PC",(L7+G8),L7)))
B9: =IF(IF(ISERROR(VLOOKUP(D9,Categorias!$B$4:$C$65,2,FALSE)),"",VLOOKUP(D9,Categorias!$B$4:$C$65,2,FALSE))=D9,"",VLOOKUP(D9,(Categorias!$B$4:$C$65),2,FALSE)) | C9: =IF(IF(ISERROR(VLOOKUP(D9,Categorias!$B$4:$C$65,2,FALSE)),"",VLOOKUP(D9,Categorias!$B$4:$C$65,2,FALSE))=D9,"",VLOOKUP(D9,(Categorias!$B$2:$D$65),3,FALSE)) | J9: =IF(H9="",(""),IF(H9="DP",(J8+G9),IF(H9="DB",(J8-G9),IF(H9="TR",(J8-G9),IF(H9="CH",(J8-G9),IF(H9="SQ",(J8-G9),J8)))))) | K9: =IF(H9="",(""),IF(H9="SQ",(K8+G9),IF(H9="RD",(K8+G9),IF(H9="DI",(K8-G9),K8)))) | L9: =IF(H9="",(""),IF(H9="CC",(L8+G9),IF(H9="PC",(L8+G9),L8)))
B10: =IF(IF(ISERROR(VLOOKUP(D10,Categorias!$B$4:$C$65,2,FALSE)),"",VLOOKUP(D10,Categorias!$B$4:$C$65,2,FALSE))=D10,"",VLOOKUP(D10,(Categorias!$B$4:$C$65),2,FALSE)) | C10: =IF(IF(ISERROR(VLOOKUP(D10,Categorias!$B$4:$C$65,2,FALSE)),"",VLOOKUP(D10,Categorias!$B$4:$C$65,2,FALSE))=D10,"",VLOOKUP(D10,(Categorias!$B$2:$D$65),3,FALSE)) | J10: =IF(H10="",(""),IF(H10="DP",(J9+G10),IF(H10="DB",(J9-G10),IF(H10="TR",(J9-G10),IF(H10="CH",(J9-G10),IF(H10="SQ",(J9-G10),J9)))))) | K10: =IF(H10="",(""),IF(H10="SQ",(K9+G10),IF(H10="RD",(K9+G10),IF(H10="DI",(K9-G10),K9)))) | L10: =IF(H10="",(""),IF(H10="CC",(L9+G10),IF(H10="PC",(L9+G10),L9)))
B11: =IF(IF(ISERROR(VLOOKUP(D11,Categorias!$B$4:$C$65,2,FALSE)),"",VLOOKUP(D11,Categorias!$B$4:$C$65,2,FALSE))=D11,"",VLOOKUP(D11,(Categorias!$B$4:$C$65),2,FALSE)) | C11: =IF(IF(ISERROR(VLOOKUP(D11,Categorias!$B$4:$C$65,2,FALSE)),"",VLOOKUP(D11,Categorias!$B$4:$C$65,2,FALSE))=D11,"",VLOOKUP(D11,(Categorias!$B$2:$D$65),3,FALSE)) | J11: =IF(H11="",(""),IF(H11="DP",(J10+G11),IF(H11="DB",(J10-G11),IF(H11="TR",(J10-G11),IF(H11="CH",(J10-G11),IF(H11="SQ",(J10-G11),J10)))))) | K11: =IF(H11="",(""),IF(H11="SQ",(K10+G11),IF(H11="RD",(K10+G11),IF(H11="DI",(K10-G11),K10)))) | L11: =IF(H11="",(""),IF(H11="CC",(L10+G11),IF(H11="PC",(L10+G11),L10)))
B12: =IF(IF(ISERROR(VLOOKUP(D12,Categorias!$B$4:$C$65,2,FALSE)),"",VLOOKUP(D12,Categorias!$B$4:$C$65,2,FALSE))=D12,"",VLOOKUP(D12,(Categorias!$B$4:$C$65),2,FALSE)) | C12: =IF(IF(ISERROR(VLOOKUP(D12,Categorias!$B$4:$C$65,2,FALSE)),"",VLOOKUP(D12,Categorias!$B$4:$C$65,2,FALSE))=D12,"",VLOOKUP(D12,(Categorias!$B$2:$D$65),3,FALSE)) | J12: =IF(H12="",(""),IF(H12="DP",(J11+G12),IF(H12="DB",(J11-G12),IF(H12="TR",(J11-G12),IF(H12="CH",(J11-G12),IF(H12="SQ",(J11-G12),J11)))))) | K12: =IF(H12="",(""),IF(H12="SQ",(K11+G12),IF(H12="RD",(K11+G12),IF(H12="DI",(K11-G12),K11)))) | L12: =IF(H12="",(""),IF(H12="CC",(L11+G12),IF(H12="PC",(L11+G12),L11)))
B13: =IF(IF(ISERROR(VLOOKUP(D13,Categorias!$B$4:$C$65,2,FALSE)),"",VLOOKUP(D13,Categorias!$B$4:$C$65,2,FALSE))=D13,"",VLOOKUP(D13,(Categorias!$B$4:$C$65),2,FALSE)) | C13: =IF(IF(ISERROR(VLOOKUP(D13,Categorias!$B$4:$C$65,2,FALSE)),"",VLOOKUP(D13,Categorias!$B$4:$C$65,2,FALSE))=D13,"",VLOOKUP(D13,(Categorias!$B$2:$D$65),3,FALSE)) | J13: =IF(H13="",(""),IF(H13="DP",(J12+G13),IF(H13="DB",(J12-G13),IF(H13="TR",(J12-G13),IF(H13="CH",(J12-G13),IF(H13="SQ",(J12-G13),J12)))))) | K13: =IF(H13="",(""),IF(H13="SQ",(K12+G13),IF(H13="RD",(K12+G13),IF(H13="DI",(K12-G13),K12)))) | L13: =IF(H13="",(""),IF(H13="CC",(L12+G13),IF(H13="PC",(L12+G13),L12)))
B14: =IF(IF(ISERROR(VLOOKUP(D14,Categorias!$B$4:$C$65,2,FALSE)),"",VLOOKUP(D14,Categorias!$B$4:$C$65,2,FALSE))=D14,"",VLOOKUP(D14,(Categorias!$B$4:$C$65),2,FALSE)) | C14: =IF(IF(ISERROR(VLOOKUP(D14,Categorias!$B$4:$C$65,2,FALSE)),"",VLOOKUP(D14,Categorias!$B$4:$C$65,2,FALSE))=D14,"",VLOOKUP(D14,(Categorias!$B$2:$D$65),3,FALSE)) | J14: =IF(H14="",(""),IF(H14="DP",(J13+G14),IF(H14="DB",(J13-G14),IF(H14="TR",(J13-G14),IF(H14="CH",(J13-G14),IF(H14="SQ",(J13-G14),J13)))))) | K14: =IF(H14="",(""),IF(H14="SQ",(K13+G14),IF(H14="RD",(K13+G14),IF(H14="DI",(K13-G14),K13)))) | L14: =IF(H14="",(""),IF(H14="CC",(L13+G14),IF(H14="PC",(L13+G14),L13)))
B15: =IF(IF(ISERROR(VLOOKUP(D15,Categorias!$B$4:$C$65,2,FALSE)),"",VLOOKUP(D15,Categorias!$B$4:$C$65,2,FALSE))=D15,"",VLOOKUP(D15,(Categorias!$B$4:$C$65),2,FALSE)) | C15: =IF(IF(ISERROR(VLOOKUP(D15,Categorias!$B$4:$C$65,2,FALSE)),"",VLOOKUP(D15,Categorias!$B$4:$C$65,2,FALSE))=D15,"",VLOOKUP(D15,(Categorias!$B$2:$D$65),3,FALSE)) | J15: =IF(H15="",(""),IF(H15="DP",(J14+G15),IF(H15="DB",(J14-G15),IF(H15="TR",(J14-G15),IF(H15="CH",(J14-G15),IF(H15="SQ",(J14-G15),J14)))))) | K15: =IF(H15="",(""),IF(H15="SQ",(K14+G15),IF(H15="RD",(K14+G15),IF(H15="DI",(K14-G15),K14)))) | L15: =IF(H15="",(""),IF(H15="CC",(L14+G15),IF(H15="PC",(L14+G15),L14)))
B16: =IF(IF(ISERROR(VLOOKUP(D16,Categorias!$B$4:$C$65,2,FALSE)),"",VLOOKUP(D16,Categorias!$B$4:$C$65,2,FALSE))=D16,"",VLOOKUP(D16,(Categorias!$B$4:$C$65),2,FALSE)) | C16: =IF(IF(ISERROR(VLOOKUP(D16,Categorias!$B$4:$C$65,2,FALSE)),"",VLOOKUP(D16,Categorias!$B$4:$C$65,2,FALSE))=D16,"",VLOOKUP(D16,(Categorias!$B$2:$D$65),3,FALSE)) | J16: =IF(H16="",(""),IF(H16="DP",(J15+G16),IF(H16="DB",(J15-G16),IF(H16="TR",(J15-G16),IF(H16="CH",(J15-G16),IF(H16="SQ",(J15-G16),J15)))))) | K16: =IF(H16="",(""),IF(H16="SQ",(K15+G16),IF(H16="RD",(K15+G16),IF(H16="DI",(K15-G16),K15)))) | L16: =IF(H16="",(""),IF(H16="CC",(L15+G16),IF(H16="PC",(L15+G16),L15)))
B17: =IF(IF(ISERROR(VLOOKUP(D17,Categorias!$B$4:$C$65,2,FALSE)),"",VLOOKUP(D17,Categorias!$B$4:$C$65,2,FALSE))=D17,"",VLOOKUP(D17,(Categorias!$B$4:$C$65),2,FALSE)) | C17: =IF(IF(ISERROR(VLOOKUP(D17,Categorias!$B$4:$C$65,2,FALSE)),"",VLOOKUP(D17,Categorias!$B$4:$C$65,2,FALSE))=D17,"",VLOOKUP(D17,(Categorias!$B$2:$D$65),3,FALSE)) | J17: =IF(H17="",(""),IF(H17="DP",(J16+G17),IF(H17="DB",(J16-G17),IF(H17="TR",(J16-G17),IF(H17="CH",(J16-G17),IF(H17="SQ",(J16-G17),J16)))))) | K17: =IF(H17="",(""),IF(H17="SQ",(K16+G17),IF(H17="RD",(K16+G17),IF(H17="DI",(K16-G17),K16)))) | L17: =IF(H17="",(""),IF(H17="CC",(L16+G17),IF(H17="PC",(L16+G17),L16)))
B18: =IF(IF(ISERROR(VLOOKUP(D18,Categorias!$B$4:$C$65,2,FALSE)),"",VLOOKUP(D18,Categorias!$B$4:$C$65,2,FALSE))=D18,"",VLOOKUP(D18,(Categorias!$B$4:$C$65),2,FALSE)) | C18: =IF(IF(ISERROR(VLOOKUP(D18,Categorias!$B$4:$C$65,2,FALSE)),"",VLOOKUP(D18,Categorias!$B$4:$C$65,2,FALSE))=D18,"",VLOOKUP(D18,(Categorias!$B$2:$D$65),3,FALSE)) | J18: =IF(H18="",(""),IF(H18="DP",(J17+G18),IF(H18="DB",(J17-G18),IF(H18="TR",(J17-G18),IF(H18="CH",(J17-G18),IF(H18="SQ",(J17-G18),J17)))))) | K18: =IF(H18="",(""),IF(H18="SQ",(K17+G18),IF(H18="RD",(K17+G18),IF(H18="DI",(K17-G18),K17)))) | L18: =IF(H18="",(""),IF(H18="CC",(L17+G18),IF(H18="PC",(L17+G18),L17)))
... B75: =IF(IF(ISERROR(VLOOKUP(D75,Categorias!$B$4:$C$65,2,FALSE)),"",VLOOKUP(D75,Categorias!$B$4:$C$65,2,FALSE))=D75,"",VLOOKUP(D75,(Categorias!$B$4:$C$65),2,FALSE)) | C75: =IF(IF(ISERROR(VLOOKUP(D75,Categorias!$B$4:$C$65,2,FALSE)),"",VLOOKUP(D75,Categorias!$B$4:$C$65,2,FALSE))=D75,"",VLOOKUP(D75,(Categorias!$B$2:$D$65),3,FALSE)) | J75: =IF(H75="",(""),IF(H75="DP",(J74+G75),IF(H75="DB",(J74-G75),IF(H75="TR",(J74-G75),IF(H75="CH",(J74-G75),IF(H75="SQ",(J74-G75),J74)))))) | K75: =IF(H75="",(""),IF(H75="SQ",(K74+G75),IF(H75="RD",(K74+G75),IF(H75="DI",(K74-G75),K74)))) | L75: =IF(H75="",(""),IF(H75="CC",(L74+G75),IF(H75="PC",(L74+G75),L74)))
F76: Saldo no mês | J76: =+J75 | K76: =+K75 | L76: =+L75
A213: 1
A214: 1

Sheet Abr
C1: Orçamento Doméstico
B2: Descritivo de Receitas e Despesas realizadas | F2: Abril | H2: =+'Instruções'!$I$19 -> #REF! | J2: Movimentação do saldo no mês
H3: Meio de pagamento | J3: Saldo do mês anterior
B4: Grupo de conta | C4: Sub-grupo de conta | D4: Cod. | E4: Data | F4: Descritivo | G4: Valor R$ | J4: C.Corrente (+ / -) | K4: Dinheiro (+ / -) | L4: C. de Crédito (+)
A6: 1 | B6: =IF(IF(ISERROR(VLOOKUP(D6,Categorias!$B$4:$C$65,2,FALSE)),"",VLOOKUP(D6,Categorias!$B$4:$C$65,2,FALSE))=D6,"",VLOOKUP(D6,(Categorias!$B$4:$C$65),2,FALSE)) | C6: =IF(IF(ISERROR(VLOOKUP(D6,Categorias!$B$4:$C$65,2,FALSE)),"",VLOOKUP(D6,Categorias!$B$4:$C$65,2,FALSE))=D6,"",VLOOKUP(D6,(Categorias!$B$2:$D$65),3,FALSE)) | J6: =IF(H6="",(""),IF(H6="DP",(J5+G6),IF(H6="DB",(J5-G6),IF(H6="TR",(J5-G6),IF(H6="CH",(J5-G6),IF(H6="SQ",(J5-G6),J5)))))) | K6: =IF(H6="",(""),IF(H6="SQ",(K5+G6),IF(H6="RD",(K5+G6),IF(H6="DI",(K5-G6),K5)))) | L6: =IF(H6="",(""),IF(H6="CC",(L5+G6),IF(H6="PC",(L5+G6),L5)))
B7: =IF(IF(ISERROR(VLOOKUP(D7,Categorias!$B$4:$C$65,2,FALSE)),"",VLOOKUP(D7,Categorias!$B$4:$C$65,2,FALSE))=D7,"",VLOOKUP(D7,(Categorias!$B$4:$C$65),2,FALSE)) | C7: =IF(IF(ISERROR(VLOOKUP(D7,Categorias!$B$4:$C$65,2,FALSE)),"",VLOOKUP(D7,Categorias!$B$4:$C$65,2,FALSE))=D7,"",VLOOKUP(D7,(Categorias!$B$2:$D$65),3,FALSE)) | J7: =IF(H7="",(""),IF(H7="DP",(J6+G7),IF(H7="DB",(J6-G7),IF(H7="TR",(J6-G7),IF(H7="CH",(J6-G7),IF(H7="SQ",(J6-G7),J6)))))) | K7: =IF(H7="",(""),IF(H7="SQ",(K6+G7),IF(H7="RD",(K6+G7),IF(H7="DI",(K6-G7),K6)))) | L7: =IF(H7="",(""),IF(H7="CC",(L6+G7),IF(H7="PC",(L6+G7),L6)))
B8: =IF(IF(ISERROR(VLOOKUP(D8,Categorias!$B$4:$C$65,2,FALSE)),"",VLOOKUP(D8,Categorias!$B$4:$C$65,2,FALSE))=D8,"",VLOOKUP(D8,(Categorias!$B$4:$C$65),2,FALSE)) | C8: =IF(IF(ISERROR(VLOOKUP(D8,Categorias!$B$4:$C$65,2,FALSE)),"",VLOOKUP(D8,Categorias!$B$4:$C$65,2,FALSE))=D8,"",VLOOKUP(D8,(Categorias!$B$2:$D$65),3,FALSE)) | J8: =IF(H8="",(""),IF(H8="DP",(J7+G8),IF(H8="DB",(J7-G8),IF(H8="TR",(J7-G8),IF(H8="CH",(J7-G8),IF(H8="SQ",(J7-G8),J7)))))) | K8: =IF(H8="",(""),IF(H8="SQ",(K7+G8),IF(H8="RD",(K7+G8),IF(H8="DI",(K7-G8),K7)))) | L8: =IF(H8="",(""),IF(H8="CC",(L7+G8),IF(H8="PC",(L7+G8),L7)))
B9: =IF(IF(ISERROR(VLOOKUP(D9,Categorias!$B$4:$C$65,2,FALSE)),"",VLOOKUP(D9,Categorias!$B$4:$C$65,2,FALSE))=D9,"",VLOOKUP(D9,(Categorias!$B$4:$C$65),2,FALSE)) | C9: =IF(IF(ISERROR(VLOOKUP(D9,Categorias!$B$4:$C$65,2,FALSE)),"",VLOOKUP(D9,Categorias!$B$4:$C$65,2,FALSE))=D9,"",VLOOKUP(D9,(Categorias!$B$2:$D$65),3,FALSE)) | J9: =IF(H9="",(""),IF(H9="DP",(J8+G9),IF(H9="DB",(J8-G9),IF(H9="TR",(J8-G9),IF(H9="CH",(J8-G9),IF(H9="SQ",(J8-G9),J8)))))) | K9: =IF(H9="",(""),IF(H9="SQ",(K8+G9),IF(H9="RD",(K8+G9),IF(H9="DI",(K8-G9),K8)))) | L9: =IF(H9="",(""),IF(H9="CC",(L8+G9),IF(H9="PC",(L8+G9),L8)))
B10: =IF(IF(ISERROR(VLOOKUP(D10,Categorias!$B$4:$C$65,2,FALSE)),"",VLOOKUP(D10,Categorias!$B$4:$C$65,2,FALSE))=D10,"",VLOOKUP(D10,(Categorias!$B$4:$C$65),2,FALSE)) | C10: =IF(IF(ISERROR(VLOOKUP(D10,Categorias!$B$4:$C$65,2,FALSE)),"",VLOOKUP(D10,Categorias!$B$4:$C$65,2,FALSE))=D10,"",VLOOKUP(D10,(Categorias!$B$2:$D$65),3,FALSE)) | J10: =IF(H10="",(""),IF(H10="DP",(J9+G10),IF(H10="DB",(J9-G10),IF(H10="TR",(J9-G10),IF(H10="CH",(J9-G10),IF(H10="SQ",(J9-G10),J9)))))) | K10: =IF(H10="",(""),IF(H10="SQ",(K9+G10),IF(H10="RD",(K9+G10),IF(H10="DI",(K9-G10),K9)))) | L10: =IF(H10="",(""),IF(H10="CC",(L9+G10),IF(H10="PC",(L9+G10),L9)))
B11: =IF(IF(ISERROR(VLOOKUP(D11,Categorias!$B$4:$C$65,2,FALSE)),"",VLOOKUP(D11,Categorias!$B$4:$C$65,2,FALSE))=D11,"",VLOOKUP(D11,(Categorias!$B$4:$C$65),2,FALSE)) | C11: =IF(IF(ISERROR(VLOOKUP(D11,Categorias!$B$4:$C$65,2,FALSE)),"",VLOOKUP(D11,Categorias!$B$4:$C$65,2,FALSE))=D11,"",VLOOKUP(D11,(Categorias!$B$2:$D$65),3,FALSE)) | J11: =IF(H11="",(""),IF(H11="DP",(J10+G11),IF(H11="DB",(J10-G11),IF(H11="TR",(J10-G11),IF(H11="CH",(J10-G11),IF(H11="SQ",(J10-G11),J10)))))) | K11: =IF(H11="",(""),IF(H11="SQ",(K10+G11),IF(H11="RD",(K10+G11),IF(H11="DI",(K10-G11),K10)))) | L11: =IF(H11="",(""),IF(H11="CC",(L10+G11),IF(H11="PC",(L10+G11),L10)))
B12: =IF(IF(ISERROR(VLOOKUP(D12,Categorias!$B$4:$C$65,2,FALSE)),"",VLOOKUP(D12,Categorias!$B$4:$C$65,2,FALSE))=D12,"",VLOOKUP(D12,(Categorias!$B$4:$C$65),2,FALSE)) | C12: =IF(IF(ISERROR(VLOOKUP(D12,Categorias!$B$4:$C$65,2,FALSE)),"",VLOOKUP(D12,Categorias!$B$4:$C$65,2,FALSE))=D12,"",VLOOKUP(D12,(Categorias!$B$2:$D$65),3,FALSE)) | J12: =IF(H12="",(""),IF(H12="DP",(J11+G12),IF(H12="DB",(J11-G12),IF(H12="TR",(J11-G12),IF(H12="CH",(J11-G12),IF(H12="SQ",(J11-G12),J11)))))) | K12: =IF(H12="",(""),IF(H12="SQ",(K11+G12),IF(H12="RD",(K11+G12),IF(H12="DI",(K11-G12),K11)))) | L12: =IF(H12="",(""),IF(H12="CC",(L11+G12),IF(H12="PC",(L11+G12),L11)))
B13: =IF(IF(ISERROR(VLOOKUP(D13,Categorias!$B$4:$C$65,2,FALSE)),"",VLOOKUP(D13,Categorias!$B$4:$C$65,2,FALSE))=D13,"",VLOOKUP(D13,(Categorias!$B$4:$C$65),2,FALSE)) | C13: =IF(IF(ISERROR(VLOOKUP(D13,Categorias!$B$4:$C$65,2,FALSE)),"",VLOOKUP(D13,Categorias!$B$4:$C$65,2,FALSE))=D13,"",VLOOKUP(D13,(Categorias!$B$2:$D$65),3,FALSE)) | J13: =IF(H13="",(""),IF(H13="DP",(J12+G13),IF(H13="DB",(J12-G13),IF(H13="TR",(J12-G13),IF(H13="CH",(J12-G13),IF(H13="SQ",(J12-G13),J12)))))) | K13: =IF(H13="",(""),IF(H13="SQ",(K12+G13),IF(H13="RD",(K12+G13),IF(H13="DI",(K12-G13),K12)))) | L13: =IF(H13="",(""),IF(H13="CC",(L12+G13),IF(H13="PC",(L12+G13),L12)))
B14: =IF(IF(ISERROR(VLOOKUP(D14,Categorias!$B$4:$C$65,2,FALSE)),"",VLOOKUP(D14,Categorias!$B$4:$C$65,2,FALSE))=D14,"",VLOOKUP(D14,(Categorias!$B$4:$C$65),2,FALSE)) | C14: =IF(IF(ISERROR(VLOOKUP(D14,Categorias!$B$4:$C$65,2,FALSE)),"",VLOOKUP(D14,Categorias!$B$4:$C$65,2,FALSE))=D14,"",VLOOKUP(D14,(Categorias!$B$2:$D$65),3,FALSE)) | J14: =IF(H14="",(""),IF(H14="DP",(J13+G14),IF(H14="DB",(J13-G14),IF(H14="TR",(J13-G14),IF(H14="CH",(J13-G14),IF(H14="SQ",(J13-G14),J13)))))) | K14: =IF(H14="",(""),IF(H14="SQ",(K13+G14),IF(H14="RD",(K13+G14),IF(H14="DI",(K13-G14),K13)))) | L14: =IF(H14="",(""),IF(H14="CC",(L13+G14),IF(H14="PC",(L13+G14),L13)))
B15: =IF(IF(ISERROR(VLOOKUP(D15,Categorias!$B$4:$C$65,2,FALSE)),"",VLOOKUP(D15,Categorias!$B$4:$C$65,2,FALSE))=D15,"",VLOOKUP(D15,(Categorias!$B$4:$C$65),2,FALSE)) | C15: =IF(IF(ISERROR(VLOOKUP(D15,Categorias!$B$4:$C$65,2,FALSE)),"",VLOOKUP(D15,Categorias!$B$4:$C$65,2,FALSE))=D15,"",VLOOKUP(D15,(Categorias!$B$2:$D$65),3,FALSE)) | J15: =IF(H15="",(""),IF(H15="DP",(J14+G15),IF(H15="DB",(J14-G15),IF(H15="TR",(J14-G15),IF(H15="CH",(J14-G15),IF(H15="SQ",(J14-G15),J14)))))) | K15: =IF(H15="",(""),IF(H15="SQ",(K14+G15),IF(H15="RD",(K14+G15),IF(H15="DI",(K14-G15),K14)))) | L15: =IF(H15="",(""),IF(H15="CC",(L14+G15),IF(H15="PC",(L14+G15),L14)))
B16: =IF(IF(ISERROR(VLOOKUP(D16,Categorias!$B$4:$C$65,2,FALSE)),"",VLOOKUP(D16,Categorias!$B$4:$C$65,2,FALSE))=D16,"",VLOOKUP(D16,(Categorias!$B$4:$C$65),2,FALSE)) | C16: =IF(IF(ISERROR(VLOOKUP(D16,Categorias!$B$4:$C$65,2,FALSE)),"",VLOOKUP(D16,Categorias!$B$4:$C$65,2,FALSE))=D16,"",VLOOKUP(D16,(Categorias!$B$2:$D$65),3,FALSE)) | J16: =IF(H16="",(""),IF(H16="DP",(J15+G16),IF(H16="DB",(J15-G16),IF(H16="TR",(J15-G16),IF(H16="CH",(J15-G16),IF(H16="SQ",(J15-G16),J15)))))) | K16: =IF(H16="",(""),IF(H16="SQ",(K15+G16),IF(H16="RD",(K15+G16),IF(H16="DI",(K15-G16),K15)))) | L16: =IF(H16="",(""),IF(H16="CC",(L15+G16),IF(H16="PC",(L15+G16),L15)))
B17: =IF(IF(ISERROR(VLOOKUP(D17,Categorias!$B$4:$C$65,2,FALSE)),"",VLOOKUP(D17,Categorias!$B$4:$C$65,2,FALSE))=D17,"",VLOOKUP(D17,(Categorias!$B$4:$C$65),2,FALSE)) | C17: =IF(IF(ISERROR(VLOOKUP(D17,Categorias!$B$4:$C$65,2,FALSE)),"",VLOOKUP(D17,Categorias!$B$4:$C$65,2,FALSE))=D17,"",VLOOKUP(D17,(Categorias!$B$2:$D$65),3,FALSE)) | J17: =IF(H17="",(""),IF(H17="DP",(J16+G17),IF(H17="DB",(J16-G17),IF(H17="TR",(J16-G17),IF(H17="CH",(J16-G17),IF(H17="SQ",(J16-G17),J16)))))) | K17: =IF(H17="",(""),IF(H17="SQ",(K16+G17),IF(H17="RD",(K16+G17),IF(H17="DI",(K16-G17),K16)))) | L17: =IF(H17="",(""),IF(H17="CC",(L16+G17),IF(H17="PC",(L16+G17),L16)))
B18: =IF(IF(ISERROR(VLOOKUP(D18,Categorias!$B$4:$C$65,2,FALSE)),"",VLOOKUP(D18,Categorias!$B$4:$C$65,2,FALSE))=D18,"",VLOOKUP(D18,(Categorias!$B$4:$C$65),2,FALSE)) | C18: =IF(IF(ISERROR(VLOOKUP(D18,Categorias!$B$4:$C$65,2,FALSE)),"",VLOOKUP(D18,Categorias!$B$4:$C$65,2,FALSE))=D18,"",VLOOKUP(D18,(Categorias!$B$2:$D$65),3,FALSE)) | J18: =IF(H18="",(""),IF(H18="DP",(J17+G18),IF(H18="DB",(J17-G18),IF(H18="TR",(J17-G18),IF(H18="CH",(J17-G18),IF(H18="SQ",(J17-G18),J17)))))) | K18: =IF(H18="",(""),IF(H18="SQ",(K17+G18),IF(H18="RD",(K17+G18),IF(H18="DI",(K17-G18),K17)))) | L18: =IF(H18="",(""),IF(H18="CC",(L17+G18),IF(H18="PC",(L17+G18),L17)))
... B75: =IF(IF(ISERROR(VLOOKUP(D75,Categorias!$B$4:$C$65,2,FALSE)),"",VLOOKUP(D75,Categorias!$B$4:$C$65,2,FALSE))=D75,"",VLOOKUP(D75,(Categorias!$B$4:$C$65),2,FALSE)) | C75: =IF(IF(ISERROR(VLOOKUP(D75,Categorias!$B$4:$C$65,2,FALSE)),"",VLOOKUP(D75,Categorias!$B$4:$C$65,2,FALSE))=D75,"",VLOOKUP(D75,(Categorias!$B$2:$D$65),3,FALSE)) | J75: =IF(H75="",(""),IF(H75="DP",(J74+G75),IF(H75="DB",(J74-G75),IF(H75="TR",(J74-G75),IF(H75="CH",(J74-G75),IF(H75="SQ",(J74-G75),J74)))))) | K75: =IF(H75="",(""),IF(H75="SQ",(K74+G75),IF(H75="RD",(K74+G75),IF(H75="DI",(K74-G75),K74)))) | L75: =IF(H75="",(""),IF(H75="CC",(L74+G75),IF(H75="PC",(L74+G75),L74)))
F76: Saldo no mês | J76: =+J75 | K76: =+K75 | L76: =+L75
A213: 1
A214: 1

Sheet Mai
C1: Orçamento Doméstico
B2: Descritivo de Receitas e Despesas realizadas | F2: Maio | H2: =+'Instruções'!$I$19 -> #REF! | J2: Movimentação do saldo no mês
H3: Meio de pagamento | J3: Saldo do mês anterior
B4: Grupo de conta | C4: Sub-grupo de conta | D4: Cod. | E4: Data | F4: Descritivo | G4: Valor R$ | J4: C.Corrente (+ / -) | K4: Dinheiro (+ / -) | L4: C. de Crédito (+)
A6: 1 | B6: =IF(IF(ISERROR(VLOOKUP(D6,Categorias!$B$4:$C$65,2,FALSE)),"",VLOOKUP(D6,Categorias!$B$4:$C$65,2,FALSE))=D6,"",VLOOKUP(D6,(Categorias!$B$4:$C$65),2,FALSE)) | C6: =IF(IF(ISERROR(VLOOKUP(D6,Categorias!$B$4:$C$65,2,FALSE)),"",VLOOKUP(D6,Categorias!$B$4:$C$65,2,FALSE))=D6,"",VLOOKUP(D6,(Categorias!$B$2:$D$65),3,FALSE)) | J6: =IF(H6="",(""),IF(H6="DP",(J5+G6),IF(H6="DB",(J5-G6),IF(H6="TR",(J5-G6),IF(H6="CH",(J5-G6),IF(H6="SQ",(J5-G6),J5)))))) | K6: =IF(H6="",(""),IF(H6="SQ",(K5+G6),IF(H6="RD",(K5+G6),IF(H6="DI",(K5-G6),K5)))) | L6: =IF(H6="",(""),IF(H6="CC",(L5+G6),IF(H6="PC",(L5+G6),L5)))
B7: =IF(IF(ISERROR(VLOOKUP(D7,Categorias!$B$4:$C$65,2,FALSE)),"",VLOOKUP(D7,Categorias!$B$4:$C$65,2,FALSE))=D7,"",VLOOKUP(D7,(Categorias!$B$4:$C$65),2,FALSE)) | C7: =IF(IF(ISERROR(VLOOKUP(D7,Categorias!$B$4:$C$65,2,FALSE)),"",VLOOKUP(D7,Categorias!$B$4:$C$65,2,FALSE))=D7,"",VLOOKUP(D7,(Categorias!$B$2:$D$65),3,FALSE)) | J7: =IF(H7="",(""),IF(H7="DP",(J6+G7),IF(H7="DB",(J6-G7),IF(H7="TR",(J6-G7),IF(H7="CH",(J6-G7),IF(H7="SQ",(J6-G7),J6)))))) | K7: =IF(H7="",(""),IF(H7="SQ",(K6+G7),IF(H7="RD",(K6+G7),IF(H7="DI",(K6-G7),K6)))) | L7: =IF(H7="",(""),IF(H7="CC",(L6+G7),IF(H7="PC",(L6+G7),L6)))
B8: =IF(IF(ISERROR(VLOOKUP(D8,Categorias!$B$4:$C$65,2,FALSE)),"",VLOOKUP(D8,Categorias!$B$4:$C$65,2,FALSE))=D8,"",VLOOKUP(D8,(Categorias!$B$4:$C$65),2,FALSE)) | C8: =IF(IF(ISERROR(VLOOKUP(D8,Categorias!$B$4:$C$65,2,FALSE)),"",VLOOKUP(D8,Categorias!$B$4:$C$65,2,FALSE))=D8,"",VLOOKUP(D8,(Categorias!$B$2:$D$65),3,FALSE)) | J8: =IF(H8="",(""),IF(H8="DP",(J7+G8),IF(H8="DB",(J7-G8),IF(H8="TR",(J7-G8),IF(H8="CH",(J7-G8),IF(H8="SQ",(J7-G8),J7)))))) | K8: =IF(H8="",(""),IF(H8="SQ",(K7+G8),IF(H8="RD",(K7+G8),IF(H8="DI",(K7-G8),K7)))) | L8: =IF(H8="",(""),IF(H8="CC",(L7+G8),IF(H8="PC",(L7+G8),L7)))
B9: =IF(IF(ISERROR(VLOOKUP(D9,Categorias!$B$4:$C$65,2,FALSE)),"",VLOOKUP(D9,Categorias!$B$4:$C$65,2,FALSE))=D9,"",VLOOKUP(D9,(Categorias!$B$4:$C$65),2,FALSE)) | C9: =IF(IF(ISERROR(VLOOKUP(D9,Categorias!$B$4:$C$65,2,FALSE)),"",VLOOKUP(D9,Categorias!$B$4:$C$65,2,FALSE))=D9,"",VLOOKUP(D9,(Categorias!$B$2:$D$65),3,FALSE)) | J9: =IF(H9="",(""),IF(H9="DP",(J8+G9),IF(H9="DB",(J8-G9),IF(H9="TR",(J8-G9),IF(H9="CH",(J8-G9),IF(H9="SQ",(J8-G9),J8)))))) | K9: =IF(H9="",(""),IF(H9="SQ",(K8+G9),IF(H9="RD",(K8+G9),IF(H9="DI",(K8-G9),K8)))) | L9: =IF(H9="",(""),IF(H9="CC",(L8+G9),IF(H9="PC",(L8+G9),L8)))
B10: =IF(IF(ISERROR(VLOOKUP(D10,Categorias!$B$4:$C$65,2,FALSE)),"",VLOOKUP(D10,Categorias!$B$4:$C$65,2,FALSE))=D10,"",VLOOKUP(D10,(Categorias!$B$4:$C$65),2,FALSE)) | C10: =IF(IF(ISERROR(VLOOKUP(D10,Categorias!$B$4:$C$65,2,FALSE)),"",VLOOKUP(D10,Categorias!$B$4:$C$65,2,FALSE))=D10,"",VLOOKUP(D10,(Categorias!$B$2:$D$65),3,FALSE)) | J10: =IF(H10="",(""),IF(H10="DP",(J9+G10),IF(H10="DB",(J9-G10),IF(H10="TR",(J9-G10),IF(H10="CH",(J9-G10),IF(H10="SQ",(J9-G10),J9)))))) | K10: =IF(H10="",(""),IF(H10="SQ",(K9+G10),IF(H10="RD",(K9+G10),IF(H10="DI",(K9-G10),K9)))) | L10: =IF(H10="",(""),IF(H10="CC",(L9+G10),IF(H10="PC",(L9+G10),L9)))
B11: =IF(IF(ISERROR(VLOOKUP(D11,Categorias!$B$4:$C$65,2,FALSE)),"",VLOOKUP(D11,Categorias!$B$4:$C$65,2,FALSE))=D11,"",VLOOKUP(D11,(Categorias!$B$4:$C$65),2,FALSE)) | C11: =IF(IF(ISERROR(VLOOKUP(D11,Categorias!$B$4:$C$65,2,FALSE)),"",VLOOKUP(D11,Categorias!$B$4:$C$65,2,FALSE))=D11,"",VLOOKUP(D11,(Categorias!$B$2:$D$65),3,FALSE)) | J11: =IF(H11="",(""),IF(H11="DP",(J10+G11),IF(H11="DB",(J10-G11),IF(H11="TR",(J10-G11),IF(H11="CH",(J10-G11),IF(H11="SQ",(J10-G11),J10)))))) | K11: =IF(H11="",(""),IF(H11="SQ",(K10+G11),IF(H11="RD",(K10+G11),IF(H11="DI",(K10-G11),K10)))) | L11: =IF(H11="",(""),IF(H11="CC",(L10+G11),IF(H11="PC",(L10+G11),L10)))
B12: =IF(IF(ISERROR(VLOOKUP(D12,Categorias!$B$4:$C$65,2,FALSE)),"",VLOOKUP(D12,Categorias!$B$4:$C$65,2,FALSE))=D12,"",VLOOKUP(D12,(Categorias!$B$4:$C$65),2,FALSE)) | C12: =IF(IF(ISERROR(VLOOKUP(D12,Categorias!$B$4:$C$65,2,FALSE)),"",VLOOKUP(D12,Categorias!$B$4:$C$65,2,FALSE))=D12,"",VLOOKUP(D12,(Categorias!$B$2:$D$65),3,FALSE)) | J12: =IF(H12="",(""),IF(H12="DP",(J11+G12),IF(H12="DB",(J11-G12),IF(H12="TR",(J11-G12),IF(H12="CH",(J11-G12),IF(H12="SQ",(J11-G12),J11)))))) | K12: =IF(H12="",(""),IF(H12="SQ",(K11+G12),IF(H12="RD",(K11+G12),IF(H12="DI",(K11-G12),K11)))) | L12: =IF(H12="",(""),IF(H12="CC",(L11+G12),IF(H12="PC",(L11+G12),L11)))
B13: =IF(IF(ISERROR(VLOOKUP(D13,Categorias!$B$4:$C$65,2,FALSE)),"",VLOOKUP(D13,Categorias!$B$4:$C$65,2,FALSE))=D13,"",VLOOKUP(D13,(Categorias!$B$4:$C$65),2,FALSE)) | C13: =IF(IF(ISERROR(VLOOKUP(D13,Categorias!$B$4:$C$65,2,FALSE)),"",VLOOKUP(D13,Categorias!$B$4:$C$65,2,FALSE))=D13,"",VLOOKUP(D13,(Categorias!$B$2:$D$65),3,FALSE)) | J13: =IF(H13="",(""),IF(H13="DP",(J12+G13),IF(H13="DB",(J12-G13),IF(H13="TR",(J12-G13),IF(H13="CH",(J12-G13),IF(H13="SQ",(J12-G13),J12)))))) | K13: =IF(H13="",(""),IF(H13="SQ",(K12+G13),IF(H13="RD",(K12+G13),IF(H13="DI",(K12-G13),K12)))) | L13: =IF(H13="",(""),IF(H13="CC",(L12+G13),IF(H13="PC",(L12+G13),L12)))
B14: =IF(IF(ISERROR(VLOOKUP(D14,Categorias!$B$4:$C$65,2,FALSE)),"",VLOOKUP(D14,Categorias!$B$4:$C$65,2,FALSE))=D14,"",VLOOKUP(D14,(Categorias!$B$4:$C$65),2,FALSE)) | C14: =IF(IF(ISERROR(VLOOKUP(D14,Categorias!$B$4:$C$65,2,FALSE)),"",VLOOKUP(D14,Categorias!$B$4:$C$65,2,FALSE))=D14,"",VLOOKUP(D14,(Categorias!$B$2:$D$65),3,FALSE)) | J14: =IF(H14="",(""),IF(H14="DP",(J13+G14),IF(H14="DB",(J13-G14),IF(H14="TR",(J13-G14),IF(H14="CH",(J13-G14),IF(H14="SQ",(J13-G14),J13)))))) | K14: =IF(H14="",(""),IF(H14="SQ",(K13+G14),IF(H14="RD",(K13+G14),IF(H14="DI",(K13-G14),K13)))) | L14: =IF(H14="",(""),IF(H14="CC",(L13+G14),IF(H14="PC",(L13+G14),L13)))
B15: =IF(IF(ISERROR(VLOOKUP(D15,Categorias!$B$4:$C$65,2,FALSE)),"",VLOOKUP(D15,Categorias!$B$4:$C$65,2,FALSE))=D15,"",VLOOKUP(D15,(Categorias!$B$4:$C$65),2,FALSE)) | C15: =IF(IF(ISERROR(VLOOKUP(D15,Categorias!$B$4:$C$65,2,FALSE)),"",VLOOKUP(D15,Categorias!$B$4:$C$65,2,FALSE))=D15,"",VLOOKUP(D15,(Categorias!$B$2:$D$65),3,FALSE)) | J15: =IF(H15="",(""),IF(H15="DP",(J14+G15),IF(H15="DB",(J14-G15),IF(H15="TR",(J14-G15),IF(H15="CH",(J14-G15),IF(H15="SQ",(J14-G15),J14)))))) | K15: =IF(H15="",(""),IF(H15="SQ",(K14+G15),IF(H15="RD",(K14+G15),IF(H15="DI",(K14-G15),K14)))) | L15: =IF(H15="",(""),IF(H15="CC",(L14+G15),IF(H15="PC",(L14+G15),L14)))
B16: =IF(IF(ISERROR(VLOOKUP(D16,Categorias!$B$4:$C$65,2,FALSE)),"",VLOOKUP(D16,Categorias!$B$4:$C$65,2,FALSE))=D16,"",VLOOKUP(D16,(Categorias!$B$4:$C$65),2,FALSE)) | C16: =IF(IF(ISERROR(VLOOKUP(D16,Categorias!$B$4:$C$65,2,FALSE)),"",VLOOKUP(D16,Categorias!$B$4:$C$65,2,FALSE))=D16,"",VLOOKUP(D16,(Categorias!$B$2:$D$65),3,FALSE)) | J16: =IF(H16="",(""),IF(H16="DP",(J15+G16),IF(H16="DB",(J15-G16),IF(H16="TR",(J15-G16),IF(H16="CH",(J15-G16),IF(H16="SQ",(J15-G16),J15)))))) | K16: =IF(H16="",(""),IF(H16="SQ",(K15+G16),IF(H16="RD",(K15+G16),IF(H16="DI",(K15-G16),K15)))) | L16: =IF(H16="",(""),IF(H16="CC",(L15+G16),IF(H16="PC",(L15+G16),L15)))
B17: =IF(IF(ISERROR(VLOOKUP(D17,Categorias!$B$4:$C$65,2,FALSE)),"",VLOOKUP(D17,Categorias!$B$4:$C$65,2,FALSE))=D17,"",VLOOKUP(D17,(Categorias!$B$4:$C$65),2,FALSE)) | C17: =IF(IF(ISERROR(VLOOKUP(D17,Categorias!$B$4:$C$65,2,FALSE)),"",VLOOKUP(D17,Categorias!$B$4:$C$65,2,FALSE))=D17,"",VLOOKUP(D17,(Categorias!$B$2:$D$65),3,FALSE)) | J17: =IF(H17="",(""),IF(H17="DP",(J16+G17),IF(H17="DB",(J16-G17),IF(H17="TR",(J16-G17),IF(H17="CH",(J16-G17),IF(H17="SQ",(J16-G17),J16)))))) | K17: =IF(H17="",(""),IF(H17="SQ",(K16+G17),IF(H17="RD",(K16+G17),IF(H17="DI",(K16-G17),K16)))) | L17: =IF(H17="",(""),IF(H17="CC",(L16+G17),IF(H17="PC",(L16+G17),L16)))
B18: =IF(IF(ISERROR(VLOOKUP(D18,Categorias!$B$4:$C$65,2,FALSE)),"",VLOOKUP(D18,Categorias!$B$4:$C$65,2,FALSE))=D18,"",VLOOKUP(D18,(Categorias!$B$4:$C$65),2,FALSE)) | C18: =IF(IF(ISERROR(VLOOKUP(D18,Categorias!$B$4:$C$65,2,FALSE)),"",VLOOKUP(D18,Categorias!$B$4:$C$65,2,FALSE))=D18,"",VLOOKUP(D18,(Categorias!$B$2:$D$65),3,FALSE)) | J18: =IF(H18="",(""),IF(H18="DP",(J17+G18),IF(H18="DB",(J17-G18),IF(H18="TR",(J17-G18),IF(H18="CH",(J17-G18),IF(H18="SQ",(J17-G18),J17)))))) | K18: =IF(H18="",(""),IF(H18="SQ",(K17+G18),IF(H18="RD",(K17+G18),IF(H18="DI",(K17-G18),K17)))) | L18: =IF(H18="",(""),IF(H18="CC",(L17+G18),IF(H18="PC",(L17+G18),L17)))
... B75: =IF(IF(ISERROR(VLOOKUP(D75,Categorias!$B$4:$C$65,2,FALSE)),"",VLOOKUP(D75,Categorias!$B$4:$C$65,2,FALSE))=D75,"",VLOOKUP(D75,(Categorias!$B$4:$C$65),2,FALSE)) | C75: =IF(IF(ISERROR(VLOOKUP(D75,Categorias!$B$4:$C$65,2,FALSE)),"",VLOOKUP(D75,Categorias!$B$4:$C$65,2,FALSE))=D75,"",VLOOKUP(D75,(Categorias!$B$2:$D$65),3,FALSE)) | J75: =IF(H75="",(""),IF(H75="DP",(J74+G75),IF(H75="DB",(J74-G75),IF(H75="TR",(J74-G75),IF(H75="CH",(J74-G75),IF(H75="SQ",(J74-G75),J74)))))) | K75: =IF(H75="",(""),IF(H75="SQ",(K74+G75),IF(H75="RD",(K74+G75),IF(H75="DI",(K74-G75),K74)))) | L75: =IF(H75="",(""),IF(H75="CC",(L74+G75),IF(H75="PC",(L74+G75),L74)))
F76: Saldo no mês | J76: =+J75 | K76: =+K75 | L76: =+L75
A213: 1
A214: 1

Sheet Jun
C1: Orçamento Doméstico
B2: Descritivo de Receitas e Despesas realizadas | F2: Junho | H2: =+'Instruções'!$I$19 -> #REF! | J2: Movimentação do saldo no mês
H3: Meio de pagamento | J3: Saldo do mês anterior
B4: Grupo de conta | C4: Sub-grupo de conta | D4: Cod. | E4: Data | F4: Descritivo | G4: Valor R$ | J4: C.Corrente (+ / -) | K4: Dinheiro (+ / -) | L4: C. de Crédito (+)
A6: 1 | B6: =IF(IF(ISERROR(VLOOKUP(D6,Categorias!$B$4:$C$65,2,FALSE)),"",VLOOKUP(D6,Categorias!$B$4:$C$65,2,FALSE))=D6,"",VLOOKUP(D6,(Categorias!$B$4:$C$65),2,FALSE)) | C6: =IF(IF(ISERROR(VLOOKUP(D6,Categorias!$B$4:$C$65,2,FALSE)),"",VLOOKUP(D6,Categorias!$B$4:$C$65,2,FALSE))=D6,"",VLOOKUP(D6,(Categorias!$B$2:$D$65),3,FALSE)) | J6: =IF(H6="",(""),IF(H6="DP",(J5+G6),IF(H6="DB",(J5-G6),IF(H6="TR",(J5-G6),IF(H6="CH",(J5-G6),IF(H6="SQ",(J5-G6),J5)))))) | K6: =IF(H6="",(""),IF(H6="SQ",(K5+G6),IF(H6="RD",(K5+G6),IF(H6="DI",(K5-G6),K5)))) | L6: =IF(H6="",(""),IF(H6="CC",(L5+G6),IF(H6="PC",(L5+G6),L5)))
B7: =IF(IF(ISERROR(VLOOKUP(D7,Categorias!$B$4:$C$65,2,FALSE)),"",VLOOKUP(D7,Categorias!$B$4:$C$65,2,FALSE))=D7,"",VLOOKUP(D7,(Categorias!$B$4:$C$65),2,FALSE)) | C7: =IF(IF(ISERROR(VLOOKUP(D7,Categorias!$B$4:$C$65,2,FALSE)),"",VLOOKUP(D7,Categorias!$B$4:$C$65,2,FALSE))=D7,"",VLOOKUP(D7,(Categorias!$B$2:$D$65),3,FALSE)) | J7: =IF(H7="",(""),IF(H7="DP",(J6+G7),IF(H7="DB",(J6-G7),IF(H7="TR",(J6-G7),IF(H7="CH",(J6-G7),IF(H7="SQ",(J6-G7),J6)))))) | K7: =IF(H7="",(""),IF(H7="SQ",(K6+G7),IF(H7="RD",(K6+G7),IF(H7="DI",(K6-G7),K6)))) | L7: =IF(H7="",(""),IF(H7="CC",(L6+G7),IF(H7="PC",(L6+G7),L6)))
B8: =IF(IF(ISERROR(VLOOKUP(D8,Categorias!$B$4:$C$65,2,FALSE)),"",VLOOKUP(D8,Categorias!$B$4:$C$65,2,FALSE))=D8,"",VLOOKUP(D8,(Categorias!$B$4:$C$65),2,FALSE)) | C8: =IF(IF(ISERROR(VLOOKUP(D8,Categorias!$B$4:$C$65,2,FALSE)),"",VLOOKUP(D8,Categorias!$B$4:$C$65,2,FALSE))=D8,"",VLOOKUP(D8,(Categorias!$B$2:$D$65),3,FALSE)) | J8: =IF(H8="",(""),IF(H8="DP",(J7+G8),IF(H8="DB",(J7-G8),IF(H8="TR",(J7-G8),IF(H8="CH",(J7-G8),IF(H8="SQ",(J7-G8),J7)))))) | K8: =IF(H8="",(""),IF(H8="SQ",(K7+G8),IF(H8="RD",(K7+G8),IF(H8="DI",(K7-G8),K7)))) | L8: =IF(H8="",(""),IF(H8="CC",(L7+G8),IF(H8="PC",(L7+G8),L7)))
B9: =IF(IF(ISERROR(VLOOKUP(D9,Categorias!$B$4:$C$65,2,FALSE)),"",VLOOKUP(D9,Categorias!$B$4:$C$65,2,FALSE))=D9,"",VLOOKUP(D9,(Categorias!$B$4:$C$65),2,FALSE)) | C9: =IF(IF(ISERROR(VLOOKUP(D9,Categorias!$B$4:$C$65,2,FALSE)),"",VLOOKUP(D9,Categorias!$B$4:$C$65,2,FALSE))=D9,"",VLOOKUP(D9,(Categorias!$B$2:$D$65),3,FALSE)) | J9: =IF(H9="",(""),IF(H9="DP",(J8+G9),IF(H9="DB",(J8-G9),IF(H9="TR",(J8-G9),IF(H9="CH",(J8-G9),IF(H9="SQ",(J8-G9),J8)))))) | K9: =IF(H9="",(""),IF(H9="SQ",(K8+G9),IF(H9="RD",(K8+G9),IF(H9="DI",(K8-G9),K8)))) | L9: =IF(H9="",(""),IF(H9="CC",(L8+G9),IF(H9="PC",(L8+G9),L8)))
B10: =IF(IF(ISERROR(VLOOKUP(D10,Categorias!$B$4:$C$65,2,FALSE)),"",VLOOKUP(D10,Categorias!$B$4:$C$65,2,FALSE))=D10,"",VLOOKUP(D10,(Categorias!$B$4:$C$65),2,FALSE)) | C10: =IF(IF(ISERROR(VLOOKUP(D10,Categorias!$B$4:$C$65,2,FALSE)),"",VLOOKUP(D10,Categorias!$B$4:$C$65,2,FALSE))=D10,"",VLOOKUP(D10,(Categorias!$B$2:$D$65),3,FALSE)) | J10: =IF(H10="",(""),IF(H10="DP",(J9+G10),IF(H10="DB",(J9-G10),IF(H10="TR",(J9-G10),IF(H10="CH",(J9-G10),IF(H10="SQ",(J9-G10),J9)))))) | K10: =IF(H10="",(""),IF(H10="SQ",(K9+G10),IF(H10="RD",(K9+G10),IF(H10="DI",(K9-G10),K9)))) | L10: =IF(H10="",(""),IF(H10="CC",(L9+G10),IF(H10="PC",(L9+G10),L9)))
B11: =IF(IF(ISERROR(VLOOKUP(D11,Categorias!$B$4:$C$65,2,FALSE)),"",VLOOKUP(D11,Categorias!$B$4:$C$65,2,FALSE))=D11,"",VLOOKUP(D11,(Categorias!$B$4:$C$65),2,FALSE)) | C11: =IF(IF(ISERROR(VLOOKUP(D11,Categorias!$B$4:$C$65,2,FALSE)),"",VLOOKUP(D11,Categorias!$B$4:$C$65,2,FALSE))=D11,"",VLOOKUP(D11,(Categorias!$B$2:$D$65),3,FALSE)) | J11: =IF(H11="",(""),IF(H11="DP",(J10+G11),IF(H11="DB",(J10-G11),IF(H11="TR",(J10-G11),IF(H11="CH",(J10-G11),IF(H11="SQ",(J10-G11),J10)))))) | K11: =IF(H11="",(""),IF(H11="SQ",(K10+G11),IF(H11="RD",(K10+G11),IF(H11="DI",(K10-G11),K10)))) | L11: =IF(H11="",(""),IF(H11="CC",(L10+G11),IF(H11="PC",(L10+G11),L10)))
B12: =IF(IF(ISERROR(VLOOKUP(D12,Categorias!$B$4:$C$65,2,FALSE)),"",VLOOKUP(D12,Categorias!$B$4:$C$65,2,FALSE))=D12,"",VLOOKUP(D12,(Categorias!$B$4:$C$65),2,FALSE)) | C12: =IF(IF(ISERROR(VLOOKUP(D12,Categorias!$B$4:$C$65,2,FALSE)),"",VLOOKUP(D12,Categorias!$B$4:$C$65,2,FALSE))=D12,"",VLOOKUP(D12,(Categorias!$B$2:$D$65),3,FALSE)) | J12: =IF(H12="",(""),IF(H12="DP",(J11+G12),IF(H12="DB",(J11-G12),IF(H12="TR",(J11-G12),IF(H12="CH",(J11-G12),IF(H12="SQ",(J11-G12),J11)))))) | K12: =IF(H12="",(""),IF(H12="SQ",(K11+G12),IF(H12="RD",(K11+G12),IF(H12="DI",(K11-G12),K11)))) | L12: =IF(H12="",(""),IF(H12="CC",(L11+G12),IF(H12="PC",(L11+G12),L11)))
B13: =IF(IF(ISERROR(VLOOKUP(D13,Categorias!$B$4:$C$65,2,FALSE)),"",VLOOKUP(D13,Categorias!$B$4:$C$65,2,FALSE))=D13,"",VLOOKUP(D13,(Categorias!$B$4:$C$65),2,FALSE)) | C13: =IF(IF(ISERROR(VLOOKUP(D13,Categorias!$B$4:$C$65,2,FALSE)),"",VLOOKUP(D13,Categorias!$B$4:$C$65,2,FALSE))=D13,"",VLOOKUP(D13,(Categorias!$B$2:$D$65),3,FALSE)) | J13: =IF(H13="",(""),IF(H13="DP",(J12+G13),IF(H13="DB",(J12-G13),IF(H13="TR",(J12-G13),IF(H13="CH",(J12-G13),IF(H13="SQ",(J12-G13),J12)))))) | K13: =IF(H13="",(""),IF(H13="SQ",(K12+G13),IF(H13="RD",(K12+G13),IF(H13="DI",(K12-G13),K12)))) | L13: =IF(H13="",(""),IF(H13="CC",(L12+G13),IF(H13="PC",(L12+G13),L12)))
B14: =IF(IF(ISERROR(VLOOKUP(D14,Categorias!$B$4:$C$65,2,FALSE)),"",VLOOKUP(D14,Categorias!$B$4:$C$65,2,FALSE))=D14,"",VLOOKUP(D14,(Categorias!$B$4:$C$65),2,FALSE)) | C14: =IF(IF(ISERROR(VLOOKUP(D14,Categorias!$B$4:$C$65,2,FALSE)),"",VLOOKUP(D14,Categorias!$B$4:$C$65,2,FALSE))=D14,"",VLOOKUP(D14,(Categorias!$B$2:$D$65),3,FALSE)) | J14: =IF(H14="",(""),IF(H14="DP",(J13+G14),IF(H14="DB",(J13-G14),IF(H14="TR",(J13-G14),IF(H14="CH",(J13-G14),IF(H14="SQ",(J13-G14),J13)))))) | K14: =IF(H14="",(""),IF(H14="SQ",(K13+G14),IF(H14="RD",(K13+G14),IF(H14="DI",(K13-G14),K13)))) | L14: =IF(H14="",(""),IF(H14="CC",(L13+G14),IF(H14="PC",(L13+G14),L13)))
B15: =IF(IF(ISERROR(VLOOKUP(D15,Categorias!$B$4:$C$65,2,FALSE)),"",VLOOKUP(D15,Categorias!$B$4:$C$65,2,FALSE))=D15,"",VLOOKUP(D15,(Categorias!$B$4:$C$65),2,FALSE)) | C15: =IF(IF(ISERROR(VLOOKUP(D15,Categorias!$B$4:$C$65,2,FALSE)),"",VLOOKUP(D15,Categorias!$B$4:$C$65,2,FALSE))=D15,"",VLOOKUP(D15,(Categorias!$B$2:$D$65),3,FALSE)) | J15: =IF(H15="",(""),IF(H15="DP",(J14+G15),IF(H15="DB",(J14-G15),IF(H15="TR",(J14-G15),IF(H15="CH",(J14-G15),IF(H15="SQ",(J14-G15),J14)))))) | K15: =IF(H15="",(""),IF(H15="SQ",(K14+G15),IF(H15="RD",(K14+G15),IF(H15="DI",(K14-G15),K14)))) | L15: =IF(H15="",(""),IF(H15="CC",(L14+G15),IF(H15="PC",(L14+G15),L14)))
B16: =IF(IF(ISERROR(VLOOKUP(D16,Categorias!$B$4:$C$65,2,FALSE)),"",VLOOKUP(D16,Categorias!$B$4:$C$65,2,FALSE))=D16,"",VLOOKUP(D16,(Categorias!$B$4:$C$65),2,FALSE)) | C16: =IF(IF(ISERROR(VLOOKUP(D16,Categorias!$B$4:$C$65,2,FALSE)),"",VLOOKUP(D16,Categorias!$B$4:$C$65,2,FALSE))=D16,"",VLOOKUP(D16,(Categorias!$B$2:$D$65),3,FALSE)) | J16: =IF(H16="",(""),IF(H16="DP",(J15+G16),IF(H16="DB",(J15-G16),IF(H16="TR",(J15-G16),IF(H16="CH",(J15-G16),IF(H16="SQ",(J15-G16),J15)))))) | K16: =IF(H16="",(""),IF(H16="SQ",(K15+G16),IF(H16="RD",(K15+G16),IF(H16="DI",(K15-G16),K15)))) | L16: =IF(H16="",(""),IF(H16="CC",(L15+G16),IF(H16="PC",(L15+G16),L15)))
B17: =IF(IF(ISERROR(VLOOKUP(D17,Categorias!$B$4:$C$65,2,FALSE)),"",VLOOKUP(D17,Categorias!$B$4:$C$65,2,FALSE))=D17,"",VLOOKUP(D17,(Categorias!$B$4:$C$65),2,FALSE)) | C17: =IF(IF(ISERROR(VLOOKUP(D17,Categorias!$B$4:$C$65,2,FALSE)),"",VLOOKUP(D17,Categorias!$B$4:$C$65,2,FALSE))=D17,"",VLOOKUP(D17,(Categorias!$B$2:$D$65),3,FALSE)) | J17: =IF(H17="",(""),IF(H17="DP",(J16+G17),IF(H17="DB",(J16-G17),IF(H17="TR",(J16-G17),IF(H17="CH",(J16-G17),IF(H17="SQ",(J16-G17),J16)))))) | K17: =IF(H17="",(""),IF(H17="SQ",(K16+G17),IF(H17="RD",(K16+G17),IF(H17="DI",(K16-G17),K16)))) | L17: =IF(H17="",(""),IF(H17="CC",(L16+G17),IF(H17="PC",(L16+G17),L16)))
B18: =IF(IF(ISERROR(VLOOKUP(D18,Categorias!$B$4:$C$65,2,FALSE)),"",VLOOKUP(D18,Categorias!$B$4:$C$65,2,FALSE))=D18,"",VLOOKUP(D18,(Categorias!$B$4:$C$65),2,FALSE)) | C18: =IF(IF(ISERROR(VLOOKUP(D18,Categorias!$B$4:$C$65,2,FALSE)),"",VLOOKUP(D18,Categorias!$B$4:$C$65,2,FALSE))=D18,"",VLOOKUP(D18,(Categorias!$B$2:$D$65),3,FALSE)) | J18: =IF(H18="",(""),IF(H18="DP",(J17+G18),IF(H18="DB",(J17-G18),IF(H18="TR",(J17-G18),IF(H18="CH",(J17-G18),IF(H18="SQ",(J17-G18),J17)))))) | K18: =IF(H18="",(""),IF(H18="SQ",(K17+G18),IF(H18="RD",(K17+G18),IF(H18="DI",(K17-G18),K17)))) | L18: =IF(H18="",(""),IF(H18="CC",(L17+G18),IF(H18="PC",(L17+G18),L17)))
... B75: =IF(IF(ISERROR(VLOOKUP(D75,Categorias!$B$4:$C$65,2,FALSE)),"",VLOOKUP(D75,Categorias!$B$4:$C$65,2,FALSE))=D75,"",VLOOKUP(D75,(Categorias!$B$4:$C$65),2,FALSE)) | C75: =IF(IF(ISERROR(VLOOKUP(D75,Categorias!$B$4:$C$65,2,FALSE)),"",VLOOKUP(D75,Categorias!$B$4:$C$65,2,FALSE))=D75,"",VLOOKUP(D75,(Categorias!$B$2:$D$65),3,FALSE)) | J75: =IF(H75="",(""),IF(H75="DP",(J74+G75),IF(H75="DB",(J74-G75),IF(H75="TR",(J74-G75),IF(H75="CH",(J74-G75),IF(H75="SQ",(J74-G75),J74)))))) | K75: =IF(H75="",(""),IF(H75="SQ",(K74+G75),IF(H75="RD",(K74+G75),IF(H75="DI",(K74-G75),K74)))) | L75: =IF(H75="",(""),IF(H75="CC",(L74+G75),IF(H75="PC",(L74+G75),L74)))
F76: Saldo no mês | J76: =+J75 | K76: =+K75 | L76: =+L75
A213: 1
A214: 1

Sheet Jul
C1: Orçamento Doméstico
B2: Descritivo de Receitas e Despesas realizadas | F2: Julho | H2: =+'Instruções'!$I$19 -> #REF! | J2: Movimentação do saldo no mês
H3: Meio de pagamento | J3: Saldo do mês anterior
B4: Grupo de conta | C4: Sub-grupo de conta | D4: Cod. | E4: Data | F4: Descritivo | G4: Valor R$ | J4: C.Corrente (+ / -) | K4: Dinheiro (+ / -) | L4: C. de Crédito (+)
A6: 1 | B6: =IF(IF(ISERROR(VLOOKUP(D6,Categorias!$B$4:$C$65,2,FALSE)),"",VLOOKUP(D6,Categorias!$B$4:$C$65,2,FALSE))=D6,"",VLOOKUP(D6,(Categorias!$B$4:$C$65),2,FALSE)) | C6: =IF(IF(ISERROR(VLOOKUP(D6,Categorias!$B$4:$C$65,2,FALSE)),"",VLOOKUP(D6,Categorias!$B$4:$C$65,2,FALSE))=D6,"",VLOOKUP(D6,(Categorias!$B$2:$D$65),3,FALSE)) | J6: =IF(H6="",(""),IF(H6="DP",(J5+G6),IF(H6="DB",(J5-G6),IF(H6="TR",(J5-G6),IF(H6="CH",(J5-G6),IF(H6="SQ",(J5-G6),J5)))))) | K6: =IF(H6="",(""),IF(H6="SQ",(K5+G6),IF(H6="RD",(K5+G6),IF(H6="DI",(K5-G6),K5)))) | L6: =IF(H6="",(""),IF(H6="CC",(L5+G6),IF(H6="PC",(L5+G6),L5)))
B7: =IF(IF(ISERROR(VLOOKUP(D7,Categorias!$B$4:$C$65,2,FALSE)),"",VLOOKUP(D7,Categorias!$B$4:$C$65,2,FALSE))=D7,"",VLOOKUP(D7,(Categorias!$B$4:$C$65),2,FALSE)) | C7: =IF(IF(ISERROR(VLOOKUP(D7,Categorias!$B$4:$C$65,2,FALSE)),"",VLOOKUP(D7,Categorias!$B$4:$C$65,2,FALSE))=D7,"",VLOOKUP(D7,(Categorias!$B$2:$D$65),3,FALSE)) | J7: =IF(H7="",(""),IF(H7="DP",(J6+G7),IF(H7="DB",(J6-G7),IF(H7="TR",(J6-G7),IF(H7="CH",(J6-G7),IF(H7="SQ",(J6-G7),J6)))))) | K7: =IF(H7="",(""),IF(H7="SQ",(K6+G7),IF(H7="RD",(K6+G7),IF(H7="DI",(K6-G7),K6)))) | L7: =IF(H7="",(""),IF(H7="CC",(L6+G7),IF(H7="PC",(L6+G7),L6)))
B8: =IF(IF(ISERROR(VLOOKUP(D8,Categorias!$B$4:$C$65,2,FALSE)),"",VLOOKUP(D8,Categorias!$B$4:$C$65,2,FALSE))=D8,"",VLOOKUP(D8,(Categorias!$B$4:$C$65),2,FALSE)) | C8: =IF(IF(ISERROR(VLOOKUP(D8,Categorias!$B$4:$C$65,2,FALSE)),"",VLOOKUP(D8,Categorias!$B$4:$C$65,2,FALSE))=D8,"",VLOOKUP(D8,(Categorias!$B$2:$D$65),3,FALSE)) | J8: =IF(H8="",(""),IF(H8="DP",(J7+G8),IF(H8="DB",(J7-G8),IF(H8="TR",(J7-G8),IF(H8="CH",(J7-G8),IF(H8="SQ",(J7-G8),J7)))))) | K8: =IF(H8="",(""),IF(H8="SQ",(K7+G8),IF(H8="RD",(K7+G8),IF(H8="DI",(K7-G8),K7)))) | L8: =IF(H8="",(""),IF(H8="CC",(L7+G8),IF(H8="PC",(L7+G8),L7)))
B9: =IF(IF(ISERROR(VLOOKUP(D9,Categorias!$B$4:$C$65,2,FALSE)),"",VLOOKUP(D9,Categorias!$B$4:$C$65,2,FALSE))=D9,"",VLOOKUP(D9,(Categorias!$B$4:$C$65),2,FALSE)) | C9: =IF(IF(ISERROR(VLOOKUP(D9,Categorias!$B$4:$C$65,2,FALSE)),"",VLOOKUP(D9,Categorias!$B$4:$C$65,2,FALSE))=D9,"",VLOOKUP(D9,(Categorias!$B$2:$D$65),3,FALSE)) | J9: =IF(H9="",(""),IF(H9="DP",(J8+G9),IF(H9="DB",(J8-G9),IF(H9="TR",(J8-G9),IF(H9="CH",(J8-G9),IF(H9="SQ",(J8-G9),J8)))))) | K9: =IF(H9="",(""),IF(H9="SQ",(K8+G9),IF(H9="RD",(K8+G9),IF(H9="DI",(K8-G9),K8)))) | L9: =IF(H9="",(""),IF(H9="CC",(L8+G9),IF(H9="PC",(L8+G9),L8)))
B10: =IF(IF(ISERROR(VLOOKUP(D10,Categorias!$B$4:$C$65,2,FALSE)),"",VLOOKUP(D10,Categorias!$B$4:$C$65,2,FALSE))=D10,"",VLOOKUP(D10,(Categorias!$B$4:$C$65),2,FALSE)) | C10: =IF(IF(ISERROR(VLOOKUP(D10,Categorias!$B$4:$C$65,2,FALSE)),"",VLOOKUP(D10,Categorias!$B$4:$C$65,2,FALSE))=D10,"",VLOOKUP(D10,(Categorias!$B$2:$D$65),3,FALSE)) | J10: =IF(H10="",(""),IF(H10="DP",(J9+G10),IF(H10="DB",(J9-G10),IF(H10="TR",(J9-G10),IF(H10="CH",(J9-G10),IF(H10="SQ",(J9-G10),J9)))))) | K10: =IF(H10="",(""),IF(H10="SQ",(K9+G10),IF(H10="RD",(K9+G10),IF(H10="DI",(K9-G10),K9)))) | L10: =IF(H10="",(""),IF(H10="CC",(L9+G10),IF(H10="PC",(L9+G10),L9)))
B11: =IF(IF(ISERROR(VLOOKUP(D11,Categorias!$B$4:$C$65,2,FALSE)),"",VLOOKUP(D11,Categorias!$B$4:$C$65,2,FALSE))=D11,"",VLOOKUP(D11,(Categorias!$B$4:$C$65),2,FALSE)) | C11: =IF(IF(ISERROR(VLOOKUP(D11,Categorias!$B$4:$C$65,2,FALSE)),"",VLOOKUP(D11,Categorias!$B$4:$C$65,2,FALSE))=D11,"",VLOOKUP(D11,(Categorias!$B$2:$D$65),3,FALSE)) | J11: =IF(H11="",(""),IF(H11="DP",(J10+G11),IF(H11="DB",(J10-G11),IF(H11="TR",(J10-G11),IF(H11="CH",(J10-G11),IF(H11="SQ",(J10-G11),J10)))))) | K11: =IF(H11="",(""),IF(H11="SQ",(K10+G11),IF(H11="RD",(K10+G11),IF(H11="DI",(K10-G11),K10)))) | L11: =IF(H11="",(""),IF(H11="CC",(L10+G11),IF(H11="PC",(L10+G11),L10)))
B12: =IF(IF(ISERROR(VLOOKUP(D12,Categorias!$B$4:$C$65,2,FALSE)),"",VLOOKUP(D12,Categorias!$B$4:$C$65,2,FALSE))=D12,"",VLOOKUP(D12,(Categorias!$B$4:$C$65),2,FALSE)) | C12: =IF(IF(ISERROR(VLOOKUP(D12,Categorias!$B$4:$C$65,2,FALSE)),"",VLOOKUP(D12,Categorias!$B$4:$C$65,2,FALSE))=D12,"",VLOOKUP(D12,(Categorias!$B$2:$D$65),3,FALSE)) | J12: =IF(H12="",(""),IF(H12="DP",(J11+G12),IF(H12="DB",(J11-G12),IF(H12="TR",(J11-G12),IF(H12="CH",(J11-G12),IF(H12="SQ",(J11-G12),J11)))))) | K12: =IF(H12="",(""),IF(H12="SQ",(K11+G12),IF(H12="RD",(K11+G12),IF(H12="DI",(K11-G12),K11)))) | L12: =IF(H12="",(""),IF(H12="CC",(L11+G12),IF(H12="PC",(L11+G12),L11)))
B13: =IF(IF(ISERROR(VLOOKUP(D13,Categorias!$B$4:$C$65,2,FALSE)),"",VLOOKUP(D13,Categorias!$B$4:$C$65,2,FALSE))=D13,"",VLOOKUP(D13,(Categorias!$B$4:$C$65),2,FALSE)) | C13: =IF(IF(ISERROR(VLOOKUP(D13,Categorias!$B$4:$C$65,2,FALSE)),"",VLOOKUP(D13,Categorias!$B$4:$C$65,2,FALSE))=D13,"",VLOOKUP(D13,(Categorias!$B$2:$D$65),3,FALSE)) | J13: =IF(H13="",(""),IF(H13="DP",(J12+G13),IF(H13="DB",(J12-G13),IF(H13="TR",(J12-G13),IF(H13="CH",(J12-G13),IF(H13="SQ",(J12-G13),J12)))))) | K13: =IF(H13="",(""),IF(H13="SQ",(K12+G13),IF(H13="RD",(K12+G13),IF(H13="DI",(K12-G13),K12)))) | L13: =IF(H13="",(""),IF(H13="CC",(L12+G13),IF(H13="PC",(L12+G13),L12)))
B14: =IF(IF(ISERROR(VLOOKUP(D14,Categorias!$B$4:$C$65,2,FALSE)),"",VLOOKUP(D14,Categorias!$B$4:$C$65,2,FALSE))=D14,"",VLOOKUP(D14,(Categorias!$B$4:$C$65),2,FALSE)) | C14: =IF(IF(ISERROR(VLOOKUP(D14,Categorias!$B$4:$C$65,2,FALSE)),"",VLOOKUP(D14,Categorias!$B$4:$C$65,2,FALSE))=D14,"",VLOOKUP(D14,(Categorias!$B$2:$D$65),3,FALSE)) | J14: =IF(H14="",(""),IF(H14="DP",(J13+G14),IF(H14="DB",(J13-G14),IF(H14="TR",(J13-G14),IF(H14="CH",(J13-G14),IF(H14="SQ",(J13-G14),J13)))))) | K14: =IF(H14="",(""),IF(H14="SQ",(K13+G14),IF(H14="RD",(K13+G14),IF(H14="DI",(K13-G14),K13)))) | L14: =IF(H14="",(""),IF(H14="CC",(L13+G14),IF(H14="PC",(L13+G14),L13)))
B15: =IF(IF(ISERROR(VLOOKUP(D15,Categorias!$B$4:$C$65,2,FALSE)),"",VLOOKUP(D15,Categorias!$B$4:$C$65,2,FALSE))=D15,"",VLOOKUP(D15,(Categorias!$B$4:$C$65),2,FALSE)) | C15: =IF(IF(ISERROR(VLOOKUP(D15,Categorias!$B$4:$C$65,2,FALSE)),"",VLOOKUP(D15,Categorias!$B$4:$C$65,2,FALSE))=D15,"",VLOOKUP(D15,(Categorias!$B$2:$D$65),3,FALSE)) | J15: =IF(H15="",(""),IF(H15="DP",(J14+G15),IF(H15="DB",(J14-G15),IF(H15="TR",(J14-G15),IF(H15="CH",(J14-G15),IF(H15="SQ",(J14-G15),J14)))))) | K15: =IF(H15="",(""),IF(H15="SQ",(K14+G15),IF(H15="RD",(K14+G15),IF(H15="DI",(K14-G15),K14)))) | L15: =IF(H15="",(""),IF(H15="CC",(L14+G15),IF(H15="PC",(L14+G15),L14)))
B16: =IF(IF(ISERROR(VLOOKUP(D16,Categorias!$B$4:$C$65,2,FALSE)),"",VLOOKUP(D16,Categorias!$B$4:$C$65,2,FALSE))=D16,"",VLOOKUP(D16,(Categorias!$B$4:$C$65),2,FALSE)) | C16: =IF(IF(ISERROR(VLOOKUP(D16,Categorias!$B$4:$C$65,2,FALSE)),"",VLOOKUP(D16,Categorias!$B$4:$C$65,2,FALSE))=D16,"",VLOOKUP(D16,(Categorias!$B$2:$D$65),3,FALSE)) | J16: =IF(H16="",(""),IF(H16="DP",(J15+G16),IF(H16="DB",(J15-G16),IF(H16="TR",(J15-G16),IF(H16="CH",(J15-G16),IF(H16="SQ",(J15-G16),J15)))))) | K16: =IF(H16="",(""),IF(H16="SQ",(K15+G16),IF(H16="RD",(K15+G16),IF(H16="DI",(K15-G16),K15)))) | L16: =IF(H16="",(""),IF(H16="CC",(L15+G16),IF(H16="PC",(L15+G16),L15)))
B17: =IF(IF(ISERROR(VLOOKUP(D17,Categorias!$B$4:$C$65,2,FALSE)),"",VLOOKUP(D17,Categorias!$B$4:$C$65,2,FALSE))=D17,"",VLOOKUP(D17,(Categorias!$B$4:$C$65),2,FALSE)) | C17: =IF(IF(ISERROR(VLOOKUP(D17,Categorias!$B$4:$C$65,2,FALSE)),"",VLOOKUP(D17,Categorias!$B$4:$C$65,2,FALSE))=D17,"",VLOOKUP(D17,(Categorias!$B$2:$D$65),3,FALSE)) | J17: =IF(H17="",(""),IF(H17="DP",(J16+G17),IF(H17="DB",(J16-G17),IF(H17="TR",(J16-G17),IF(H17="CH",(J16-G17),IF(H17="SQ",(J16-G17),J16)))))) | K17: =IF(H17="",(""),IF(H17="SQ",(K16+G17),IF(H17="RD",(K16+G17),IF(H17="DI",(K16-G17),K16)))) | L17: =IF(H17="",(""),IF(H17="CC",(L16+G17),IF(H17="PC",(L16+G17),L16)))
B18: =IF(IF(ISERROR(VLOOKUP(D18,Categorias!$B$4:$C$65,2,FALSE)),"",VLOOKUP(D18,Categorias!$B$4:$C$65,2,FALSE))=D18,"",VLOOKUP(D18,(Categorias!$B$4:$C$65),2,FALSE)) | C18: =IF(IF(ISERROR(VLOOKUP(D18,Categorias!$B$4:$C$65,2,FALSE)),"",VLOOKUP(D18,Categorias!$B$4:$C$65,2,FALSE))=D18,"",VLOOKUP(D18,(Categorias!$B$2:$D$65),3,FALSE)) | J18: =IF(H18="",(""),IF(H18="DP",(J17+G18),IF(H18="DB",(J17-G18),IF(H18="TR",(J17-G18),IF(H18="CH",(J17-G18),IF(H18="SQ",(J17-G18),J17)))))) | K18: =IF(H18="",(""),IF(H18="SQ",(K17+G18),IF(H18="RD",(K17+G18),IF(H18="DI",(K17-G18),K17)))) | L18: =IF(H18="",(""),IF(H18="CC",(L17+G18),IF(H18="PC",(L17+G18),L17)))
... B75: =IF(IF(ISERROR(VLOOKUP(D75,Categorias!$B$4:$C$65,2,FALSE)),"",VLOOKUP(D75,Categorias!$B$4:$C$65,2,FALSE))=D75,"",VLOOKUP(D75,(Categorias!$B$4:$C$65),2,FALSE)) | C75: =IF(IF(ISERROR(VLOOKUP(D75,Categorias!$B$4:$C$65,2,FALSE)),"",VLOOKUP(D75,Categorias!$B$4:$C$65,2,FALSE))=D75,"",VLOOKUP(D75,(Categorias!$B$2:$D$65),3,FALSE)) | J75: =IF(H75="",(""),IF(H75="DP",(J74+G75),IF(H75="DB",(J74-G75),IF(H75="TR",(J74-G75),IF(H75="CH",(J74-G75),IF(H75="SQ",(J74-G75),J74)))))) | K75: =IF(H75="",(""),IF(H75="SQ",(K74+G75),IF(H75="RD",(K74+G75),IF(H75="DI",(K74-G75),K74)))) | L75: =IF(H75="",(""),IF(H75="CC",(L74+G75),IF(H75="PC",(L74+G75),L74)))
F76: Saldo no mês | J76: =+J75 | K76: =+K75 | L76: =+L75
A213: 1
A214: 1

Sheet Ago
C1: Orçamento Doméstico
B2: Descritivo de Receitas e Despesas realizadas | F2: Agosto | H2: =+'Instruções'!$I$19 -> #REF! | J2: Movimentação do saldo no mês
H3: Meio de pagamento | J3: Saldo do mês anterior
B4: Grupo de conta | C4: Sub-grupo de conta | D4: Cod. | E4: Data | F4: Descritivo | G4: Valor R$ | J4: C.Corrente (+ / -) | K4: Dinheiro (+ / -) | L4: C. de Crédito (+)
A6: 1 | B6: =IF(IF(ISERROR(VLOOKUP(D6,Categorias!$B$4:$C$65,2,FALSE)),"",VLOOKUP(D6,Categorias!$B$4:$C$65,2,FALSE))=D6,"",VLOOKUP(D6,(Categorias!$B$4:$C$65),2,FALSE)) | C6: =IF(IF(ISERROR(VLOOKUP(D6,Categorias!$B$4:$C$65,2,FALSE)),"",VLOOKUP(D6,Categorias!$B$4:$C$65,2,FALSE))=D6,"",VLOOKUP(D6,(Categorias!$B$2:$D$65),3,FALSE)) | J6: =IF(H6="",(""),IF(H6="DP",(J5+G6),IF(H6="DB",(J5-G6),IF(H6="TR",(J5-G6),IF(H6="CH",(J5-G6),IF(H6="SQ",(J5-G6),J5)))))) | K6: =IF(H6="",(""),IF(H6="SQ",(K5+G6),IF(H6="RD",(K5+G6),IF(H6="DI",(K5-G6),K5)))) | L6: =IF(H6="",(""),IF(H6="CC",(L5+G6),IF(H6="PC",(L5+G6),L5)))
B7: =IF(IF(ISERROR(VLOOKUP(D7,Categorias!$B$4:$C$65,2,FALSE)),"",VLOOKUP(D7,Categorias!$B$4:$C$65,2,FALSE))=D7,"",VLOOKUP(D7,(Categorias!$B$4:$C$65),2,FALSE)) | C7: =IF(IF(ISERROR(VLOOKUP(D7,Categorias!$B$4:$C$65,2,FALSE)),"",VLOOKUP(D7,Categorias!$B$4:$C$65,2,FALSE))=D7,"",VLOOKUP(D7,(Categorias!$B$2:$D$65),3,FALSE)) | J7: =IF(H7="",(""),IF(H7="DP",(J6+G7),IF(H7="DB",(J6-G7),IF(H7="TR",(J6-G7),IF(H7="CH",(J6-G7),IF(H7="SQ",(J6-G7),J6)))))) | K7: =IF(H7="",(""),IF(H7="SQ",(K6+G7),IF(H7="RD",(K6+G7),IF(H7="DI",(K6-G7),K6)))) | L7: =IF(H7="",(""),IF(H7="CC",(L6+G7),IF(H7="PC",(L6+G7),L6)))
B8: =IF(IF(ISERROR(VLOOKUP(D8,Categorias!$B$4:$C$65,2,FALSE)),"",VLOOKUP(D8,Categorias!$B$4:$C$65,2,FALSE))=D8,"",VLOOKUP(D8,(Categorias!$B$4:$C$65),2,FALSE)) | C8: =IF(IF(ISERROR(VLOOKUP(D8,Categorias!$B$4:$C$65,2,FALSE)),"",VLOOKUP(D8,Categorias!$B$4:$C$65,2,FALSE))=D8,"",VLOOKUP(D8,(Categorias!$B$2:$D$65),3,FALSE)) | J8: =IF(H8="",(""),IF(H8="DP",(J7+G8),IF(H8="DB",(J7-G8),IF(H8="TR",(J7-G8),IF(H8="CH",(J7-G8),IF(H8="SQ",(J7-G8),J7)))))) | K8: =IF(H8="",(""),IF(H8="SQ",(K7+G8),IF(H8="RD",(K7+G8),IF(H8="DI",(K7-G8),K7)))) | L8: =IF(H8="",(""),IF(H8="CC",(L7+G8),IF(H8="PC",(L7+G8),L7)))
B9: =IF(IF(ISERROR(VLOOKUP(D9,Categorias!$B$4:$C$65,2,FALSE)),"",VLOOKUP(D9,Categorias!$B$4:$C$65,2,FALSE))=D9,"",VLOOKUP(D9,(Categorias!$B$4:$C$65),2,FALSE)) | C9: =IF(IF(ISERROR(VLOOKUP(D9,Categorias!$B$4:$C$65,2,FALSE)),"",VLOOKUP(D9,Categorias!$B$4:$C$65,2,FALSE))=D9,"",VLOOKUP(D9,(Categorias!$B$2:$D$65),3,FALSE)) | J9: =IF(H9="",(""),IF(H9="DP",(J8+G9),IF(H9="DB",(J8-G9),IF(H9="TR",(J8-G9),IF(H9="CH",(J8-G9),IF(H9="SQ",(J8-G9),J8)))))) | K9: =IF(H9="",(""),IF(H9="SQ",(K8+G9),IF(H9="RD",(K8+G9),IF(H9="DI",(K8-G9),K8)))) | L9: =IF(H9="",(""),IF(H9="CC",(L8+G9),IF(H9="PC",(L8+G9),L8)))
B10: =IF(IF(ISERROR(VLOOKUP(D10,Categorias!$B$4:$C$65,2,FALSE)),"",VLOOKUP(D10,Categorias!$B$4:$C$65,2,FALSE))=D10,"",VLOOKUP(D10,(Categorias!$B$4:$C$65),2,FALSE)) | C10: =IF(IF(ISERROR(VLOOKUP(D10,Categorias!$B$4:$C$65,2,FALSE)),"",VLOOKUP(D10,Categorias!$B$4:$C$65,2,FALSE))=D10,"",VLOOKUP(D10,(Categorias!$B$2:$D$65),3,FALSE)) | J10: =IF(H10="",(""),IF(H10="DP",(J9+G10),IF(H10="DB",(J9-G10),IF(H10="TR",(J9-G10),IF(H10="CH",(J9-G10),IF(H10="SQ",(J9-G10),J9)))))) | K10: =IF(H10="",(""),IF(H10="SQ",(K9+G10),IF(H10="RD",(K9+G10),IF(H10="DI",(K9-G10),K9)))) | L10: =IF(H10="",(""),IF(H10="CC",(L9+G10),IF(H10="PC",(L9+G10),L9)))
B11: =IF(IF(ISERROR(VLOOKUP(D11,Categorias!$B$4:$C$65,2,FALSE)),"",VLOOKUP(D11,Categorias!$B$4:$C$65,2,FALSE))=D11,"",VLOOKUP(D11,(Categorias!$B$4:$C$65),2,FALSE)) | C11: =IF(IF(ISERROR(VLOOKUP(D11,Categorias!$B$4:$C$65,2,FALSE)),"",VLOOKUP(D11,Categorias!$B$4:$C$65,2,FALSE))=D11,"",VLOOKUP(D11,(Categorias!$B$2:$D$65),3,FALSE)) | J11: =IF(H11="",(""),IF(H11="DP",(J10+G11),IF(H11="DB",(J10-G11),IF(H11="TR",(J10-G11),IF(H11="CH",(J10-G11),IF(H11="SQ",(J10-G11),J10)))))) | K11: =IF(H11="",(""),IF(H11="SQ",(K10+G11),IF(H11="RD",(K10+G11),IF(H11="DI",(K10-G11),K10)))) | L11: =IF(H11="",(""),IF(H11="CC",(L10+G11),IF(H11="PC",(L10+G11),L10)))
B12: =IF(IF(ISERROR(VLOOKUP(D12,Categorias!$B$4:$C$65,2,FALSE)),"",VLOOKUP(D12,Categorias!$B$4:$C$65,2,FALSE))=D12,"",VLOOKUP(D12,(Categorias!$B$4:$C$65),2,FALSE)) | C12: =IF(IF(ISERROR(VLOOKUP(D12,Categorias!$B$4:$C$65,2,FALSE)),"",VLOOKUP(D12,Categorias!$B$4:$C$65,2,FALSE))=D12,"",VLOOKUP(D12,(Categorias!$B$2:$D$65),3,FALSE)) | J12: =IF(H12="",(""),IF(H12="DP",(J11+G12),IF(H12="DB",(J11-G12),IF(H12="TR",(J11-G12),IF(H12="CH",(J11-G12),IF(H12="SQ",(J11-G12),J11)))))) | K12: =IF(H12="",(""),IF(H12="SQ",(K11+G12),IF(H12="RD",(K11+G12),IF(H12="DI",(K11-G12),K11)))) | L12: =IF(H12="",(""),IF(H12="CC",(L11+G12),IF(H12="PC",(L11+G12),L11)))
B13: =IF(IF(ISERROR(VLOOKUP(D13,Categorias!$B$4:$C$65,2,FALSE)),"",VLOOKUP(D13,Categorias!$B$4:$C$65,2,FALSE))=D13,"",VLOOKUP(D13,(Categorias!$B$4:$C$65),2,FALSE)) | C13: =IF(IF(ISERROR(VLOOKUP(D13,Categorias!$B$4:$C$65,2,FALSE)),"",VLOOKUP(D13,Categorias!$B$4:$C$65,2,FALSE))=D13,"",VLOOKUP(D13,(Categorias!$B$2:$D$65),3,FALSE)) | J13: =IF(H13="",(""),IF(H13="DP",(J12+G13),IF(H13="DB",(J12-G13),IF(H13="TR",(J12-G13),IF(H13="CH",(J12-G13),IF(H13="SQ",(J12-G13),J12)))))) | K13: =IF(H13="",(""),IF(H13="SQ",(K12+G13),IF(H13="RD",(K12+G13),IF(H13="DI",(K12-G13),K12)))) | L13: =IF(H13="",(""),IF(H13="CC",(L12+G13),IF(H13="PC",(L12+G13),L12)))
B14: =IF(IF(ISERROR(VLOOKUP(D14,Categorias!$B$4:$C$65,2,FALSE)),"",VLOOKUP(D14,Categorias!$B$4:$C$65,2,FALSE))=D14,"",VLOOKUP(D14,(Categorias!$B$4:$C$65),2,FALSE)) | C14: =IF(IF(ISERROR(VLOOKUP(D14,Categorias!$B$4:$C$65,2,FALSE)),"",VLOOKUP(D14,Categorias!$B$4:$C$65,2,FALSE))=D14,"",VLOOKUP(D14,(Categorias!$B$2:$D$65),3,FALSE)) | J14: =IF(H14="",(""),IF(H14="DP",(J13+G14),IF(H14="DB",(J13-G14),IF(H14="TR",(J13-G14),IF(H14="CH",(J13-G14),IF(H14="SQ",(J13-G14),J13)))))) | K14: =IF(H14="",(""),IF(H14="SQ",(K13+G14),IF(H14="RD",(K13+G14),IF(H14="DI",(K13-G14),K13)))) | L14: =IF(H14="",(""),IF(H14="CC",(L13+G14),IF(H14="PC",(L13+G14),L13)))
B15: =IF(IF(ISERROR(VLOOKUP(D15,Categorias!$B$4:$C$65,2,FALSE)),"",VLOOKUP(D15,Categorias!$B$4:$C$65,2,FALSE))=D15,"",VLOOKUP(D15,(Categorias!$B$4:$C$65),2,FALSE)) | C15: =IF(IF(ISERROR(VLOOKUP(D15,Categorias!$B$4:$C$65,2,FALSE)),"",VLOOKUP(D15,Categorias!$B$4:$C$65,2,FALSE))=D15,"",VLOOKUP(D15,(Categorias!$B$2:$D$65),3,FALSE)) | J15: =IF(H15="",(""),IF(H15="DP",(J14+G15),IF(H15="DB",(J14-G15),IF(H15="TR",(J14-G15),IF(H15="CH",(J14-G15),IF(H15="SQ",(J14-G15),J14)))))) | K15: =IF(H15="",(""),IF(H15="SQ",(K14+G15),IF(H15="RD",(K14+G15),IF(H15="DI",(K14-G15),K14)))) | L15: =IF(H15="",(""),IF(H15="CC",(L14+G15),IF(H15="PC",(L14+G15),L14)))
B16: =IF(IF(ISERROR(VLOOKUP(D16,Categorias!$B$4:$C$65,2,FALSE)),"",VLOOKUP(D16,Categorias!$B$4:$C$65,2,FALSE))=D16,"",VLOOKUP(D16,(Categorias!$B$4:$C$65),2,FALSE)) | C16: =IF(IF(ISERROR(VLOOKUP(D16,Categorias!$B$4:$C$65,2,FALSE)),"",VLOOKUP(D16,Categorias!$B$4:$C$65,2,FALSE))=D16,"",VLOOKUP(D16,(Categorias!$B$2:$D$65),3,FALSE)) | J16: =IF(H16="",(""),IF(H16="DP",(J15+G16),IF(H16="DB",(J15-G16),IF(H16="TR",(J15-G16),IF(H16="CH",(J15-G16),IF(H16="SQ",(J15-G16),J15)))))) | K16: =IF(H16="",(""),IF(H16="SQ",(K15+G16),IF(H16="RD",(K15+G16),IF(H16="DI",(K15-G16),K15)))) | L16: =IF(H16="",(""),IF(H16="CC",(L15+G16),IF(H16="PC",(L15+G16),L15)))
B17: =IF(IF(ISERROR(VLOOKUP(D17,Categorias!$B$4:$C$65,2,FALSE)),"",VLOOKUP(D17,Categorias!$B$4:$C$65,2,FALSE))=D17,"",VLOOKUP(D17,(Categorias!$B$4:$C$65),2,FALSE)) | C17: =IF(IF(ISERROR(VLOOKUP(D17,Categorias!$B$4:$C$65,2,FALSE)),"",VLOOKUP(D17,Categorias!$B$4:$C$65,2,FALSE))=D17,"",VLOOKUP(D17,(Categorias!$B$2:$D$65),3,FALSE)) | J17: =IF(H17="",(""),IF(H17="DP",(J16+G17),IF(H17="DB",(J16-G17),IF(H17="TR",(J16-G17),IF(H17="CH",(J16-G17),IF(H17="SQ",(J16-G17),J16)))))) | K17: =IF(H17="",(""),IF(H17="SQ",(K16+G17),IF(H17="RD",(K16+G17),IF(H17="DI",(K16-G17),K16)))) | L17: =IF(H17="",(""),IF(H17="CC",(L16+G17),IF(H17="PC",(L16+G17),L16)))
B18: =IF(IF(ISERROR(VLOOKUP(D18,Categorias!$B$4:$C$65,2,FALSE)),"",VLOOKUP(D18,Categorias!$B$4:$C$65,2,FALSE))=D18,"",VLOOKUP(D18,(Categorias!$B$4:$C$65),2,FALSE)) | C18: =IF(IF(ISERROR(VLOOKUP(D18,Categorias!$B$4:$C$65,2,FALSE)),"",VLOOKUP(D18,Categorias!$B$4:$C$65,2,FALSE))=D18,"",VLOOKUP(D18,(Categorias!$B$2:$D$65),3,FALSE)) | J18: =IF(H18="",(""),IF(H18="DP",(J17+G18),IF(H18="DB",(J17-G18),IF(H18="TR",(J17-G18),IF(H18="CH",(J17-G18),IF(H18="SQ",(J17-G18),J17)))))) | K18: =IF(H18="",(""),IF(H18="SQ",(K17+G18),IF(H18="RD",(K17+G18),IF(H18="DI",(K17-G18),K17)))) | L18: =IF(H18="",(""),IF(H18="CC",(L17+G18),IF(H18="PC",(L17+G18),L17)))
... B75: =IF(IF(ISERROR(VLOOKUP(D75,Categorias!$B$4:$C$65,2,FALSE)),"",VLOOKUP(D75,Categorias!$B$4:$C$65,2,FALSE))=D75,"",VLOOKUP(D75,(Categorias!$B$4:$C$65),2,FALSE)) | C75: =IF(IF(ISERROR(VLOOKUP(D75,Categorias!$B$4:$C$65,2,FALSE)),"",VLOOKUP(D75,Categorias!$B$4:$C$65,2,FALSE))=D75,"",VLOOKUP(D75,(Categorias!$B$2:$D$65),3,FALSE)) | J75: =IF(H75="",(""),IF(H75="DP",(J74+G75),IF(H75="DB",(J74-G75),IF(H75="TR",(J74-G75),IF(H75="CH",(J74-G75),IF(H75="SQ",(J74-G75),J74)))))) | K75: =IF(H75="",(""),IF(H75="SQ",(K74+G75),IF(H75="RD",(K74+G75),IF(H75="DI",(K74-G75),K74)))) | L75: =IF(H75="",(""),IF(H75="CC",(L74+G75),IF(H75="PC",(L74+G75),L74)))
F76: Saldo no mês | J76: =+J75 | K76: =+K75 | L76: =+L75
A213: 1
A214: 1

Sheet Set
C1: Orçamento Doméstico
B2: Descritivo de Receitas e Despesas realizadas | F2: Setembro | H2: =+'Instruções'!$I$19 -> #REF! | J2: Movimentação do saldo no mês
H3: Meio de pagamento | J3: Saldo do mês anterior
B4: Grupo de conta | C4: Sub-grupo de conta | D4: Cod. | E4: Data | F4: Descritivo | G4: Valor R$ | J4: C.Corrente (+ / -) | K4: Dinheiro (+ / -) | L4: C. de Crédito (+)
A6: 1 | B6: =IF(IF(ISERROR(VLOOKUP(D6,Categorias!$B$4:$C$65,2,FALSE)),"",VLOOKUP(D6,Categorias!$B$4:$C$65,2,FALSE))=D6,"",VLOOKUP(D6,(Categorias!$B$4:$C$65),2,FALSE)) | C6: =IF(IF(ISERROR(VLOOKUP(D6,Categorias!$B$4:$C$65,2,FALSE)),"",VLOOKUP(D6,Categorias!$B$4:$C$65,2,FALSE))=D6,"",VLOOKUP(D6,(Categorias!$B$2:$D$65),3,FALSE)) | J6: =IF(H6="",(""),IF(H6="DP",(J5+G6),IF(H6="DB",(J5-G6),IF(H6="TR",(J5-G6),IF(H6="CH",(J5-G6),IF(H6="SQ",(J5-G6),J5)))))) | K6: =IF(H6="",(""),IF(H6="SQ",(K5+G6),IF(H6="RD",(K5+G6),IF(H6="DI",(K5-G6),K5)))) | L6: =IF(H6="",(""),IF(H6="CC",(L5+G6),IF(H6="PC",(L5+G6),L5)))
B7: =IF(IF(ISERROR(VLOOKUP(D7,Categorias!$B$4:$C$65,2,FALSE)),"",VLOOKUP(D7,Categorias!$B$4:$C$65,2,FALSE))=D7,"",VLOOKUP(D7,(Categorias!$B$4:$C$65),2,FALSE)) | C7: =IF(IF(ISERROR(VLOOKUP(D7,Categorias!$B$4:$C$65,2,FALSE)),"",VLOOKUP(D7,Categorias!$B$4:$C$65,2,FALSE))=D7,"",VLOOKUP(D7,(Categorias!$B$2:$D$65),3,FALSE)) | J7: =IF(H7="",(""),IF(H7="DP",(J6+G7),IF(H7="DB",(J6-G7),IF(H7="TR",(J6-G7),IF(H7="CH",(J6-G7),IF(H7="SQ",(J6-G7),J6)))))) | K7: =IF(H7="",(""),IF(H7="SQ",(K6+G7),IF(H7="RD",(K6+G7),IF(H7="DI",(K6-G7),K6)))) | L7: =IF(H7="",(""),IF(H7="CC",(L6+G7),IF(H7="PC",(L6+G7),L6)))
B8: =IF(IF(ISERROR(VLOOKUP(D8,Categorias!$B$4:$C$65,2,FALSE)),"",VLOOKUP(D8,Categorias!$B$4:$C$65,2,FALSE))=D8,"",VLOOKUP(D8,(Categorias!$B$4:$C$65),2,FALSE)) | C8: =IF(IF(ISERROR(VLOOKUP(D8,Categorias!$B$4:$C$65,2,FALSE)),"",VLOOKUP(D8,Categorias!$B$4:$C$65,2,FALSE))=D8,"",VLOOKUP(D8,(Categorias!$B$2:$D$65),3,FALSE)) | J8: =IF(H8="",(""),IF(H8="DP",(J7+G8),IF(H8="DB",(J7-G8),IF(H8="TR",(J7-G8),IF(H8="CH",(J7-G8),IF(H8="SQ",(J7-G8),J7)))))) | K8: =IF(H8="",(""),IF(H8="SQ",(K7+G8),IF(H8="RD",(K7+G8),IF(H8="DI",(K7-G8),K7)))) | L8: =IF(H8="",(""),IF(H8="CC",(L7+G8),IF(H8="PC",(L7+G8),L7)))
B9: =IF(IF(ISERROR(VLOOKUP(D9,Categorias!$B$4:$C$65,2,FALSE)),"",VLOOKUP(D9,Categorias!$B$4:$C$65,2,FALSE))=D9,"",VLOOKUP(D9,(Categorias!$B$4:$C$65),2,FALSE)) | C9: =IF(IF(ISERROR(VLOOKUP(D9,Categorias!$B$4:$C$65,2,FALSE)),"",VLOOKUP(D9,Categorias!$B$4:$C$65,2,FALSE))=D9,"",VLOOKUP(D9,(Categorias!$B$2:$D$65),3,FALSE)) | J9: =IF(H9="",(""),IF(H9="DP",(J8+G9),IF(H9="DB",(J8-G9),IF(H9="TR",(J8-G9),IF(H9="CH",(J8-G9),IF(H9="SQ",(J8-G9),J8)))))) | K9: =IF(H9="",(""),IF(H9="SQ",(K8+G9),IF(H9="RD",(K8+G9),IF(H9="DI",(K8-G9),K8)))) | L9: =IF(H9="",(""),IF(H9="CC",(L8+G9),IF(H9="PC",(L8+G9),L8)))
B10: =IF(IF(ISERROR(VLOOKUP(D10,Categorias!$B$4:$C$65,2,FALSE)),"",VLOOKUP(D10,Categorias!$B$4:$C$65,2,FALSE))=D10,"",VLOOKUP(D10,(Categorias!$B$4:$C$65),2,FALSE)) | C10: =IF(IF(ISERROR(VLOOKUP(D10,Categorias!$B$4:$C$65,2,FALSE)),"",VLOOKUP(D10,Categorias!$B$4:$C$65,2,FALSE))=D10,"",VLOOKUP(D10,(Categorias!$B$2:$D$65),3,FALSE)) | J10: =IF(H10="",(""),IF(H10="DP",(J9+G10),IF(H10="DB",(J9-G10),IF(H10="TR",(J9-G10),IF(H10="CH",(J9-G10),IF(H10="SQ",(J9-G10),J9)))))) | K10: =IF(H10="",(""),IF(H10="SQ",(K9+G10),IF(H10="RD",(K9+G10),IF(H10="DI",(K9-G10),K9)))) | L10: =IF(H10="",(""),IF(H10="CC",(L9+G10),IF(H10="PC",(L9+G10),L9)))
B11: =IF(IF(ISERROR(VLOOKUP(D11,Categorias!$B$4:$C$65,2,FALSE)),"",VLOOKUP(D11,Categorias!$B$4:$C$65,2,FALSE))=D11,"",VLOOKUP(D11,(Categorias!$B$4:$C$65),2,FALSE)) | C11: =IF(IF(ISERROR(VLOOKUP(D11,Categorias!$B$4:$C$65,2,FALSE)),"",VLOOKUP(D11,Categorias!$B$4:$C$65,2,FALSE))=D11,"",VLOOKUP(D11,(Categorias!$B$2:$D$65),3,FALSE)) | J11: =IF(H11="",(""),IF(H11="DP",(J10+G11),IF(H11="DB",(J10-G11),IF(H11="TR",(J10-G11),IF(H11="CH",(J10-G11),IF(H11="SQ",(J10-G11),J10)))))) | K11: =IF(H11="",(""),IF(H11="SQ",(K10+G11),IF(H11="RD",(K10+G11),IF(H11="DI",(K10-G11),K10)))) | L11: =IF(H11="",(""),IF(H11="CC",(L10+G11),IF(H11="PC",(L10+G11),L10)))
B12: =IF(IF(ISERROR(VLOOKUP(D12,Categorias!$B$4:$C$65,2,FALSE)),"",VLOOKUP(D12,Categorias!$B$4:$C$65,2,FALSE))=D12,"",VLOOKUP(D12,(Categorias!$B$4:$C$65),2,FALSE)) | C12: =IF(IF(ISERROR(VLOOKUP(D12,Categorias!$B$4:$C$65,2,FALSE)),"",VLOOKUP(D12,Categorias!$B$4:$C$65,2,FALSE))=D12,"",VLOOKUP(D12,(Categorias!$B$2:$D$65),3,FALSE)) | J12: =IF(H12="",(""),IF(H12="DP",(J11+G12),IF(H12="DB",(J11-G12),IF(H12="TR",(J11-G12),IF(H12="CH",(J11-G12),IF(H12="SQ",(J11-G12),J11)))))) | K12: =IF(H12="",(""),IF(H12="SQ",(K11+G12),IF(H12="RD",(K11+G12),IF(H12="DI",(K11-G12),K11)))) | L12: =IF(H12="",(""),IF(H12="CC",(L11+G12),IF(H12="PC",(L11+G12),L11)))
B13: =IF(IF(ISERROR(VLOOKUP(D13,Categorias!$B$4:$C$65,2,FALSE)),"",VLOOKUP(D13,Categorias!$B$4:$C$65,2,FALSE))=D13,"",VLOOKUP(D13,(Categorias!$B$4:$C$65),2,FALSE)) | C13: =IF(IF(ISERROR(VLOOKUP(D13,Categorias!$B$4:$C$65,2,FALSE)),"",VLOOKUP(D13,Categorias!$B$4:$C$65,2,FALSE))=D13,"",VLOOKUP(D13,(Categorias!$B$2:$D$65),3,FALSE)) | J13: =IF(H13="",(""),IF(H13="DP",(J12+G13),IF(H13="DB",(J12-G13),IF(H13="TR",(J12-G13),IF(H13="CH",(J12-G13),IF(H13="SQ",(J12-G13),J12)))))) | K13: =IF(H13="",(""),IF(H13="SQ",(K12+G13),IF(H13="RD",(K12+G13),IF(H13="DI",(K12-G13),K12)))) | L13: =IF(H13="",(""),IF(H13="CC",(L12+G13),IF(H13="PC",(L12+G13),L12)))
B14: =IF(IF(ISERROR(VLOOKUP(D14,Categorias!$B$4:$C$65,2,FALSE)),"",VLOOKUP(D14,Categorias!$B$4:$C$65,2,FALSE))=D14,"",VLOOKUP(D14,(Categorias!$B$4:$C$65),2,FALSE)) | C14: =IF(IF(ISERROR(VLOOKUP(D14,Categorias!$B$4:$C$65,2,FALSE)),"",VLOOKUP(D14,Categorias!$B$4:$C$65,2,FALSE))=D14,"",VLOOKUP(D14,(Categorias!$B$2:$D$65),3,FALSE)) | J14: =IF(H14="",(""),IF(H14="DP",(J13+G14),IF(H14="DB",(J13-G14),IF(H14="TR",(J13-G14),IF(H14="CH",(J13-G14),IF(H14="SQ",(J13-G14),J13)))))) | K14: =IF(H14="",(""),IF(H14="SQ",(K13+G14),IF(H14="RD",(K13+G14),IF(H14="DI",(K13-G14),K13)))) | L14: =IF(H14="",(""),IF(H14="CC",(L13+G14),IF(H14="PC",(L13+G14),L13)))
B15: =IF(IF(ISERROR(VLOOKUP(D15,Categorias!$B$4:$C$65,2,FALSE)),"",VLOOKUP(D15,Categorias!$B$4:$C$65,2,FALSE))=D15,"",VLOOKUP(D15,(Categorias!$B$4:$C$65),2,FALSE)) | C15: =IF(IF(ISERROR(VLOOKUP(D15,Categorias!$B$4:$C$65,2,FALSE)),"",VLOOKUP(D15,Categorias!$B$4:$C$65,2,FALSE))=D15,"",VLOOKUP(D15,(Categorias!$B$2:$D$65),3,FALSE)) | J15: =IF(H15="",(""),IF(H15="DP",(J14+G15),IF(H15="DB",(J14-G15),IF(H15="TR",(J14-G15),IF(H15="CH",(J14-G15),IF(H15="SQ",(J14-G15),J14)))))) | K15: =IF(H15="",(""),IF(H15="SQ",(K14+G15),IF(H15="RD",(K14+G15),IF(H15="DI",(K14-G15),K14)))) | L15: =IF(H15="",(""),IF(H15="CC",(L14+G15),IF(H15="PC",(L14+G15),L14)))
B16: =IF(IF(ISERROR(VLOOKUP(D16,Categorias!$B$4:$C$65,2,FALSE)),"",VLOOKUP(D16,Categorias!$B$4:$C$65,2,FALSE))=D16,"",VLOOKUP(D16,(Categorias!$B$4:$C$65),2,FALSE)) | C16: =IF(IF(ISERROR(VLOOKUP(D16,Categorias!$B$4:$C$65,2,FALSE)),"",VLOOKUP(D16,Categorias!$B$4:$C$65,2,FALSE))=D16,"",VLOOKUP(D16,(Categorias!$B$2:$D$65),3,FALSE)) | J16: =IF(H16="",(""),IF(H16="DP",(J15+G16),IF(H16="DB",(J15-G16),IF(H16="TR",(J15-G16),IF(H16="CH",(J15-G16),IF(H16="SQ",(J15-G16),J15)))))) | K16: =IF(H16="",(""),IF(H16="SQ",(K15+G16),IF(H16="RD",(K15+G16),IF(H16="DI",(K15-G16),K15)))) | L16: =IF(H16="",(""),IF(H16="CC",(L15+G16),IF(H16="PC",(L15+G16),L15)))
B17: =IF(IF(ISERROR(VLOOKUP(D17,Categorias!$B$4:$C$65,2,FALSE)),"",VLOOKUP(D17,Categorias!$B$4:$C$65,2,FALSE))=D17,"",VLOOKUP(D17,(Categorias!$B$4:$C$65),2,FALSE)) | C17: =IF(IF(ISERROR(VLOOKUP(D17,Categorias!$B$4:$C$65,2,FALSE)),"",VLOOKUP(D17,Categorias!$B$4:$C$65,2,FALSE))=D17,"",VLOOKUP(D17,(Categorias!$B$2:$D$65),3,FALSE)) | J17: =IF(H17="",(""),IF(H17="DP",(J16+G17),IF(H17="DB",(J16-G17),IF(H17="TR",(J16-G17),IF(H17="CH",(J16-G17),IF(H17="SQ",(J16-G17),J16)))))) | K17: =IF(H17="",(""),IF(H17="SQ",(K16+G17),IF(H17="RD",(K16+G17),IF(H17="DI",(K16-G17),K16)))) | L17: =IF(H17="",(""),IF(H17="CC",(L16+G17),IF(H17="PC",(L16+G17),L16)))
B18: =IF(IF(ISERROR(VLOOKUP(D18,Categorias!$B$4:$C$65,2,FALSE)),"",VLOOKUP(D18,Categorias!$B$4:$C$65,2,FALSE))=D18,"",VLOOKUP(D18,(Categorias!$B$4:$C$65),2,FALSE)) | C18: =IF(IF(ISERROR(VLOOKUP(D18,Categorias!$B$4:$C$65,2,FALSE)),"",VLOOKUP(D18,Categorias!$B$4:$C$65,2,FALSE))=D18,"",VLOOKUP(D18,(Categorias!$B$2:$D$65),3,FALSE)) | J18: =IF(H18="",(""),IF(H18="DP",(J17+G18),IF(H18="DB",(J17-G18),IF(H18="TR",(J17-G18),IF(H18="CH",(J17-G18),IF(H18="SQ",(J17-G18),J17)))))) | K18: =IF(H18="",(""),IF(H18="SQ",(K17+G18),IF(H18="RD",(K17+G18),IF(H18="DI",(K17-G18),K17)))) | L18: =IF(H18="",(""),IF(H18="CC",(L17+G18),IF(H18="PC",(L17+G18),L17)))
... B75: =IF(IF(ISERROR(VLOOKUP(D75,Categorias!$B$4:$C$65,2,FALSE)),"",VLOOKUP(D75,Categorias!$B$4:$C$65,2,FALSE))=D75,"",VLOOKUP(D75,(Categorias!$B$4:$C$65),2,FALSE)) | C75: =IF(IF(ISERROR(VLOOKUP(D75,Categorias!$B$4:$C$65,2,FALSE)),"",VLOOKUP(D75,Categorias!$B$4:$C$65,2,FALSE))=D75,"",VLOOKUP(D75,(Categorias!$B$2:$D$65),3,FALSE)) | J75: =IF(H75="",(""),IF(H75="DP",(J74+G75),IF(H75="DB",(J74-G75),IF(H75="TR",(J74-G75),IF(H75="CH",(J74-G75),IF(H75="SQ",(J74-G75),J74)))))) | K75: =IF(H75="",(""),IF(H75="SQ",(K74+G75),IF(H75="RD",(K74+G75),IF(H75="DI",(K74-G75),K74)))) | L75: =IF(H75="",(""),IF(H75="CC",(L74+G75),IF(H75="PC",(L74+G75),L74)))
F76: Saldo no mês | J76: =+J75 | K76: =+K75 | L76: =+L75
A213: 1
A214: 1

Sheet Out
C1: Orçamento Doméstico
B2: Descritivo de Receitas e Despesas realizadas | F2: Outubro | H2: =+'Instruções'!$I$19 -> #REF! | J2: Movimentação do saldo no mês
H3: Meio de pagamento | J3: Saldo do mês anterior
B4: Grupo de conta | C4: Sub-grupo de conta | D4: Cod. | E4: Data | F4: Descritivo | G4: Valor R$ | J4: C.Corrente (+ / -) | K4: Dinheiro (+ / -) | L4: C. de Crédito (+)
A6: 1 | B6: =IF(IF(ISERROR(VLOOKUP(D6,Categorias!$B$4:$C$65,2,FALSE)),"",VLOOKUP(D6,Categorias!$B$4:$C$65,2,FALSE))=D6,"",VLOOKUP(D6,(Categorias!$B$4:$C$65),2,FALSE)) | C6: =IF(IF(ISERROR(VLOOKUP(D6,Categorias!$B$4:$C$65,2,FALSE)),"",VLOOKUP(D6,Categorias!$B$4:$C$65,2,FALSE))=D6,"",VLOOKUP(D6,(Categorias!$B$2:$D$65),3,FALSE)) | J6: =IF(H6="",(""),IF(H6="DP",(J5+G6),IF(H6="DB",(J5-G6),IF(H6="TR",(J5-G6),IF(H6="CH",(J5-G6),IF(H6="SQ",(J5-G6),J5)))))) | K6: =IF(H6="",(""),IF(H6="SQ",(K5+G6),IF(H6="RD",(K5+G6),IF(H6="DI",(K5-G6),K5)))) | L6: =IF(H6="",(""),IF(H6="CC",(L5+G6),IF(H6="PC",(L5+G6),L5)))
B7: =IF(IF(ISERROR(VLOOKUP(D7,Categorias!$B$4:$C$65,2,FALSE)),"",VLOOKUP(D7,Categorias!$B$4:$C$65,2,FALSE))=D7,"",VLOOKUP(D7,(Categorias!$B$4:$C$65),2,FALSE)) | C7: =IF(IF(ISERROR(VLOOKUP(D7,Categorias!$B$4:$C$65,2,FALSE)),"",VLOOKUP(D7,Categorias!$B$4:$C$65,2,FALSE))=D7,"",VLOOKUP(D7,(Categorias!$B$2:$D$65),3,FALSE)) | J7: =IF(H7="",(""),IF(H7="DP",(J6+G7),IF(H7="DB",(J6-G7),IF(H7="TR",(J6-G7),IF(H7="CH",(J6-G7),IF(H7="SQ",(J6-G7),J6)))))) | K7: =IF(H7="",(""),IF(H7="SQ",(K6+G7),IF(H7="RD",(K6+G7),IF(H7="DI",(K6-G7),K6)))) | L7: =IF(H7="",(""),IF(H7="CC",(L6+G7),IF(H7="PC",(L6+G7),L6)))
B8: =IF(IF(ISERROR(VLOOKUP(D8,Categorias!$B$4:$C$65,2,FALSE)),"",VLOOKUP(D8,Categorias!$B$4:$C$65,2,FALSE))=D8,"",VLOOKUP(D8,(Categorias!$B$4:$C$65),2,FALSE)) | C8: =IF(IF(ISERROR(VLOOKUP(D8,Categorias!$B$4:$C$65,2,FALSE)),"",VLOOKUP(D8,Categorias!$B$4:$C$65,2,FALSE))=D8,"",VLOOKUP(D8,(Categorias!$B$2:$D$65),3,FALSE)) | J8: =IF(H8="",(""),IF(H8="DP",(J7+G8),IF(H8="DB",(J7-G8),IF(H8="TR",(J7-G8),IF(H8="CH",(J7-G8),IF(H8="SQ",(J7-G8),J7)))))) | K8: =IF(H8="",(""),IF(H8="SQ",(K7+G8),IF(H8="RD",(K7+G8),IF(H8="DI",(K7-G8),K7)))) | L8: =IF(H8="",(""),IF(H8="CC",(L7+G8),IF(H8="PC",(L7+G8),L7)))
B9: =IF(IF(ISERROR(VLOOKUP(D9,Categorias!$B$4:$C$65,2,FALSE)),"",VLOOKUP(D9,Categorias!$B$4:$C$65,2,FALSE))=D9,"",VLOOKUP(D9,(Categorias!$B$4:$C$65),2,FALSE)) | C9: =IF(IF(ISERROR(VLOOKUP(D9,Categorias!$B$4:$C$65,2,FALSE)),"",VLOOKUP(D9,Categorias!$B$4:$C$65,2,FALSE))=D9,"",VLOOKUP(D9,(Categorias!$B$2:$D$65),3,FALSE)) | J9: =IF(H9="",(""),IF(H9="DP",(J8+G9),IF(H9="DB",(J8-G9),IF(H9="TR",(J8-G9),IF(H9="CH",(J8-G9),IF(H9="SQ",(J8-G9),J8)))))) | K9: =IF(H9="",(""),IF(H9="SQ",(K8+G9),IF(H9="RD",(K8+G9),IF(H9="DI",(K8-G9),K8)))) | L9: =IF(H9="",(""),IF(H9="CC",(L8+G9),IF(H9="PC",(L8+G9),L8)))
B10: =IF(IF(ISERROR(VLOOKUP(D10,Categorias!$B$4:$C$65,2,FALSE)),"",VLOOKUP(D10,Categorias!$B$4:$C$65,2,FALSE))=D10,"",VLOOKUP(D10,(Categorias!$B$4:$C$65),2,FALSE)) | C10: =IF(IF(ISERROR(VLOOKUP(D10,Categorias!$B$4:$C$65,2,FALSE)),"",VLOOKUP(D10,Categorias!$B$4:$C$65,2,FALSE))=D10,"",VLOOKUP(D10,(Categorias!$B$2:$D$65),3,FALSE)) | J10: =IF(H10="",(""),IF(H10="DP",(J9+G10),IF(H10="DB",(J9-G10),IF(H10="TR",(J9-G10),IF(H10="CH",(J9-G10),IF(H10="SQ",(J9-G10),J9)))))) | K10: =IF(H10="",(""),IF(H10="SQ",(K9+G10),IF(H10="RD",(K9+G10),IF(H10="DI",(K9-G10),K9)))) | L10: =IF(H10="",(""),IF(H10="CC",(L9+G10),IF(H10="PC",(L9+G10),L9)))
B11: =IF(IF(ISERROR(VLOOKUP(D11,Categorias!$B$4:$C$65,2,FALSE)),"",VLOOKUP(D11,Categorias!$B$4:$C$65,2,FALSE))=D11,"",VLOOKUP(D11,(Categorias!$B$4:$C$65),2,FALSE)) | C11: =IF(IF(ISERROR(VLOOKUP(D11,Categorias!$B$4:$C$65,2,FALSE)),"",VLOOKUP(D11,Categorias!$B$4:$C$65,2,FALSE))=D11,"",VLOOKUP(D11,(Categorias!$B$2:$D$65),3,FALSE)) | J11: =IF(H11="",(""),IF(H11="DP",(J10+G11),IF(H11="DB",(J10-G11),IF(H11="TR",(J10-G11),IF(H11="CH",(J10-G11),IF(H11="SQ",(J10-G11),J10)))))) | K11: =IF(H11="",(""),IF(H11="SQ",(K10+G11),IF(H11="RD",(K10+G11),IF(H11="DI",(K10-G11),K10)))) | L11: =IF(H11="",(""),IF(H11="CC",(L10+G11),IF(H11="PC",(L10+G11),L10)))
B12: =IF(IF(ISERROR(VLOOKUP(D12,Categorias!$B$4:$C$65,2,FALSE)),"",VLOOKUP(D12,Categorias!$B$4:$C$65,2,FALSE))=D12,"",VLOOKUP(D12,(Categorias!$B$4:$C$65),2,FALSE)) | C12: =IF(IF(ISERROR(VLOOKUP(D12,Categorias!$B$4:$C$65,2,FALSE)),"",VLOOKUP(D12,Categorias!$B$4:$C$65,2,FALSE))=D12,"",VLOOKUP(D12,(Categorias!$B$2:$D$65),3,FALSE)) | J12: =IF(H12="",(""),IF(H12="DP",(J11+G12),IF(H12="DB",(J11-G12),IF(H12="TR",(J11-G12),IF(H12="CH",(J11-G12),IF(H12="SQ",(J11-G12),J11)))))) | K12: =IF(H12="",(""),IF(H12="SQ",(K11+G12),IF(H12="RD",(K11+G12),IF(H12="DI",(K11-G12),K11)))) | L12: =IF(H12="",(""),IF(H12="CC",(L11+G12),IF(H12="PC",(L11+G12),L11)))
B13: =IF(IF(ISERROR(VLOOKUP(D13,Categorias!$B$4:$C$65,2,FALSE)),"",VLOOKUP(D13,Categorias!$B$4:$C$65,2,FALSE))=D13,"",VLOOKUP(D13,(Categorias!$B$4:$C$65),2,FALSE)) | C13: =IF(IF(ISERROR(VLOOKUP(D13,Categorias!$B$4:$C$65,2,FALSE)),"",VLOOKUP(D13,Categorias!$B$4:$C$65,2,FALSE))=D13,"",VLOOKUP(D13,(Categorias!$B$2:$D$65),3,FALSE)) | J13: =IF(H13="",(""),IF(H13="DP",(J12+G13),IF(H13="DB",(J12-G13),IF(H13="TR",(J12-G13),IF(H13="CH",(J12-G13),IF(H13="SQ",(J12-G13),J12)))))) | K13: =IF(H13="",(""),IF(H13="SQ",(K12+G13),IF(H13="RD",(K12+G13),IF(H13="DI",(K12-G13),K12)))) | L13: =IF(H13="",(""),IF(H13="CC",(L12+G13),IF(H13="PC",(L12+G13),L12)))
B14: =IF(IF(ISERROR(VLOOKUP(D14,Categorias!$B$4:$C$65,2,FALSE)),"",VLOOKUP(D14,Categorias!$B$4:$C$65,2,FALSE))=D14,"",VLOOKUP(D14,(Categorias!$B$4:$C$65),2,FALSE)) | C14: =IF(IF(ISERROR(VLOOKUP(D14,Categorias!$B$4:$C$65,2,FALSE)),"",VLOOKUP(D14,Categorias!$B$4:$C$65,2,FALSE))=D14,"",VLOOKUP(D14,(Categorias!$B$2:$D$65),3,FALSE)) | J14: =IF(H14="",(""),IF(H14="DP",(J13+G14),IF(H14="DB",(J13-G14),IF(H14="TR",(J13-G14),IF(H14="CH",(J13-G14),IF(H14="SQ",(J13-G14),J13)))))) | K14: =IF(H14="",(""),IF(H14="SQ",(K13+G14),IF(H14="RD",(K13+G14),IF(H14="DI",(K13-G14),K13)))) | L14: =IF(H14="",(""),IF(H14="CC",(L13+G14),IF(H14="PC",(L13+G14),L13)))
B15: =IF(IF(ISERROR(VLOOKUP(D15,Categorias!$B$4:$C$65,2,FALSE)),"",VLOOKUP(D15,Categorias!$B$4:$C$65,2,FALSE))=D15,"",VLOOKUP(D15,(Categorias!$B$4:$C$65),2,FALSE)) | C15: =IF(IF(ISERROR(VLOOKUP(D15,Categorias!$B$4:$C$65,2,FALSE)),"",VLOOKUP(D15,Categorias!$B$4:$C$65,2,FALSE))=D15,"",VLOOKUP(D15,(Categorias!$B$2:$D$65),3,FALSE)) | J15: =IF(H15="",(""),IF(H15="DP",(J14+G15),IF(H15="DB",(J14-G15),IF(H15="TR",(J14-G15),IF(H15="CH",(J14-G15),IF(H15="SQ",(J14-G15),J14)))))) | K15: =IF(H15="",(""),IF(H15="SQ",(K14+G15),IF(H15="RD",(K14+G15),IF(H15="DI",(K14-G15),K14)))) | L15: =IF(H15="",(""),IF(H15="CC",(L14+G15),IF(H15="PC",(L14+G15),L14)))
B16: =IF(IF(ISERROR(VLOOKUP(D16,Categorias!$B$4:$C$65,2,FALSE)),"",VLOOKUP(D16,Categorias!$B$4:$C$65,2,FALSE))=D16,"",VLOOKUP(D16,(Categorias!$B$4:$C$65),2,FALSE)) | C16: =IF(IF(ISERROR(VLOOKUP(D16,Categorias!$B$4:$C$65,2,FALSE)),"",VLOOKUP(D16,Categorias!$B$4:$C$65,2,FALSE))=D16,"",VLOOKUP(D16,(Categorias!$B$2:$D$65),3,FALSE)) | J16: =IF(H16="",(""),IF(H16="DP",(J15+G16),IF(H16="DB",(J15-G16),IF(H16="TR",(J15-G16),IF(H16="CH",(J15-G16),IF(H16="SQ",(J15-G16),J15)))))) | K16: =IF(H16="",(""),IF(H16="SQ",(K15+G16),IF(H16="RD",(K15+G16),IF(H16="DI",(K15-G16),K15)))) | L16: =IF(H16="",(""),IF(H16="CC",(L15+G16),IF(H16="PC",(L15+G16),L15)))
B17: =IF(IF(ISERROR(VLOOKUP(D17,Categorias!$B$4:$C$65,2,FALSE)),"",VLOOKUP(D17,Categorias!$B$4:$C$65,2,FALSE))=D17,"",VLOOKUP(D17,(Categorias!$B$4:$C$65),2,FALSE)) | C17: =IF(IF(ISERROR(VLOOKUP(D17,Categorias!$B$4:$C$65,2,FALSE)),"",VLOOKUP(D17,Categorias!$B$4:$C$65,2,FALSE))=D17,"",VLOOKUP(D17,(Categorias!$B$2:$D$65),3,FALSE)) | J17: =IF(H17="",(""),IF(H17="DP",(J16+G17),IF(H17="DB",(J16-G17),IF(H17="TR",(J16-G17),IF(H17="CH",(J16-G17),IF(H17="SQ",(J16-G17),J16)))))) | K17: =IF(H17="",(""),IF(H17="SQ",(K16+G17),IF(H17="RD",(K16+G17),IF(H17="DI",(K16-G17),K16)))) | L17: =IF(H17="",(""),IF(H17="CC",(L16+G17),IF(H17="PC",(L16+G17),L16)))
B18: =IF(IF(ISERROR(VLOOKUP(D18,Categorias!$B$4:$C$65,2,FALSE)),"",VLOOKUP(D18,Categorias!$B$4:$C$65,2,FALSE))=D18,"",VLOOKUP(D18,(Categorias!$B$4:$C$65),2,FALSE)) | C18: =IF(IF(ISERROR(VLOOKUP(D18,Categorias!$B$4:$C$65,2,FALSE)),"",VLOOKUP(D18,Categorias!$B$4:$C$65,2,FALSE))=D18,"",VLOOKUP(D18,(Categorias!$B$2:$D$65),3,FALSE)) | J18: =IF(H18="",(""),IF(H18="DP",(J17+G18),IF(H18="DB",(J17-G18),IF(H18="TR",(J17-G18),IF(H18="CH",(J17-G18),IF(H18="SQ",(J17-G18),J17)))))) | K18: =IF(H18="",(""),IF(H18="SQ",(K17+G18),IF(H18="RD",(K17+G18),IF(H18="DI",(K17-G18),K17)))) | L18: =IF(H18="",(""),IF(H18="CC",(L17+G18),IF(H18="PC",(L17+G18),L17)))
... B75: =IF(IF(ISERROR(VLOOKUP(D75,Categorias!$B$4:$C$65,2,FALSE)),"",VLOOKUP(D75,Categorias!$B$4:$C$65,2,FALSE))=D75,"",VLOOKUP(D75,(Categorias!$B$4:$C$65),2,FALSE)) | C75: =IF(IF(ISERROR(VLOOKUP(D75,Categorias!$B$4:$C$65,2,FALSE)),"",VLOOKUP(D75,Categorias!$B$4:$C$65,2,FALSE))=D75,"",VLOOKUP(D75,(Categorias!$B$2:$D$65),3,FALSE)) | J75: =IF(H75="",(""),IF(H75="DP",(J74+G75),IF(H75="DB",(J74-G75),IF(H75="TR",(J74-G75),IF(H75="CH",(J74-G75),IF(H75="SQ",(J74-G75),J74)))))) | K75: =IF(H75="",(""),IF(H75="SQ",(K74+G75),IF(H75="RD",(K74+G75),IF(H75="DI",(K74-G75),K74)))) | L75: =IF(H75="",(""),IF(H75="CC",(L74+G75),IF(H75="PC",(L74+G75),L74)))
F76: Saldo no mês | J76: =+J75 | K76: =+K75 | L76: =+L75
A213: 1
A214: 1

Sheet Nov
C1: Orçamento Doméstico
B2: Descritivo de Receitas e Despesas realizadas | F2: Novembro | H2: =+'Instruções'!$I$19 -> #REF! | J2: Movimentação do saldo no mês
H3: Meio de pagamento | J3: Saldo do mês anterior
B4: Grupo de conta | C4: Sub-grupo de conta | D4: Cod. | E4: Data | F4: Descritivo | G4: Valor R$ | J4: C.Corrente (+ / -) | K4: Dinheiro (+ / -) | L4: C. de Crédito (+)
A6: 1 | B6: =IF(IF(ISERROR(VLOOKUP(D6,Categorias!$B$4:$C$65,2,FALSE)),"",VLOOKUP(D6,Categorias!$B$4:$C$65,2,FALSE))=D6,"",VLOOKUP(D6,(Categorias!$B$4:$C$65),2,FALSE)) | C6: =IF(IF(ISERROR(VLOOKUP(D6,Categorias!$B$4:$C$65,2,FALSE)),"",VLOOKUP(D6,Categorias!$B$4:$C$65,2,FALSE))=D6,"",VLOOKUP(D6,(Categorias!$B$2:$D$65),3,FALSE)) | J6: =IF(H6="",(""),IF(H6="DP",(J5+G6),IF(H6="DB",(J5-G6),IF(H6="TR",(J5-G6),IF(H6="CH",(J5-G6),IF(H6="SQ",(J5-G6),J5)))))) | K6: =IF(H6="",(""),IF(H6="SQ",(K5+G6),IF(H6="RD",(K5+G6),IF(H6="DI",(K5-G6),K5)))) | L6: =IF(H6="",(""),IF(H6="CC",(L5+G6),IF(H6="PC",(L5+G6),L5)))
B7: =IF(IF(ISERROR(VLOOKUP(D7,Categorias!$B$4:$C$65,2,FALSE)),"",VLOOKUP(D7,Categorias!$B$4:$C$65,2,FALSE))=D7,"",VLOOKUP(D7,(Categorias!$B$4:$C$65),2,FALSE)) | C7: =IF(IF(ISERROR(VLOOKUP(D7,Categorias!$B$4:$C$65,2,FALSE)),"",VLOOKUP(D7,Categorias!$B$4:$C$65,2,FALSE))=D7,"",VLOOKUP(D7,(Categorias!$B$2:$D$65),3,FALSE)) | J7: =IF(H7="",(""),IF(H7="DP",(J6+G7),IF(H7="DB",(J6-G7),IF(H7="TR",(J6-G7),IF(H7="CH",(J6-G7),IF(H7="SQ",(J6-G7),J6)))))) | K7: =IF(H7="",(""),IF(H7="SQ",(K6+G7),IF(H7="RD",(K6+G7),IF(H7="DI",(K6-G7),K6)))) | L7: =IF(H7="",(""),IF(H7="CC",(L6+G7),IF(H7="PC",(L6+G7),L6)))
B8: =IF(IF(ISERROR(VLOOKUP(D8,Categorias!$B$4:$C$65,2,FALSE)),"",VLOOKUP(D8,Categorias!$B$4:$C$65,2,FALSE))=D8,"",VLOOKUP(D8,(Categorias!$B$4:$C$65),2,FALSE)) | C8: =IF(IF(ISERROR(VLOOKUP(D8,Categorias!$B$4:$C$65,2,FALSE)),"",VLOOKUP(D8,Categorias!$B$4:$C$65,2,FALSE))=D8,"",VLOOKUP(D8,(Categorias!$B$2:$D$65),3,FALSE)) | J8: =IF(H8="",(""),IF(H8="DP",(J7+G8),IF(H8="DB",(J7-G8),IF(H8="TR",(J7-G8),IF(H8="CH",(J7-G8),IF(H8="SQ",(J7-G8),J7)))))) | K8: =IF(H8="",(""),IF(H8="SQ",(K7+G8),IF(H8="RD",(K7+G8),IF(H8="DI",(K7-G8),K7)))) | L8: =IF(H8="",(""),IF(H8="CC",(L7+G8),IF(H8="PC",(L7+G8),L7)))
B9: =IF(IF(ISERROR(VLOOKUP(D9,Categorias!$B$4:$C$65,2,FALSE)),"",VLOOKUP(D9,Categorias!$B$4:$C$65,2,FALSE))=D9,"",VLOOKUP(D9,(Categorias!$B$4:$C$65),2,FALSE)) | C9: =IF(IF(ISERROR(VLOOKUP(D9,Categorias!$B$4:$C$65,2,FALSE)),"",VLOOKUP(D9,Categorias!$B$4:$C$65,2,FALSE))=D9,"",VLOOKUP(D9,(Categorias!$B$2:$D$65),3,FALSE)) | J9: =IF(H9="",(""),IF(H9="DP",(J8+G9),IF(H9="DB",(J8-G9),IF(H9="TR",(J8-G9),IF(H9="CH",(J8-G9),IF(H9="SQ",(J8-G9),J8)))))) | K9: =IF(H9="",(""),IF(H9="SQ",(K8+G9),IF(H9="RD",(K8+G9),IF(H9="DI",(K8-G9),K8)))) | L9: =IF(H9="",(""),IF(H9="CC",(L8+G9),IF(H9="PC",(L8+G9),L8)))
B10: =IF(IF(ISERROR(VLOOKUP(D10,Categorias!$B$4:$C$65,2,FALSE)),"",VLOOKUP(D10,Categorias!$B$4:$C$65,2,FALSE))=D10,"",VLOOKUP(D10,(Categorias!$B$4:$C$65),2,FALSE)) | C10: =IF(IF(ISERROR(VLOOKUP(D10,Categorias!$B$4:$C$65,2,FALSE)),"",VLOOKUP(D10,Categorias!$B$4:$C$65,2,FALSE))=D10,"",VLOOKUP(D10,(Categorias!$B$2:$D$65),3,FALSE)) | J10: =IF(H10="",(""),IF(H10="DP",(J9+G10),IF(H10="DB",(J9-G10),IF(H10="TR",(J9-G10),IF(H10="CH",(J9-G10),IF(H10="SQ",(J9-G10),J9)))))) | K10: =IF(H10="",(""),IF(H10="SQ",(K9+G10),IF(H10="RD",(K9+G10),IF(H10="DI",(K9-G10),K9)))) | L10: =IF(H10="",(""),IF(H10="CC",(L9+G10),IF(H10="PC",(L9+G10),L9)))
B11: =IF(IF(ISERROR(VLOOKUP(D11,Categorias!$B$4:$C$65,2,FALSE)),"",VLOOKUP(D11,Categorias!$B$4:$C$65,2,FALSE))=D11,"",VLOOKUP(D11,(Categorias!$B$4:$C$65),2,FALSE)) | C11: =IF(IF(ISERROR(VLOOKUP(D11,Categorias!$B$4:$C$65,2,FALSE)),"",VLOOKUP(D11,Categorias!$B$4:$C$65,2,FALSE))=D11,"",VLOOKUP(D11,(Categorias!$B$2:$D$65),3,FALSE)) | J11: =IF(H11="",(""),IF(H11="DP",(J10+G11),IF(H11="DB",(J10-G11),IF(H11="TR",(J10-G11),IF(H11="CH",(J10-G11),IF(H11="SQ",(J10-G11),J10)))))) | K11: =IF(H11="",(""),IF(H11="SQ",(K10+G11),IF(H11="RD",(K10+G11),IF(H11="DI",(K10-G11),K10)))) | L11: =IF(H11="",(""),IF(H11="CC",(L10+G11),IF(H11="PC",(L10+G11),L10)))
B12: =IF(IF(ISERROR(VLOOKUP(D12,Categorias!$B$4:$C$65,2,FALSE)),"",VLOOKUP(D12,Categorias!$B$4:$C$65,2,FALSE))=D12,"",VLOOKUP(D12,(Categorias!$B$4:$C$65),2,FALSE)) | C12: =IF(IF(ISERROR(VLOOKUP(D12,Categorias!$B$4:$C$65,2,FALSE)),"",VLOOKUP(D12,Categorias!$B$4:$C$65,2,FALSE))=D12,"",VLOOKUP(D12,(Categorias!$B$2:$D$65),3,FALSE)) | J12: =IF(H12="",(""),IF(H12="DP",(J11+G12),IF(H12="DB",(J11-G12),IF(H12="TR",(J11-G12),IF(H12="CH",(J11-G12),IF(H12="SQ",(J11-G12),J11)))))) | K12: =IF(H12="",(""),IF(H12="SQ",(K11+G12),IF(H12="RD",(K11+G12),IF(H12="DI",(K11-G12),K11)))) | L12: =IF(H12="",(""),IF(H12="CC",(L11+G12),IF(H12="PC",(L11+G12),L11)))
B13: =IF(IF(ISERROR(VLOOKUP(D13,Categorias!$B$4:$C$65,2,FALSE)),"",VLOOKUP(D13,Categorias!$B$4:$C$65,2,FALSE))=D13,"",VLOOKUP(D13,(Categorias!$B$4:$C$65),2,FALSE)) | C13: =IF(IF(ISERROR(VLOOKUP(D13,Categorias!$B$4:$C$65,2,FALSE)),"",VLOOKUP(D13,Categorias!$B$4:$C$65,2,FALSE))=D13,"",VLOOKUP(D13,(Categorias!$B$2:$D$65),3,FALSE)) | J13: =IF(H13="",(""),IF(H13="DP",(J12+G13),IF(H13="DB",(J12-G13),IF(H13="TR",(J12-G13),IF(H13="CH",(J12-G13),IF(H13="SQ",(J12-G13),J12)))))) | K13: =IF(H13="",(""),IF(H13="SQ",(K12+G13),IF(H13="RD",(K12+G13),IF(H13="DI",(K12-G13),K12)))) | L13: =IF(H13="",(""),IF(H13="CC",(L12+G13),IF(H13="PC",(L12+G13),L12)))
B14: =IF(IF(ISERROR(VLOOKUP(D14,Categorias!$B$4:$C$65,2,FALSE)),"",VLOOKUP(D14,Categorias!$B$4:$C$65,2,FALSE))=D14,"",VLOOKUP(D14,(Categorias!$B$4:$C$65),2,FALSE)) | C14: =IF(IF(ISERROR(VLOOKUP(D14,Categorias!$B$4:$C$65,2,FALSE)),"",VLOOKUP(D14,Categorias!$B$4:$C$65,2,FALSE))=D14,"",VLOOKUP(D14,(Categorias!$B$2:$D$65),3,FALSE)) | J14: =IF(H14="",(""),IF(H14="DP",(J13+G14),IF(H14="DB",(J13-G14),IF(H14="TR",(J13-G14),IF(H14="CH",(J13-G14),IF(H14="SQ",(J13-G14),J13)))))) | K14: =IF(H14="",(""),IF(H14="SQ",(K13+G14),IF(H14="RD",(K13+G14),IF(H14="DI",(K13-G14),K13)))) | L14: =IF(H14="",(""),IF(H14="CC",(L13+G14),IF(H14="PC",(L13+G14),L13)))
B15: =IF(IF(ISERROR(VLOOKUP(D15,Categorias!$B$4:$C$65,2,FALSE)),"",VLOOKUP(D15,Categorias!$B$4:$C$65,2,FALSE))=D15,"",VLOOKUP(D15,(Categorias!$B$4:$C$65),2,FALSE)) | C15: =IF(IF(ISERROR(VLOOKUP(D15,Categorias!$B$4:$C$65,2,FALSE)),"",VLOOKUP(D15,Categorias!$B$4:$C$65,2,FALSE))=D15,"",VLOOKUP(D15,(Categorias!$B$2:$D$65),3,FALSE)) | J15: =IF(H15="",(""),IF(H15="DP",(J14+G15),IF(H15="DB",(J14-G15),IF(H15="TR",(J14-G15),IF(H15="CH",(J14-G15),IF(H15="SQ",(J14-G15),J14)))))) | K15: =IF(H15="",(""),IF(H15="SQ",(K14+G15),IF(H15="RD",(K14+G15),IF(H15="DI",(K14-G15),K14)))) | L15: =IF(H15="",(""),IF(H15="CC",(L14+G15),IF(H15="PC",(L14+G15),L14)))
B16: =IF(IF(ISERROR(VLOOKUP(D16,Categorias!$B$4:$C$65,2,FALSE)),"",VLOOKUP(D16,Categorias!$B$4:$C$65,2,FALSE))=D16,"",VLOOKUP(D16,(Categorias!$B$4:$C$65),2,FALSE)) | C16: =IF(IF(ISERROR(VLOOKUP(D16,Categorias!$B$4:$C$65,2,FALSE)),"",VLOOKUP(D16,Categorias!$B$4:$C$65,2,FALSE))=D16,"",VLOOKUP(D16,(Categorias!$B$2:$D$65),3,FALSE)) | J16: =IF(H16="",(""),IF(H16="DP",(J15+G16),IF(H16="DB",(J15-G16),IF(H16="TR",(J15-G16),IF(H16="CH",(J15-G16),IF(H16="SQ",(J15-G16),J15)))))) | K16: =IF(H16="",(""),IF(H16="SQ",(K15+G16),IF(H16="RD",(K15+G16),IF(H16="DI",(K15-G16),K15)))) | L16: =IF(H16="",(""),IF(H16="CC",(L15+G16),IF(H16="PC",(L15+G16),L15)))
B17: =IF(IF(ISERROR(VLOOKUP(D17,Categorias!$B$4:$C$65,2,FALSE)),"",VLOOKUP(D17,Categorias!$B$4:$C$65,2,FALSE))=D17,"",VLOOKUP(D17,(Categorias!$B$4:$C$65),2,FALSE)) | C17: =IF(IF(ISERROR(VLOOKUP(D17,Categorias!$B$4:$C$65,2,FALSE)),"",VLOOKUP(D17,Categorias!$B$4:$C$65,2,FALSE))=D17,"",VLOOKUP(D17,(Categorias!$B$2:$D$65),3,FALSE)) | J17: =IF(H17="",(""),IF(H17="DP",(J16+G17),IF(H17="DB",(J16-G17),IF(H17="TR",(J16-G17),IF(H17="CH",(J16-G17),IF(H17="SQ",(J16-G17),J16)))))) | K17: =IF(H17="",(""),IF(H17="SQ",(K16+G17),IF(H17="RD",(K16+G17),IF(H17="DI",(K16-G17),K16)))) | L17: =IF(H17="",(""),IF(H17="CC",(L16+G17),IF(H17="PC",(L16+G17),L16)))
B18: =IF(IF(ISERROR(VLOOKUP(D18,Categorias!$B$4:$C$65,2,FALSE)),"",VLOOKUP(D18,Categorias!$B$4:$C$65,2,FALSE))=D18,"",VLOOKUP(D18,(Categorias!$B$4:$C$65),2,FALSE)) | C18: =IF(IF(ISERROR(VLOOKUP(D18,Categorias!$B$4:$C$65,2,FALSE)),"",VLOOKUP(D18,Categorias!$B$4:$C$65,2,FALSE))=D18,"",VLOOKUP(D18,(Categorias!$B$2:$D$65),3,FALSE)) | J18: =IF(H18="",(""),IF(H18="DP",(J17+G18),IF(H18="DB",(J17-G18),IF(H18="TR",(J17-G18),IF(H18="CH",(J17-G18),IF(H18="SQ",(J17-G18),J17)))))) | K18: =IF(H18="",(""),IF(H18="SQ",(K17+G18),IF(H18="RD",(K17+G18),IF(H18="DI",(K17-G18),K17)))) | L18: =IF(H18="",(""),IF(H18="CC",(L17+G18),IF(H18="PC",(L17+G18),L17)))
... B75: =IF(IF(ISERROR(VLOOKUP(D75,Categorias!$B$4:$C$65,2,FALSE)),"",VLOOKUP(D75,Categorias!$B$4:$C$65,2,FALSE))=D75,"",VLOOKUP(D75,(Categorias!$B$4:$C$65),2,FALSE)) | C75: =IF(IF(ISERROR(VLOOKUP(D75,Categorias!$B$4:$C$65,2,FALSE)),"",VLOOKUP(D75,Categorias!$B$4:$C$65,2,FALSE))=D75,"",VLOOKUP(D75,(Categorias!$B$2:$D$65),3,FALSE)) | J75: =IF(H75="",(""),IF(H75="DP",(J74+G75),IF(H75="DB",(J74-G75),IF(H75="TR",(J74-G75),IF(H75="CH",(J74-G75),IF(H75="SQ",(J74-G75),J74)))))) | K75: =IF(H75="",(""),IF(H75="SQ",(K74+G75),IF(H75="RD",(K74+G75),IF(H75="DI",(K74-G75),K74)))) | L75: =IF(H75="",(""),IF(H75="CC",(L74+G75),IF(H75="PC",(L74+G75),L74)))
F76: Saldo no mês | J76: =+J75 | K76: =+K75 | L76: =+L75
A213: 1
A214: 1

Sheet Dez
C1: Orçamento Doméstico
B2: Descritivo de Receitas e Despesas realizadas | F2: Dezembro | H2: =+'Instruções'!$I$19 -> #REF! | J2: Movimentação do saldo no mês
H3: Meio de pagamento | J3: Saldo do mês anterior
B4: Grupo de conta | C4: Sub-grupo de conta | D4: Cod. | E4: Data | F4: Descritivo | G4: Valor R$ | J4: C.Corrente (+ / -) | K4: Dinheiro (+ / -) | L4: C. de Crédito (+)
J5: -165
A6: 1 | B6: =IF(IF(ISERROR(VLOOKUP(D6,Categorias!$B$4:$C$65,2,FALSE)),"",VLOOKUP(D6,Categorias!$B$4:$C$65,2,FALSE))=D6,"",VLOOKUP(D6,(Categorias!$B$4:$C$65),2,FALSE)) | C6: =IF(IF(ISERROR(VLOOKUP(D6,Categorias!$B$4:$C$65,2,FALSE)),"",VLOOKUP(D6,Categorias!$B$4:$C$65,2,FALSE))=D6,"",VLOOKUP(D6,(Categorias!$B$2:$D$65),3,FALSE)) | J6: =IF(H6="",(""),IF(H6="DP",(J5+G6),IF(H6="DB",(J5-G6),IF(H6="TR",(J5-G6),IF(H6="CH",(J5-G6),IF(H6="SQ",(J5-G6),J5)))))) | K6: =IF(H6="",(""),IF(H6="SQ",(K5+G6),IF(H6="RD",(K5+G6),IF(H6="DI",(K5-G6),K5)))) | L6: =IF(H6="",(""),IF(H6="CC",(L5+G6),IF(H6="PC",(L5+G6),L5)))
B7: =IF(IF(ISERROR(VLOOKUP(D7,Categorias!$B$4:$C$65,2,FALSE)),"",VLOOKUP(D7,Categorias!$B$4:$C$65,2,FALSE))=D7,"",VLOOKUP(D7,(Categorias!$B$4:$C$65),2,FALSE)) | C7: =IF(IF(ISERROR(VLOOKUP(D7,Categorias!$B$4:$C$65,2,FALSE)),"",VLOOKUP(D7,Categorias!$B$4:$C$65,2,FALSE))=D7,"",VLOOKUP(D7,(Categorias!$B$2:$D$65),3,FALSE)) | J7: =IF(H7="",(""),IF(H7="DP",(J6+G7),IF(H7="DB",(J6-G7),IF(H7="TR",(J6-G7),IF(H7="CH",(J6-G7),IF(H7="SQ",(J6-G7),J6)))))) | K7: =IF(H7="",(""),IF(H7="SQ",(K6+G7),IF(H7="RD",(K6+G7),IF(H7="DI",(K6-G7),K6)))) | L7: =IF(H7="",(""),IF(H7="CC",(L6+G7),IF(H7="PC",(L6+G7),L6)))
B8: =IF(IF(ISERROR(VLOOKUP(D8,Categorias!$B$4:$C$65,2,FALSE)),"",VLOOKUP(D8,Categorias!$B$4:$C$65,2,FALSE))=D8,"",VLOOKUP(D8,(Categorias!$B$4:$C$65),2,FALSE)) | C8: =IF(IF(ISERROR(VLOOKUP(D8,Categorias!$B$4:$C$65,2,FALSE)),"",VLOOKUP(D8,Categorias!$B$4:$C$65,2,FALSE))=D8,"",VLOOKUP(D8,(Categorias!$B$2:$D$65),3,FALSE)) | J8: =IF(H8="",(""),IF(H8="DP",(J7+G8),IF(H8="DB",(J7-G8),IF(H8="TR",(J7-G8),IF(H8="CH",(J7-G8),IF(H8="SQ",(J7-G8),J7)))))) | K8: =IF(H8="",(""),IF(H8="SQ",(K7+G8),IF(H8="RD",(K7+G8),IF(H8="DI",(K7-G8),K7)))) | L8: =IF(H8="",(""),IF(H8="CC",(L7+G8),IF(H8="PC",(L7+G8),L7)))
B9: =IF(IF(ISERROR(VLOOKUP(D9,Categorias!$B$4:$C$65,2,FALSE)),"",VLOOKUP(D9,Categorias!$B$4:$C$65,2,FALSE))=D9,"",VLOOKUP(D9,(Categorias!$B$4:$C$65),2,FALSE)) | C9: =IF(IF(ISERROR(VLOOKUP(D9,Categorias!$B$4:$C$65,2,FALSE)),"",VLOOKUP(D9,Categorias!$B$4:$C$65,2,FALSE))=D9,"",VLOOKUP(D9,(Categorias!$B$2:$D$65),3,FALSE)) | J9: =IF(H9="",(""),IF(H9="DP",(J8+G9),IF(H9="DB",(J8-G9),IF(H9="TR",(J8-G9),IF(H9="CH",(J8-G9),IF(H9="SQ",(J8-G9),J8)))))) | K9: =IF(H9="",(""),IF(H9="SQ",(K8+G9),IF(H9="RD",(K8+G9),IF(H9="DI",(K8-G9),K8)))) | L9: =IF(H9="",(""),IF(H9="CC",(L8+G9),IF(H9="PC",(L8+G9),L8)))
B10: =IF(IF(ISERROR(VLOOKUP(D10,Categorias!$B$4:$C$65,2,FALSE)),"",VLOOKUP(D10,Categorias!$B$4:$C$65,2,FALSE))=D10,"",VLOOKUP(D10,(Categorias!$B$4:$C$65),2,FALSE)) | C10: =IF(IF(ISERROR(VLOOKUP(D10,Categorias!$B$4:$C$65,2,FALSE)),"",VLOOKUP(D10,Categorias!$B$4:$C$65,2,FALSE))=D10,"",VLOOKUP(D10,(Categorias!$B$2:$D$65),3,FALSE)) | J10: =IF(H10="",(""),IF(H10="DP",(J9+G10),IF(H10="DB",(J9-G10),IF(H10="TR",(J9-G10),IF(H10="CH",(J9-G10),IF(H10="SQ",(J9-G10),J9)))))) | K10: =IF(H10="",(""),IF(H10="SQ",(K9+G10),IF(H10="RD",(K9+G10),IF(H10="DI",(K9-G10),K9)))) | L10: =IF(H10="",(""),IF(H10="CC",(L9+G10),IF(H10="PC",(L9+G10),L9)))
B11: =IF(IF(ISERROR(VLOOKUP(D11,Categorias!$B$4:$C$65,2,FALSE)),"",VLOOKUP(D11,Categorias!$B$4:$C$65,2,FALSE))=D11,"",VLOOKUP(D11,(Categorias!$B$4:$C$65),2,FALSE)) | C11: =IF(IF(ISERROR(VLOOKUP(D11,Categorias!$B$4:$C$65,2,FALSE)),"",VLOOKUP(D11,Categorias!$B$4:$C$65,2,FALSE))=D11,"",VLOOKUP(D11,(Categorias!$B$2:$D$65),3,FALSE)) | J11: =IF(H11="",(""),IF(H11="DP",(J10+G11),IF(H11="DB",(J10-G11),IF(H11="TR",(J10-G11),IF(H11="CH",(J10-G11),IF(H11="SQ",(J10-G11),J10)))))) | K11: =IF(H11="",(""),IF(H11="SQ",(K10+G11),IF(H11="RD",(K10+G11),IF(H11="DI",(K10-G11),K10)))) | L11: =IF(H11="",(""),IF(H11="CC",(L10+G11),IF(H11="PC",(L10+G11),L10)))
B12: =IF(IF(ISERROR(VLOOKUP(D12,Categorias!$B$4:$C$65,2,FALSE)),"",VLOOKUP(D12,Categorias!$B$4:$C$65,2,FALSE))=D12,"",VLOOKUP(D12,(Categorias!$B$4:$C$65),2,FALSE)) | C12: =IF(IF(ISERROR(VLOOKUP(D12,Categorias!$B$4:$C$65,2,FALSE)),"",VLOOKUP(D12,Categorias!$B$4:$C$65,2,FALSE))=D12,"",VLOOKUP(D12,(Categorias!$B$2:$D$65),3,FALSE)) | J12: =IF(H12="",(""),IF(H12="DP",(J11+G12),IF(H12="DB",(J11-G12),IF(H12="TR",(J11-G12),IF(H12="CH",(J11-G12),IF(H12="SQ",(J11-G12),J11)))))) | K12: =IF(H12="",(""),IF(H12="SQ",(K11+G12),IF(H12="RD",(K11+G12),IF(H12="DI",(K11-G12),K11)))) | L12: =IF(H12="",(""),IF(H12="CC",(L11+G12),IF(H12="PC",(L11+G12),L11)))
B13: =IF(IF(ISERROR(VLOOKUP(D13,Categorias!$B$4:$C$65,2,FALSE)),"",VLOOKUP(D13,Categorias!$B$4:$C$65,2,FALSE))=D13,"",VLOOKUP(D13,(Categorias!$B$4:$C$65),2,FALSE)) | C13: =IF(IF(ISERROR(VLOOKUP(D13,Categorias!$B$4:$C$65,2,FALSE)),"",VLOOKUP(D13,Categorias!$B$4:$C$65,2,FALSE))=D13,"",VLOOKUP(D13,(Categorias!$B$2:$D$65),3,FALSE)) | J13: =IF(H13="",(""),IF(H13="DP",(J12+G13),IF(H13="DB",(J12-G13),IF(H13="TR",(J12-G13),IF(H13="CH",(J12-G13),IF(H13="SQ",(J12-G13),J12)))))) | K13: =IF(H13="",(""),IF(H13="SQ",(K12+G13),IF(H13="RD",(K12+G13),IF(H13="DI",(K12-G13),K12)))) | L13: =IF(H13="",(""),IF(H13="CC",(L12+G13),IF(H13="PC",(L12+G13),L12)))
B14: =IF(IF(ISERROR(VLOOKUP(D14,Categorias!$B$4:$C$65,2,FALSE)),"",VLOOKUP(D14,Categorias!$B$4:$C$65,2,FALSE))=D14,"",VLOOKUP(D14,(Categorias!$B$4:$C$65),2,FALSE)) | C14: =IF(IF(ISERROR(VLOOKUP(D14,Categorias!$B$4:$C$65,2,FALSE)),"",VLOOKUP(D14,Categorias!$B$4:$C$65,2,FALSE))=D14,"",VLOOKUP(D14,(Categorias!$B$2:$D$65),3,FALSE)) | J14: =IF(H14="",(""),IF(H14="DP",(J13+G14),IF(H14="DB",(J13-G14),IF(H14="TR",(J13-G14),IF(H14="CH",(J13-G14),IF(H14="SQ",(J13-G14),J13)))))) | K14: =IF(H14="",(""),IF(H14="SQ",(K13+G14),IF(H14="RD",(K13+G14),IF(H14="DI",(K13-G14),K13)))) | L14: =IF(H14="",(""),IF(H14="CC",(L13+G14),IF(H14="PC",(L13+G14),L13)))
B15: =IF(IF(ISERROR(VLOOKUP(D15,Categorias!$B$4:$C$65,2,FALSE)),"",VLOOKUP(D15,Categorias!$B$4:$C$65,2,FALSE))=D15,"",VLOOKUP(D15,(Categorias!$B$4:$C$65),2,FALSE)) | C15: =IF(IF(ISERROR(VLOOKUP(D15,Categorias!$B$4:$C$65,2,FALSE)),"",VLOOKUP(D15,Categorias!$B$4:$C$65,2,FALSE))=D15,"",VLOOKUP(D15,(Categorias!$B$2:$D$65),3,FALSE)) | J15: =IF(H15="",(""),IF(H15="DP",(J14+G15),IF(H15="DB",(J14-G15),IF(H15="TR",(J14-G15),IF(H15="CH",(J14-G15),IF(H15="SQ",(J14-G15),J14)))))) | K15: =IF(H15="",(""),IF(H15="SQ",(K14+G15),IF(H15="RD",(K14+G15),IF(H15="DI",(K14-G15),K14)))) | L15: =IF(H15="",(""),IF(H15="CC",(L14+G15),IF(H15="PC",(L14+G15),L14)))
B16: =IF(IF(ISERROR(VLOOKUP(D16,Categorias!$B$4:$C$65,2,FALSE)),"",VLOOKUP(D16,Categorias!$B$4:$C$65,2,FALSE))=D16,"",VLOOKUP(D16,(Categorias!$B$4:$C$65),2,FALSE)) | C16: =IF(IF(ISERROR(VLOOKUP(D16,Categorias!$B$4:$C$65,2,FALSE)),"",VLOOKUP(D16,Categorias!$B$4:$C$65,2,FALSE))=D16,"",VLOOKUP(D16,(Categorias!$B$2:$D$65),3,FALSE)) | J16: =IF(H16="",(""),IF(H16="DP",(J15+G16),IF(H16="DB",(J15-G16),IF(H16="TR",(J15-G16),IF(H16="CH",(J15-G16),IF(H16="SQ",(J15-G16),J15)))))) | K16: =IF(H16="",(""),IF(H16="SQ",(K15+G16),IF(H16="RD",(K15+G16),IF(H16="DI",(K15-G16),K15)))) | L16: =IF(H16="",(""),IF(H16="CC",(L15+G16),IF(H16="PC",(L15+G16),L15)))
B17: =IF(IF(ISERROR(VLOOKUP(D17,Categorias!$B$4:$C$65,2,FALSE)),"",VLOOKUP(D17,Categorias!$B$4:$C$65,2,FALSE))=D17,"",VLOOKUP(D17,(Categorias!$B$4:$C$65),2,FALSE)) | C17: =IF(IF(ISERROR(VLOOKUP(D17,Categorias!$B$4:$C$65,2,FALSE)),"",VLOOKUP(D17,Categorias!$B$4:$C$65,2,FALSE))=D17,"",VLOOKUP(D17,(Categorias!$B$2:$D$65),3,FALSE)) | J17: =IF(H17="",(""),IF(H17="DP",(J16+G17),IF(H17="DB",(J16-G17),IF(H17="TR",(J16-G17),IF(H17="CH",(J16-G17),IF(H17="SQ",(J16-G17),J16)))))) | K17: =IF(H17="",(""),IF(H17="SQ",(K16+G17),IF(H17="RD",(K16+G17),IF(H17="DI",(K16-G17),K16)))) | L17: =IF(H17="",(""),IF(H17="CC",(L16+G17),IF(H17="PC",(L16+G17),L16)))
B18: =IF(IF(ISERROR(VLOOKUP(D18,Categorias!$B$4:$C$65,2,FALSE)),"",VLOOKUP(D18,Categorias!$B$4:$C$65,2,FALSE))=D18,"",VLOOKUP(D18,(Categorias!$B$4:$C$65),2,FALSE)) | C18: =IF(IF(ISERROR(VLOOKUP(D18,Categorias!$B$4:$C$65,2,FALSE)),"",VLOOKUP(D18,Categorias!$B$4:$C$65,2,FALSE))=D18,"",VLOOKUP(D18,(Categorias!$B$2:$D$65),3,FALSE)) | J18: =IF(H18="",(""),IF(H18="DP",(J17+G18),IF(H18="DB",(J17-G18),IF(H18="TR",(J17-G18),IF(H18="CH",(J17-G18),IF(H18="SQ",(J17-G18),J17)))))) | K18: =IF(H18="",(""),IF(H18="SQ",(K17+G18),IF(H18="RD",(K17+G18),IF(H18="DI",(K17-G18),K17)))) | L18: =IF(H18="",(""),IF(H18="CC",(L17+G18),IF(H18="PC",(L17+G18),L17)))
... B75: =IF(IF(ISERROR(VLOOKUP(D75,Categorias!$B$4:$C$65,2,FALSE)),"",VLOOKUP(D75,Categorias!$B$4:$C$65,2,FALSE))=D75,"",VLOOKUP(D75,(Categorias!$B$4:$C$65),2,FALSE)) | C75: =IF(IF(ISERROR(VLOOKUP(D75,Categorias!$B$4:$C$65,2,FALSE)),"",VLOOKUP(D75,Categorias!$B$4:$C$65,2,FALSE))=D75,"",VLOOKUP(D75,(Categorias!$B$2:$D$65),3,FALSE)) | J75: =IF(H75="",(""),IF(H75="DP",(J74+G75),IF(H75="DB",(J74-G75),IF(H75="TR",(J74-G75),IF(H75="CH",(J74-G75),IF(H75="SQ",(J74-G75),J74)))))) | K75: =IF(H75="",(""),IF(H75="SQ",(K74+G75),IF(H75="RD",(K74+G75),IF(H75="DI",(K74-G75),K74)))) | L75: =IF(H75="",(""),IF(H75="CC",(L74+G75),IF(H75="PC",(L74+G75),L74)))
F76: Saldo no mês | J76: =+J75 | K76: =+K75 | L76: =+L75
A213: 1
A214: 1

Sheet Receitas 2026
B2: Receitas | O2: Ano: | P2: 2026
B4: Período | C4: 46023 | D4: 46054 | E4: 46082 | F4: 46113 | G4: 46143 | H4: 46174 | I4: 46204 | J4: 46235 | K4: 46266 | L4: 46296 | M4: 46327 | N4: 46357 | O4: Total | P4: Média
B6: Receitas Totais | C6: =SUM(C7:C11) -> 34767.64 | D6: =SUM(D7:D11) -> 4760.54 | E6: =SUM(E7:E11) -> 16430.54 | F6: =SUM(F7:F11) -> 39079.43 | G6: =SUM(G7:G11) -> 0 | H6: =SUM(H7:H11) -> 0 | I6: =SUM(I7:I11) -> 0 | J6: =SUM(J7:J11) -> 0 | ... N6: =SUM(N7:N11) -> 0 | O6: =SUM(C6:N6) -> 95038.15 | P6: =AVERAGE(C6:O6) -> 14621.254
B7: =B13 -> Entradas Roberto | C7: =C13 -> 30000 | D7: =D13 -> 0 | E7: =E13 -> 11120 | F7: =F13 -> 25704 | G7: =G13 -> 0 | H7: =H13 -> 0 | I7: =I13 -> 0 | ... N7: =N13 -> 0 | O7: =SUM(C7:N7) -> 66824 | P7: =AVERAGE(C7:O7) -> 10280.615
B8: =B20 -> Entradas Mariana | C8: =C20 -> 1250 | D8: =D20 -> 1250 | E8: =E20 -> 1800 | F8: =F20 -> 1250 | G8: =G20 -> 0 | H8: =H20 -> 0 | I8: =I20 -> 0 | ... N8: =N20 -> 0 | O8: =SUM(C8:N8) -> 5550 | P8: =AVERAGE(C8:O8) -> 853.84615
B9: =B27 -> Entradas Manuela | C9: =C27 -> 3517.64 | D9: =D28 -> 3510.54 | E9: =E27 -> 3510.54 | F9: =F27 -> 12125.43 | G9: =G27 -> 0 | H9: =H27 -> 0 | I9: =I27 -> 0 | J9: =J27 -> 0 | K9: =K27 -> 0 | L9: =L27 -> 0 | ... N9: =N27 -> 0 | O9: =SUM(C9:N9) -> 22664.15 | P9: =AVERAGE(C9:O9) -> 3486.7923
B10: Saldo Mês Anterior | O10: =SUM(C10:N10) -> 0 | P10: =AVERAGE(D10:O10) -> 0
O11: =SUM(C11:N11) -> 0 | P11: =AVERAGE(D11:O11) -> 0
B13: Entradas Roberto | C13: =SUM(C14:C18) -> 30000 | D13: =SUM(D14:D18) -> 0 | E13: =SUM(E14:E18) -> 11120 | F13: =SUM(F14:F18) -> 25704 | G13: =SUM(G14:G18) -> 0 | H13: =SUM(H14:H18) -> 0 | I13: =SUM(I14:I18) -> 0 | J13: =SUM(J14:J18) -> 0 | ... O13: =SUM(O14:O18) -> 61824 | P13: =AVERAGE(P14:P18) -> 10243.2
B14: Mastercard | C14: 30000 | O14: =SUM(C14:N14) -> 30000 | P14: =AVERAGE(C14:O14) -> 30000
B15: Bridge (Contrato I) | E15: 6120 | F15: 25704 | O15: =SUM(C15:N15) -> 31824 | P15: =AVERAGE(C15:O15) -> 21216
B16: Empréstimos | E16: 5000 | O16: =SUM(F16:N16) -> 0 | P16: =AVERAGE(F16:O16) -> 0
O17: =SUM(C17:N17) -> 0 | P17: =AVERAGE(D17:O17) -> 0
O18: =SUM(C18:N18) -> 0 | P18: =AVERAGE(D18:O18) -> 0
B20: Entradas Mariana | C20: =SUM(C21:C23) -> 1250 | D20: =SUM(D21:D23) -> 1250 | E20: =SUM(E21:E25) -> 1800 | F20: =SUM(F21:F23) -> 1250 | G20: =SUM(G21:G23) -> 0 | H20: =SUM(H21:H23) -> 0 | I20: =SUM(I21:I23) -> 0 | J20: =SUM(J21:J23) -> 0 | K20: =SUM(K21:K23) -> 0 | L20: =SUM(L21:L23) -> 0 | M20: =SUM(M21:M23) -> 0 | ... O20: =SUM(O21:O23) -> 5000 | P20: =AVERAGE(P21:P28) -> 1490.4032
B21: Estágio/Consultoria | O21: =SUM(C21:N21) -> 0 | P21: =AVERAGE(D21:O21) -> 0
B22: Processo Trabalhista | O22: =SUM(C22:N22) -> 0 | P22: =AVERAGE(D22:O22) -> 0
B23: Parcelas Filipe | C23: 1250 | D23: 1250 | E23: 1250 | F23: 1250 | O23: =SUM(C23:N23) -> 5000 | P23: =AVERAGE(C23:O23) -> 2000
B24: Vendas | O24: =SUM(C24:N24) -> 0 | P24: =AVERAGE(D24:O24) -> 0
B25: Empréstimos | E25: 550 | O25: =SUM(C25:N25) -> 550 | P25: =AVERAGE(C25:O25) -> 550
B27: Entradas Manuela | C27: =SUM(C28:C30) -> 3517.64 | D27: =SUM(D28:D30) -> 3510.54 | E27: =SUM(E28:E30) -> 3510.54 | F27: =SUM(F28:F30) -> 12125.43 | G27: =SUM(G28:G30) -> 0 | H27: =SUM(H28:H30) -> 0 | I27: =SUM(I28:I30) -> 0 | J27: =SUM(J28:J30) -> 0 | ... O27: =SUM(O28:O30) -> 22664.15 | P27: =AVERAGE(C28:P32) -> 2613.4621
B28: Pensão Mensal | C28: 3517.64 | D28: 3510.54 | E28: 3510.54 | O28: =SUM(C28:N28) -> 10538.72 | P28: =AVERAGE(C28:O28) -> 5269.36
B29: Pensão (Décimo Terceiro) | O29: =SUM(C29:N29) -> 0 | P29: =AVERAGE(D29:O29) -> 0
B30: Pensão (PLR) | F30: 12125.43 | O30: =SUM(C30:N30) -> 12125.43 | P30: =AVERAGE(D30:O30) -> 12125.43
B32: Não Programadas | C32: =SUM(C33:C34) -> 0 | D32: =SUM(D33:D34) -> 0 | E32: =SUM(E33:E34) -> 0 | F32: =SUM(F33:F34) -> 0 | G32: =SUM(G33:G34) -> 0 | H32: =SUM(H33:H34) -> 0 | I32: =SUM(I33:I34) -> 0 | J32: =SUM(J33:J34) -> 0 | ... O32: =SUM(O33:O34) -> 0 | P32: =AVERAGE(P33:P39) -> 0
O34: =SUM(C34:N34) -> 0 | P34: =AVERAGE(D34:O34) -> 0
O35: =SUM(C35:N35) -> 0 | P35: =AVERAGE(D35:O35) -> 0
O36: =SUM(C36:N36) -> 0 | P36: =AVERAGE(D36:O36) -> 0

Sheet Despesas 2026
B2: Despesas | C2: 46141 | AA2: Ano: | AB2: 2026
B4: Período | C4: 46023 | E4: 46054 | G4: 46082 | I4: 46113 | K4: 46143 | M4: 46174 | O4: 46204 | Q4: 46235 | S4: 46266 | U4: 46296 | W4: 46327 | Y4: 46357 | AA4: Total | AB4: Média
B6: Despesas Totais | C6: =sum(C9:D21) -> 33201.55 | E6: =F8+C8 -> 14581.58 | G6: =H8+E8 -> 15775.83 | I6: =J8+G8 -> 39389.19 | K6: =L8+I8 -> 7885.4 | M6: =N8+K8 -> 273.21 | O6: =sum(O9:P21) -> 0 | Q6: =sum(Q9:R21) -> 0 | S6: =sum(S9:T21) -> 0 | U6: =sum(U9:V21) -> 0 | W6: =sum(W9:X21) -> 0 | Y6: =sum(Y9:Z21) -> 0 | AA6: =sum(AA9:AA20) -> 102300.81 | AB6: =AVERAGE(D6:N6) -> 15581.042
B7: Meio de Pagamento | C7: Cartão | D7: Dinheiro | E7: Cartão | F7: Dinheiro | G7: Cartão | H7: Dinheiro | I7: Cartão | J7: Dinheiro | K7: Cartão | L7: Dinheiro | M7: Cartão | N7: Dinheiro | O7: Cartão | P7: Dinheiro | Q7: Cartão | R7: Dinheiro | S7: Cartão | T7: Dinheiro | U7: Cartão | V7: Dinheiro | W7: Cartão | X7: Dinheiro | Y7: Cartão | Z7: Dinheiro
B8: Sub-Total Despesas | C8: =SUM(C9:C21) -> 8882.18 | D8: =SUM(D9:D21) -> 24319.37 | E8: =SUM(E9:E21) -> 8594.53 | F8: =SUM(F9:F21) -> 5699.4 | G8: =SUM(G9:G21) -> 10517.84 | H8: =SUM(H9:H21) -> 7181.3 | I8: =SUM(I9:I21) -> 7885.4 | J8: =SUM(J9:J21) -> 28871.35 | ... N8: =SUM(N9:N21) -> 0
B9: =B23 -> Moradia | C9: =C23 -> 629.06 | D9: =D23 -> 4841.36 | E9: =E23 -> 344.91 | F9: =F23 -> 3500 | G9: =G23 -> 538.59 | H9: =H23 -> 4168.09 | I9: =I23 -> 432.64 | ... N9: =N23 -> 0 | AA9: =SUM(C9:N9) -> 20296.33 | AB9: =AVERAGE(C9:N9) -> 1691.3608
B10: =B41 -> Alimentação | C10: =C41 -> 1887.85 | D10: =D41 -> 1956.43 | E10: =E41 -> 1855.14 | F10: =F41 -> 703.13 | G10: =G41 -> 2714.46 | H10: =H41 -> 726.89 | I10: =I41 -> 333.88 | ... N10: =N41 -> 0 | AA10: =SUM(C10:N10) -> 12789.21 | AB10: =AVERAGE(C10:N10) -> 1065.7675
B11: =B51 -> Transporte | C11: =C51 -> 2633.63 | D11: =D51 -> 267.81 | E11: =E51 -> 2941.21 | F11: =F51 -> 331.41 | G11: =G51 -> 2788.85 | H11: =H51 -> 465.39 | I11: =I51 -> 2609.15 | ... N11: =N51 -> 0 | AA11: =SUM(C11:N11) -> 12402.08 | AB11: =AVERAGE(C11:N11) -> 1033.5067
B12: =B67 -> Saúde | C12: =C67 -> 0 | D12: =D67 -> 531.38 | E12: =E67 -> 89.91 | F12: =F67 -> 25.58 | G12: =G67 -> 173.1 | H12: =H67 -> 0 | I12: =I67 -> 310.65 | ... N12: =N67 -> 0 | AA12: =SUM(C12:N12) -> 1165.16 | AB12: =AVERAGE(C12:N12) -> 97.096667
B13: =B76 -> Pessoal | C13: =C76 -> 1794.11 | D13: =D76 -> 1100.84 | E13: =E76 -> 2174.74 | F13: =F76 -> 503.58 | G13: =G76 -> 794.74 | H13: =H76 -> 895.55 | I13: =I76 -> 2062.39 | ... N13: =N76 -> 0 | AA13: =SUM(C13:N13) -> 12499.28 | AB13: =AVERAGE(C13:N13) -> 1041.6067
B14: =B87 -> Dogs | C14: =C87 -> 205 | D14: =D87 -> 84.89 | E14: =E87 -> 389.85 | F14: =F87 -> 0 | G14: =G87 -> 723.25 | H14: =H87 -> 0 | I14: =I87 -> 696.29 | ... N14: =N87 -> 0 | AA14: =SUM(C14:N14) -> 2099.28 | AB14: =AVERAGE(C14:N14) -> 174.94
B15: =B95 -> Lazer | C15: =C95 -> 1201.4 | D15: =D95 -> 608.84 | E15: =E95 -> 740.39 | F15: =F95 -> 336.75 | G15: =G95 -> 681.91 | H15: =H95 -> 173.77 | I15: =I95 -> 1140.73 | ... N15: =N95 -> 0 | AA15: =SUM(C15:N15) -> 6380.7 | AB15: =AVERAGE(C15:N15) -> 531.725
B16: =B103 -> Despesas Financeiras | C16: =C103 -> 0 | D16: =D103 -> 4175.93 | E16: =E103 -> 0 | F16: =F103 -> 165.27 | G16: =G103 -> 216.2 | H16: =H103 -> 420.27 | I16: =I103 -> -43.32 | ... N16: =N103 -> 0 | AA16: =SUM(C16:N16) -> 9268.82 | AB16: =AVERAGE(C16:N16) -> 772.40167
B17: =B115 -> Cartões & Wallets | C17: =C115 -> 277.65 | D17: =D115 -> 8503.75 | E17: =E115 -> -1165.66 | F17: =F115 -> 125.18 | G17: =G115 -> 1293.47 | H17: =H115 -> 249.34 | I17: =I115 -> 0 | ... N17: =N115 -> 0 | AA17: =SUM(C17:N17) -> 10190.52 | AB17: =AVERAGE(C17:N17) -> 849.21
B18: =B125 -> Roberto Individual | C18: =C125 -> 253.48 | D18: =D125 -> 1500 | E18: =E125 -> 222.41 | F18: =F125 -> 0 | G18: =G125 -> 274.89 | H18: =H125 -> 0 | I18: =I125 -> 133.75 | ... N18: =N125 -> 0 | AA18: =SUM(C18:N18) -> 6284.53 | AB18: =AVERAGE(C18:N18) -> 523.71083
B19: =B133 -> Mariana Individual | C19: =C133 -> 0 | D19: =D133 -> 748.14 | E19: =E133 -> 782.14 | F19: =F133 -> 8.5 | G19: =G133 -> 187.88 | H19: =H133 -> 82 | I19: =I133 -> 169.28 | ... N19: =N133 -> 0 | AA19: =SUM(C19:N19) -> 4254.95 | AB19: =AVERAGE(C19:N19) -> 354.57917
B20: =B141 -> Manuela Individual | C20: =C141 -> 0 | D20: =D141 -> 0 | E20: =E141 -> 219.49 | F20: =F141 -> 0 | G20: =G141 -> 130.5 | H20: =H141 -> 0 | I20: =I141 -> 39.96 | ... N20: =N141 -> 0 | AA20: =SUM(C20:N20) -> 4669.95 | AB20: =AVERAGE(C20:N20) -> 389.1625
B21: =B149 -> Despesas Extraordinárias | C21: =C149 -> 0 | D21: =D149 -> 0 | E21: =E149 -> 0 | F21: =F149 -> 0 | G21: =G149 -> 0 | H21: =H149 -> 0 | I21: =I149 -> 0 | ... N21: =N149 -> 0 | AA21: =SUM(C21:N21) -> 0 | AB21: =AVERAGE(C21:N21) -> 0
B23: Moradia | C23: =SUM(C25:C39) -> 629.06 | D23: =SUM(D25:D39) -> 4841.36 | E23: =SUM(E25:E39) -> 344.91 | F23: =SUM(F25:F39) -> 3500 | G23: =SUM(G25:G39) -> 538.59 | H23: =SUM(H25:H39) -> 4168.09 | I23: =SUM(I25:I39) -> 432.64 | J23: =SUM(J25:J39) -> 5689.22 | ... N23: =SUM(N25:N39) -> 0 | O23: =sum(O25:P39) -> 0 | Q23: =sum(Q25:R39) -> 0 | S23: =sum(S25:T39) -> 0 | U23: =sum(U25:V39) -> 0 | W23: =sum(W25:X39) -> 0 | Y23: =sum(Y25:Z39) -> 0 | AA23: =SUM(AA25:AA39) -> 19739.25 | AB23: =AVERAGE(AB25:AB30) -> 1234.8456
B24: Meio de Pagamento | C24: Cartão | D24: Dinheiro | E24: Cartão | F24: Dinheiro | G24: Cartão | H24: Dinheiro | I24: Cartão | J24: Dinheiro | K24: Cartão | L24: Dinheiro | M24: Cartão | N24: Dinheiro | O24: Cartão | P24: Dinheiro | Q24: Cartão | R24: Dinheiro | S24: Cartão | T24: Dinheiro | U24: Cartão | V24: Dinheiro | W24: Cartão | X24: Dinheiro | Y24: Cartão | Z24: Dinheiro
B25: Aluguel | D25: 3500 | F25: 3500 | H25: 3500 | J25: 3500 | AA25: =SUM(C25:N25) -> 14000 | AB25: =AVERAGE(C25:AA25) -> 5600
B26: Energia Elétrica | D26: 212.43 | H26: 253.41 | J26: 509.7 | AA26: =SUM(C26:N26) -> 975.54 | AB26: =AVERAGE(C26:AA26) -> 487.77
B27: Água e Saneamento | D27: 273.76 | H27: 311.72 | J27: 373.94 | AA27: =SUM(C27:N27) -> 959.42 | AB27: =AVERAGE(C27:AA27) -> 479.71
B28: TV / Internet / Telefones | D28: 295.33 | G28: 309 | J28: 600.85 | AA28: =SUM(C28:N28) -> 1205.18 | AB28: =AVERAGE(C28:AA28) -> 602.59
B29: Reparos e Manutenção | J29: 115 | AA29: =SUM(C29:N29) -> 115 | AB29: =AVERAGE(C29:AA29) -> 115
B30: Outras despesas | C30: 25.9 | D30: 48 | E30: 120 | I30: 129.11 | J30: 49 | AA30: =SUM(C30:N30) -> 372.01 | AB30: =AVERAGE(C30:AA30) -> 124.00333
B31: Móveis, itens casa | C31: 503.61 | D31: 511.84 | E31: 76.23 | G31: 76.14 | H31: 102.96 | I31: 148.13 | J31: 540.73 | K31: 76.23 | M31: 76.23 | AA31: =SUM(C31:N31) -> 2112.1 | AB31: =AVERAGE(C31:AA31) -> 422.42
B32: Netflix
B33: Hbo | C33: 18.9 | E33: 18.9 | AB33: =AVERAGE(C33:AA33) -> 18.9
B34: Spotfy | C34: 40.9 | E34: 40.9 | G34: 40.9 | I34: 40.9 | AB34: =AVERAGE(C34:AA34) -> 40.9
B35: Amazon Prime | C35: 13.9 | E35: 13.9 | G35: 13.9 | I35: 13.9 | AB35: =AVERAGE(C35:AA35) -> 13.9
B36: Apple | C36: 19.9 | E36: 69.03 | G36: 92.7 | I36: 88.7 | AB36: =AVERAGE(C36:AA36) -> 67.5825
B37: Ifood | C37: 5.95 | E37: 5.95 | G37: 5.95 | I37: 11.9 | AB37: =AVERAGE(C37:AA37) -> 7.4375
AA39: =SUM(C39:N39) -> 0 | AB39: =AVERAGE(C39:AA39) -> 0
B41: Alimentação | C41: =SUM(C43:C49) -> 1887.85 | D41: =SUM(D43:D49) -> 1956.43 | E41: =SUM(E43:E49) -> 1855.14 | F41: =SUM(F43:F49) -> 703.13 | G41: =SUM(G43:G49) -> 2714.46 | H41: =SUM(H43:H49) -> 726.89 | I41: =SUM(I43:I49) -> 333.88 | J41: =SUM(J43:J49) -> 2611.43 | ... N41: =SUM(N43:N49) -> 0 | O41: =sum(O43:P49) -> 0 | Q41: =sum(Q43:R49) -> 0 | S41: =sum(S43:T49) -> 0 | U41: =sum(U43:V49) -> 0 | W41: =sum(W43:X49) -> 0 | Y41: =sum(Y43:Z49) -> 0 | AA41: =SUM(AA43:AA48) -> 12627.21 | AB41: =AVERAGE(AB43:AB48) -> 551.56957
B42: Meio de Pagamento | C42: Cartão | D42: Dinheiro | E42: Cartão | F42: Dinheiro | G42: Cartão | H42: Dinheiro | I42: Cartão | J42: Dinheiro | K42: Cartão | L42: Dinheiro | M42: Cartão | N42: Dinheiro | O42: Cartão | P42: Dinheiro | Q42: Cartão | R42: Dinheiro | S42: Cartão | T42: Dinheiro | U42: Cartão | V42: Dinheiro | W42: Cartão | X42: Dinheiro | Y42: Cartão | Z42: Dinheiro
B43: Supermercado | C43: 1856.92 | D43: 1783.47 | E43: 1623.41 | F43: 164.1 | G43: 2349.54 | H43: 163.65 | I43: 284.43 | J43: 1569.2 | AA43: =SUM(C43:N43) -> 9794.72 | AB43: =AVERAGE(C43:AA43) -> 2176.6044
B44: Feira / Sacolão | F44: 393.91 | G44: 235.01 | H44: 312.66 | J44: 818.26 | AA44: =SUM(C44:N44) -> 1759.84 | AB44: =AVERAGE(C44:AA44) -> 703.936
B45: Padaria | C45: 30.93 | D45: 45.29 | E45: 58.42 | F45: 5.69 | G45: 93.91 | H45: 22.22 | J45: 31.88 | AA45: =SUM(C45:N45) -> 288.34 | AB45: =AVERAGE(C45:AA45) -> 72.085
B46: Açougue | F46: 121.43 | H46: 210.36 | J46: 98.89 | AA46: =SUM(C46:N46) -> 430.68 | AB46: =AVERAGE(C46:AA46) -> 215.34
B47: Nespresso | AA47: =SUM(C47:N47) -> 0 | AB47: =AVERAGE(C47:AA47) -> 0
B48: Sorveteria | D48: 91.67 | E48: 155.31 | I48: 49.45 | J48: 57.2 | AA48: =SUM(C48:N48) -> 353.63 | AB48: =AVERAGE(C48:AA48) -> 141.452
B49: Agua | D49: 36 | E49: 18 | F49: 18 | G49: 36 | H49: 18 | J49: 36 | AA49: =SUM(C49:N49) -> 162 | AB49: =AVERAGE(C49:AA49) -> 46.285714
B51: Transporte | C51: =SUM(C53:C65) -> 2633.63 | D51: =SUM(D53:D65) -> 267.81 | E51: =SUM(E53:E65) -> 2941.21 | F51: =SUM(F53:F65) -> 331.41 | G51: =SUM(G53:G65) -> 2788.85 | H51: =SUM(H53:H65) -> 465.39 | I51: =SUM(I53:I65) -> 2609.15 | J51: =SUM(J53:J65) -> 364.63 | ... N51: =SUM(N53:N65) -> 0 | O51: =sum(O53:P65) -> 0 | Q51: =sum(Q53:R65) -> 0 | S51: =sum(S53:T65) -> 0 | U51: =sum(U53:V65) -> 0 | W51: =sum(W53:X65) -> 0 | Y51: =sum(Y53:Z65) -> 0 | AA51: =SUM(AA53:AA65) -> 12402.08 | AB51: =AVERAGE(AB53:AB58) -> 745.53837
B52: Meio de Pagamento | C52: Cartão | D52: Dinheiro | E52: Cartão | F52: Dinheiro | G52: Cartão | H52: Dinheiro | I52: Cartão | J52: Dinheiro | K52: Cartão | L52: Dinheiro | M52: Cartão | N52: Dinheiro | O52: Cartão | P52: Dinheiro | Q52: Cartão | R52: Dinheiro | S52: Cartão | T52: Dinheiro | U52: Cartão | V52: Dinheiro | W52: Cartão | X52: Dinheiro | Y52: Cartão | Z52: Dinheiro
B53: Aluguel | C53: 2439.58 | E53: 2555.95 | G53: 2368.8 | I53: 2281.44 | AA53: =SUM(C53:N53) -> 9645.77 | AB53: =AVERAGE(C53:AA53) -> 3858.308
B54: Combustível | C54: 194.05 | D54: 245.81 | E54: 316.94 | F54: 318.46 | G54: 420.05 | H54: 445.39 | I54: 287.71 | J54: 363.63 | AA54: =SUM(C54:N54) -> 2592.04 | AB54: =AVERAGE(C54:AA54) -> 576.00889
B55: Manutenção | D55: 1 | J55: 1 | AA55: =SUM(C55:N55) -> 2 | AB55: =AVERAGE(C55:AA55) -> 1.3333333
B56: Vistoria | AA56: =SUM(C56:N56) -> 0 | AB56: =AVERAGE(C56:AA56) -> 0
B57: Pedágios | AA57: =SUM(C57:N57) -> 0 | AB57: =AVERAGE(C57:AA57) -> 0
B58: Estacionamento | D58: 21 | F58: 12.95 | H58: 20 | I58: 40 | AA58: =SUM(C58:N58) -> 93.95 | AB58: =AVERAGE(C58:AA58) -> 37.58
B59: Multas | E59: 68.32 | AA59: =SUM(C59:N59) -> 68.32 | AB59: =AVERAGE(C59:AA59) -> 68.32
B60: Seguro | AA60: =SUM(C60:N60) -> 0 | AB60: =AVERAGE(C60:AA60) -> 0
B61: IPVA | AA61: =SUM(C61:N61) -> 0 | AB61: =AVERAGE(C61:AA61) -> 0
B62: Uber | AA62: =SUM(C62:N62) -> 0 | AB62: =AVERAGE(C62:AA62) -> 0
B63: Documentos | AA63: =SUM(C63:N63) -> 0 | AB63: =AVERAGE(C63:AA63) -> 0
AA64: =SUM(C64:N64) -> 0 | AB64: =AVERAGE(C64:AA64) -> 0
AA65: =SUM(C65:N65) -> 0 | AB65: =AVERAGE(C65:AA65) -> 0
B67: Saúde | C67: =SUM(C69:C74) -> 0 | D67: =SUM(D69:D74) -> 531.38 | E67: =SUM(E69:E74) -> 89.91 | F67: =SUM(F69:F74) -> 25.58 | G67: =SUM(G69:G74) -> 173.1 | H67: =SUM(H69:H74) -> 0 | I67: =SUM(I69:I74) -> 310.65 | J67: =SUM(J69:J74) -> 34.54 | ... N67: =SUM(N69:N74) -> 0 | O67: =sum(O69:P74) -> 0 | Q67: =sum(Q69:R74) -> 0 | S67: =sum(S69:T74) -> 0 | U67: =sum(U69:V74) -> 0 | W67: =sum(W69:X74) -> 0 | Y67: =sum(Y69:Z74) -> 0 | AA67: =SUM(AA69:AA74) -> 1165.16 | AB67: =AVERAGE(AB69:AB74) -> 123.06357
B68: Meio de Pagamento | C68: Cartão | D68: Dinheiro | E68: Cartão | F68: Dinheiro | G68: Cartão | H68: Dinheiro | I68: Cartão | J68: Dinheiro | K68: Cartão | L68: Dinheiro | M68: Cartão | N68: Dinheiro | O68: Cartão | P68: Dinheiro | Q68: Cartão | R68: Dinheiro | S68: Cartão | T68: Dinheiro | U68: Cartão | V68: Dinheiro | W68: Cartão | X68: Dinheiro | Y68: Cartão | Z68: Dinheiro
B69: Convênio Médico | AA69: =SUM(C69:N69) -> 0 | AB69: =AVERAGE(C69:AA69) -> 0
B70: Medicamentos | D70: 50.38 | E70: 21.59 | F70: 25.58 | G70: 104.8 | I70: 158.37 | J70: 34.54 | AA70: =SUM(C70:N70) -> 395.26 | AB70: =AVERAGE(C70:AA70) -> 112.93143
B71: Higiêne Pessoal | E71: 68.32 | G71: 68.3 | I71: 152.28 | AA71: =SUM(C71:N71) -> 288.9 | AB71: =AVERAGE(C71:AA71) -> 144.45
B72: Dentista | D72: 481 | AA72: =SUM(C72:N72) -> 481 | AB72: =AVERAGE(C72:AA72) -> 481
B73: Emergências | AA73: =SUM(C73:N73) -> 0 | AB73: =AVERAGE(C73:AA73) -> 0
AA74: =SUM(C74:N74) -> 0 | AB74: =AVERAGE(C74:AA74) -> 0
B76: Pessoal | C76: =SUM(C78:C85) -> 1794.11 | D76: =SUM(D78:D85) -> 1100.84 | E76: =SUM(E78:E85) -> 2174.74 | F76: =SUM(F78:F85) -> 503.58 | G76: =SUM(G78:G85) -> 794.74 | H76: =SUM(H78:H85) -> 895.55 | I76: =SUM(I78:I85) -> 2062.39 | J76: =SUM(J78:J85) -> 3048.33 | ... N76: =SUM(N78:N85) -> 0 | O76: =sum(O78:P85) -> 0 | Q76: =sum(Q78:R85) -> 0 | S76: =sum(S78:T85) -> 0 | U76: =sum(U78:V85) -> 0 | W76: =sum(W78:X85) -> 0 | Y76: =sum(Y78:Z85) -> 0 | AA76: =SUM(AA78:AA85) -> 12499.28 | AB76: =AVERAGE(AB78:AB83) -> 377.96569
B77: Meio de Pagamento | C77: Cartão | D77: Dinheiro | E77: Cartão | F77: Dinheiro | G77: Cartão | H77: Dinheiro | I77: Cartão | J77: Dinheiro | K77: Cartão | L77: Dinheiro | M77: Cartão | N77: Dinheiro | O77: Cartão | P77: Dinheiro | Q77: Cartão | R77: Dinheiro | S77: Cartão | T77: Dinheiro | U77: Cartão | V77: Dinheiro | W77: Cartão | X77: Dinheiro | Y77: Cartão | Z77: Dinheiro
B78: Academias / Esportes | AA78: =SUM(C78:N78) -> 0 | AB78: =AVERAGE(C78:AA78) -> 0
B79: Salão de Beleza | I79: 385 | AA79: =SUM(C79:N79) -> 385 | AB79: =AVERAGE(C79:AA79) -> 385
B80: Presentes | C80: 244.97 | D80: 189.97 | E80: 125 | G80: 125 | I80: 268.4 | J80: 133.85 | K80: 125 | AA80: =SUM(C80:N80) -> 1212.19 | AB80: =AVERAGE(C80:AA80) -> 303.0475
B81: Vestuário | C81: 1078.57 | E81: 858.68 | G81: 251.19 | I81: 550.8 | J81: 2000 | AA81: =SUM(C81:N81) -> 4739.24 | AB81: =AVERAGE(C81:AA81) -> 1579.7467
B82: Terapia / Tratamentos | AA82: =SUM(C82:N82) -> 0 | AB82: =AVERAGE(C82:AA82) -> 0
B83: Restaurante Trabalho | AA83: =SUM(C83:N83) -> 0 | AB83: =AVERAGE(C83:AA83) -> 0
B84: Cigarro | C84: 164.49 | D84: 588 | E84: 726.27 | F84: 393.5 | G84: 308.98 | H84: 630.95 | I84: 634.25 | J84: 783 | AA84: =SUM(C84:N84) -> 4229.44 | AB84: =AVERAGE(C84:AA84) -> 939.87556
B85: Cerveja | C85: 306.08 | D85: 322.87 | E85: 464.79 | F85: 110.08 | G85: 109.57 | H85: 264.6 | I85: 223.94 | J85: 131.48 | AA85: =SUM(C85:N85) -> 1933.41 | AB85: =AVERAGE(C85:AA85) -> 429.64667
B87: Dogs | C87: =SUM(C89:C93) -> 205 | D87: =SUM(D89:D93) -> 84.89 | E87: =SUM(E89:E93) -> 389.85 | F87: =SUM(F89:F93) -> 0 | G87: =SUM(G89:G93) -> 723.25 | H87: =SUM(H89:H93) -> 0 | I87: =SUM(I89:I93) -> 696.29 | J87: =SUM(J89:J93) -> 0 | ... N87: =SUM(N89:N93) -> 0 | O87: =sum(O89:P93) -> 0 | Q87: =sum(Q89:R93) -> 0 | S87: =sum(S89:T93) -> 0 | U87: =sum(U89:V93) -> 0 | W87: =sum(W89:X93) -> 0 | Y87: =sum(Y89:Z93) -> 0 | AA87: =SUM(AA89:AA93) -> 2099.28 | AB87: =AVERAGE(AB89:AB94) -> 219.3504
B88: Meio de Pagamento | C88: Cartão | D88: Dinheiro | E88: Cartão | F88: Dinheiro | G88: Cartão | H88: Dinheiro | I88: Cartão | J88: Dinheiro | K88: Cartão | L88: Dinheiro | M88: Cartão | N88: Dinheiro | O88: Cartão | P88: Dinheiro | Q88: Cartão | R88: Dinheiro | S88: Cartão | T88: Dinheiro | U88: Cartão | V88: Dinheiro | W88: Cartão | X88: Dinheiro | Y88: Cartão | Z88: Dinheiro
B89: Ração | E89: 116.95 | G89: 116.95 | AA89: =SUM(C89:N89) -> 233.9 | AB89: =AVERAGE(C89:AA89) -> 155.93333
B90: Banho e Tosa | C90: 205 | E90: 205 | G90: 184.5 | I90: 184.5 | AA90: =SUM(C90:N90) -> 779 | AB90: =AVERAGE(C90:AA90) -> 311.6
B91: Veterinário | G91: 365 | I91: 365 | AA91: =SUM(C91:N91) -> 730 | AB91: =AVERAGE(C91:AA91) -> 486.66667
B92: Assessórios / Brinquedos | D92: 84.89 | E92: 67.9 | G92: 56.8 | I92: 146.79 | AA92: =SUM(C92:N92) -> 356.38 | AB92: =AVERAGE(C92:AA92) -> 142.552
AA93: =SUM(C93:N93) -> 0 | AB93: =AVERAGE(C93:AA93) -> 0
B95: Lazer | C95: =SUM(C97:C101) -> 1201.4 | D95: =SUM(D97:D101) -> 608.84 | E95: =SUM(E97:E101) -> 740.39 | F95: =SUM(F97:F101) -> 336.75 | G95: =SUM(G97:G101) -> 681.91 | H95: =SUM(H97:H101) -> 173.77 | I95: =SUM(I97:I101) -> 1140.73 | J95: =SUM(J97:J101) -> 1496.91 | ... N95: =SUM(N97:N101) -> 0 | O95: =sum(O97:P101) -> 0 | Q95: =sum(Q97:R101) -> 0 | S95: =sum(S97:T101) -> 0 | U95: =sum(U97:V101) -> 0 | W95: =sum(W97:X101) -> 0 | Y95: =sum(Y97:Z101) -> 0 | AA95: =SUM(AA97:AA101) -> 6380.7 | AB95: =AVERAGE(AB97:AB102) -> 349.2449
B96: Meio de Pagamento | C96: Cartão | D96: Dinheiro | E96: Cartão | F96: Dinheiro | G96: Cartão | H96: Dinheiro | I96: Cartão | J96: Dinheiro | K96: Cartão | L96: Dinheiro | M96: Cartão | N96: Dinheiro | O96: Cartão | P96: Dinheiro | Q96: Cartão | R96: Dinheiro | S96: Cartão | T96: Dinheiro | U96: Cartão | V96: Dinheiro | W96: Cartão | X96: Dinheiro | Y96: Cartão | Z96: Dinheiro
B97: Restaurantes e Passeios | C97: 607.31 | D97: 467.69 | E97: 604.01 | F97: 336.75 | G97: 540.67 | H97: 173.77 | I97: 1115.23 | J97: 1414.21 | AA97: =SUM(C97:N97) -> 5259.64 | AB97: =AVERAGE(C97:AA97) -> 1168.8089
B98: Diversão Local | C98: 28 | D98: 20 | E98: 98.4 | G98: 68.4 | I98: 7.5 | J98: 11.9 | AA98: =SUM(C98:N98) -> 234.2 | AB98: =AVERAGE(C98:AA98) -> 66.914286
B99: Famílias e Amigos | D99: 121.15 | E99: 37.98 | G99: 72.84 | J99: 70.8 | AA99: =SUM(C99:N99) -> 302.77 | AB99: =AVERAGE(C99:AA99) -> 121.108
B100: Viagens | C100: 566.09 | I100: 18 | AA100: =SUM(C100:N100) -> 584.09 | AB100: =AVERAGE(C100:AA100) -> 389.39333
C101: =B101 | D101: =C101 | E101: =D101 | F101: =E101 | G101: =F101 | H101: =G101 | I101: =H101 | J101: =I101 | ... N101: =M101 | AA101: =SUM(C101:N101) -> 0 | AB101: =AVERAGE(C101:AA101) -> 0
B103: Despesas Financeiras | C103: =SUM(C105:C113) -> 0 | D103: =SUM(D105:D113) -> 4175.93 | E103: =SUM(E105:E113) -> 0 | F103: =SUM(F105:F113) -> 165.27 | G103: =SUM(G105:G113) -> 216.2 | H103: =SUM(H105:H113) -> 420.27 | I103: =SUM(I105:I113) -> -43.32 | J103: =SUM(J105:J113) -> 4334.47 | ... N103: =SUM(N105:N113) -> 0 | O103: =sum(O105:P113) -> 0 | Q103: =sum(Q105:R113) -> 0 | S103: =sum(S105:T113) -> 0 | U103: =sum(U105:V113) -> 0 | W103: =sum(W105:X113) -> 0 | Y103: =sum(Y105:Z113) -> 0 | AA103: =SUM(AA105:AA113) -> 6697.48 | AB103: =AVERAGE(AB105:AB113) -> 427.14907
B104: Meio de Pagamento | C104: Cartão | D104: Dinheiro | E104: Cartão | F104: Dinheiro | G104: Cartão | H104: Dinheiro | I104: Cartão | J104: Dinheiro | K104: Cartão | L104: Dinheiro | M104: Cartão | N104: Dinheiro | O104: Cartão | P104: Dinheiro | Q104: Cartão | R104: Dinheiro | S104: Cartão | T104: Dinheiro | U104: Cartão | V104: Dinheiro | W104: Cartão | X104: Dinheiro | Y104: Cartão | Z104: Dinheiro
B105: Taxas Bancárias | D105: 2000.95 | F105: 79.5 | G105: 198.84 | H105: 159.75 | J105: 141 | AA105: =SUM(C105:N105) -> 2580.04 | AB105: =AVERAGE(C105:AA105) -> 860.01333
B106: Saques | F106: 72.78 | I106: -43.32 | J106: 26.5 | AA106: =SUM(C106:N106) -> 55.96 | AB106: =AVERAGE(C106:AA106) -> 27.98
B107: Seguro de Vida | AA107: =SUM(C107:N107) -> 0 | AB107: =AVERAGE(C107:AA107) -> 0
B108: Imposto de Renda | AA108: =SUM(C108:N108) -> 0 | AB108: =AVERAGE(C108:AA108) -> 0
B109: Jogos Loteria | D109: 124 | AA109: =SUM(C109:N109) -> 124 | AB109: =AVERAGE(C109:AA109) -> 124
B110: Correios | AA110: =SUM(C110:N110) -> 0 | AB110: =AVERAGE(C110:AA110) -> 0
B111: Cartório | F111: 12.99 | AA111: =SUM(C111:N111) -> 12.99 | AB111: =AVERAGE(C111:AA111) -> 12.99
B112: Contador | D112: 684 | H112: 260.52 | J112: 1626.82 | AB112: =AVERAGE(C112:AA112) -> 857.11333
...
